Workbook

Sheet EVALUASI
A1: EVALUASI PER PEMBIMBING
A3: No | B3: Pembimbing | C3: Jumlah Pemagang | D3: Total Hari Kerja | E3: Total Hadir | F3: % Kehadiran | G3: Total Hari Terlambat | H3: % Tepat Waktu | I3: Tanpa Absen Pulang | J3: % Laporan Aktivitas | K3: Rata-rata Skor | L3: Predikat | M3: Skor Terendah | N3: Pemagang Skor Terendah | O3: key
A4: 1 | B4: =EVALUASI!D80 -> AHMAD JALALUDDIN BASYAR | C4: =COUNTIF(EVALUASI!$D$79:$D$132,$B4) -> 7 | D4: =SUMIFS(EVALUASI!$I$79:$I$132,EVALUASI!$D$79:$D$132,$B4) -> 408 | E4: =SUMIFS(EVALUASI!$J$79:$J$132,EVALUASI!$D$79:$D$132,$B4) -> 399 | F4: =IFERROR(E4/D4,0) -> 0.97794118 | G4: =SUMIFS(EVALUASI!$M$79:$M$132,EVALUASI!$D$79:$D$132,$B4) -> 64 | H4: =IFERROR(1-G4/SUMIFS(DETAIL!$M$2:$M$137,DETAIL!$C$2:$C$137,$B4),0) -> 0.84615385 | I4: =SUMIFS(EVALUASI!$P$79:$P$132,EVALUASI!$D$79:$D$132,$B4) -> 20 | J4: =IFERROR(SUMIFS(DETAIL!$Q$2:$Q$137,DETAIL!$C$2:$C$137,$B4)/SUMIFS(DETAIL!$M$2:$M$137,DETAIL!$C$2:$C$137,$B4),0) -> 0.87980769 | K4: =ROUND(AVERAGEIF(EVALUASI!$D$79:$D$132,$B4,EVALUASI!$W$79:$W$132),1) -> 85.1 | L4: =IF(K4>=100*SUMMARY!$C$14,"Sangat Baik",IF(K4>=100*SUMMARY!$C$15,"Baik",IF(K4>=100*SUMMARY!$C$16,"Cukup","Perlu Pembinaan"))) -> Baik | M4: =MIN(EVALUASI!$W$80:$W$86) -> 65.4 | N4: =INDEX(EVALUASI!$C$80:$C$86,MATCH(M4,EVALUASI!$W$80:$W$86,0)) -> WIDIYA DESY MAWAR SARI | O4: =K4-ROW()/100000 -> 85.09996
A5: 2 | B5: =EVALUASI!D88 -> AKHMAT ABIDIN | C5: =COUNTIF(EVALUASI!$D$79:$D$132,$B5) -> 1 | D5: =SUMIFS(EVALUASI!$I$79:$I$132,EVALUASI!$D$79:$D$132,$B5) -> 52 | E5: =SUMIFS(EVALUASI!$J$79:$J$132,EVALUASI!$D$79:$D$132,$B5) -> 48 | F5: =IFERROR(E5/D5,0) -> 0.92307692 | G5: =SUMIFS(EVALUASI!$M$79:$M$132,EVALUASI!$D$79:$D$132,$B5) -> 3 | H5: =IFERROR(1-G5/SUMIFS(DETAIL!$M$2:$M$137,DETAIL!$C$2:$C$137,$B5),0) -> 0.94444444 | I5: =SUMIFS(EVALUASI!$P$79:$P$132,EVALUASI!$D$79:$D$132,$B5) -> 5 | J5: =IFERROR(SUMIFS(DETAIL!$Q$2:$Q$137,DETAIL!$C$2:$C$137,$B5)/SUMIFS(DETAIL!$M$2:$M$137,DETAIL!$C$2:$C$137,$B5),0) -> 0.94444444 | K5: =ROUND(AVERAGEIF(EVALUASI!$D$79:$D$132,$B5,EVALUASI!$W$79:$W$132),1) -> 95.5 | L5: =IF(K5>=100*SUMMARY!$C$14,"Sangat Baik",IF(K5>=100*SUMMARY!$C$15,"Baik",IF(K5>=100*SUMMARY!$C$16,"Cukup","Perlu Pembinaan"))) -> Sangat Baik | M5: =MIN(EVALUASI!$W$88:$W$88) -> 95.5 | N5: =INDEX(EVALUASI!$C$88:$C$88,MATCH(M5,EVALUASI!$W$88:$W$88,0)) -> NURIKA AMELIA ROSYIDAH | O5: =K5-ROW()/100000 -> 95.49995
A6: 3 | B6: =EVALUASI!D90 -> ARIFANO KUSUMA BAYU | C6: =COUNTIF(EVALUASI!$D$79:$D$132,$B6) -> 1 | D6: =SUMIFS(EVALUASI!$I$79:$I$132,EVALUASI!$D$79:$D$132,$B6) -> 75 | E6: =SUMIFS(EVALUASI!$J$79:$J$132,EVALUASI!$D$79:$D$132,$B6) -> 71 | F6: =IFERROR(E6/D6,0) -> 0.94666667 | G6: =SUMIFS(EVALUASI!$M$79:$M$132,EVALUASI!$D$79:$D$132,$B6) -> 28 | H6: =IFERROR(1-G6/SUMIFS(DETAIL!$M$2:$M$137,DETAIL!$C$2:$C$137,$B6),0) -> 0.63636364 | I6: =SUMIFS(EVALUASI!$P$79:$P$132,EVALUASI!$D$79:$D$132,$B6) -> 3 | J6: =IFERROR(SUMIFS(DETAIL!$Q$2:$Q$137,DETAIL!$C$2:$C$137,$B6)/SUMIFS(DETAIL!$M$2:$M$137,DETAIL!$C$2:$C$137,$B6),0) -> 0.98701299 | K6: =ROUND(AVERAGEIF(EVALUASI!$D$79:$D$132,$B6,EVALUASI!$W$79:$W$132),1) -> 90.9 | L6: =IF(K6>=100*SUMMARY!$C$14,"Sangat Baik",IF(K6>=100*SUMMARY!$C$15,"Baik",IF(K6>=100*SUMMARY!$C$16,"Cukup","Perlu Pembinaan"))) -> Sangat Baik | M6: =MIN(EVALUASI!$W$90:$W$90) -> 90.9 | N6: =INDEX(EVALUASI!$C$90:$C$90,MATCH(M6,EVALUASI!$W$90:$W$90,0)) -> JANU PRASTYO | O6: =K6-ROW()/100000 -> 90.89994
A7: 4 | B7: =EVALUASI!D92 -> DIAN RIZKA SARI | C7: =COUNTIF(EVALUASI!$D$79:$D$132,$B7) -> 2 | D7: =SUMIFS(EVALUASI!$I$79:$I$132,EVALUASI!$D$79:$D$132,$B7) -> 65 | E7: =SUMIFS(EVALUASI!$J$79:$J$132,EVALUASI!$D$79:$D$132,$B7) -> 58 | F7: =IFERROR(E7/D7,0) -> 0.89230769 | G7: =SUMIFS(EVALUASI!$M$79:$M$132,EVALUASI!$D$79:$D$132,$B7) -> 0 | H7: =IFERROR(1-G7/SUMIFS(DETAIL!$M$2:$M$137,DETAIL!$C$2:$C$137,$B7),0) -> 1 | I7: =SUMIFS(EVALUASI!$P$79:$P$132,EVALUASI!$D$79:$D$132,$B7) -> 3 | J7: =IFERROR(SUMIFS(DETAIL!$Q$2:$Q$137,DETAIL!$C$2:$C$137,$B7)/SUMIFS(DETAIL!$M$2:$M$137,DETAIL!$C$2:$C$137,$B7),0) -> 0.98275862 | K7: =ROUND(AVERAGEIF(EVALUASI!$D$79:$D$132,$B7,EVALUASI!$W$79:$W$132),1) -> 81.4 | L7: =IF(K7>=100*SUMMARY!$C$14,"Sangat Baik",IF(K7>=100*SUMMARY!$C$15,"Baik",IF(K7>=100*SUMMARY!$C$16,"Cukup","Perlu Pembinaan"))) -> Baik | M7: =MIN(EVALUASI!$W$92:$W$93) -> 81.3 | N7: =INDEX(EVALUASI!$C$92:$C$93,MATCH(M7,EVALUASI!$W$92:$W$93,0)) -> NIKEN AURELIA SAPUTRI | O7: =K7-ROW()/100000 -> 81.39993
A8: 5 | B8: =EVALUASI!D95 -> DWI SULIASTARI | C8: =COUNTIF(EVALUASI!$D$79:$D$132,$B8) -> 2 | D8: =SUMIFS(EVALUASI!$I$79:$I$132,EVALUASI!$D$79:$D$132,$B8) -> 148 | E8: =SUMIFS(EVALUASI!$J$79:$J$132,EVALUASI!$D$79:$D$132,$B8) -> 138 | F8: =IFERROR(E8/D8,0) -> 0.93243243 | G8: =SUMIFS(EVALUASI!$M$79:$M$132,EVALUASI!$D$79:$D$132,$B8) -> 7 | H8: =IFERROR(1-G8/SUMIFS(DETAIL!$M$2:$M$137,DETAIL!$C$2:$C$137,$B8),0) -> 0.94927536 | I8: =SUMIFS(EVALUASI!$P$79:$P$132,EVALUASI!$D$79:$D$132,$B8) -> 6 | J8: =IFERROR(SUMIFS(DETAIL!$Q$2:$Q$137,DETAIL!$C$2:$C$137,$B8)/SUMIFS(DETAIL!$M$2:$M$137,DETAIL!$C$2:$C$137,$B8),0) -> 0.95652174 | K8: =ROUND(AVERAGEIF(EVALUASI!$D$79:$D$132,$B8,EVALUASI!$W$79:$W$132),1) -> 80.4 | L8: =IF(K8>=100*SUMMARY!$C$14,"Sangat Baik",IF(K8>=100*SUMMARY!$C$15,"Baik",IF(K8>=100*SUMMARY!$C$16,"Cukup","Perlu Pembinaan"))) -> Baik | M8: =MIN(EVALUASI!$W$95:$W$96) -> 77.7 | N8: =INDEX(EVALUASI!$C$95:$C$96,MATCH(M8,EVALUASI!$W$95:$W$96,0)) -> EKA PUTRI FEBRIANTI | O8: =K8-ROW()/100000 -> 80.39992
A9: 6 | B9: =EVALUASI!D98 -> ELFANO RANGGA PRATAMA | C9: =COUNTIF(EVALUASI!$D$79:$D$132,$B9) -> 1 | D9: =SUMIFS(EVALUASI!$I$79:$I$132,EVALUASI!$D$79:$D$132,$B9) -> 75 | E9: =SUMIFS(EVALUASI!$J$79:$J$132,EVALUASI!$D$79:$D$132,$B9) -> 70 | F9: =IFERROR(E9/D9,0) -> 0.93333333 | G9: =SUMIFS(EVALUASI!$M$79:$M$132,EVALUASI!$D$79:$D$132,$B9) -> 59 | H9: =IFERROR(1-G9/SUMIFS(DETAIL!$M$2:$M$137,DETAIL!$C$2:$C$137,$B9),0) -> 0.37234043 | I9: =SUMIFS(EVALUASI!$P$79:$P$132,EVALUASI!$D$79:$D$132,$B9) -> 1 | J9: =IFERROR(SUMIFS(DETAIL!$Q$2:$Q$137,DETAIL!$C$2:$C$137,$B9)/SUMIFS(DETAIL!$M$2:$M$137,DETAIL!$C$2:$C$137,$B9),0) -> 0.91489362 | K9: =ROUND(AVERAGEIF(EVALUASI!$D$79:$D$132,$B9,EVALUASI!$W$79:$W$132),1) -> 74.5 | L9: =IF(K9>=100*SUMMARY!$C$14,"Sangat Baik",IF(K9>=100*SUMMARY!$C$15,"Baik",IF(K9>=100*SUMMARY!$C$16,"Cukup","Perlu Pembinaan"))) -> Cukup | M9: =MIN(EVALUASI!$W$98:$W$98) -> 74.5 | N9: =INDEX(EVALUASI!$C$98:$C$98,MATCH(M9,EVALUASI!$W$98:$W$98,0)) -> FETI FATMAWATI | O9: =K9-ROW()/100000 -> 74.49991
A10: 7 | B10: =EVALUASI!D100 -> ENDAH YUNIA SRI WINDARI | C10: =COUNTIF(EVALUASI!$D$79:$D$132,$B10) -> 2 | D10: =SUMIFS(EVALUASI!$I$79:$I$132,EVALUASI!$D$79:$D$132,$B10) -> 72 | E10: =SUMIFS(EVALUASI!$J$79:$J$132,EVALUASI!$D$79:$D$132,$B10) -> 68 | F10: =IFERROR(E10/D10,0) -> 0.94444444 | G10: =SUMIFS(EVALUASI!$M$79:$M$132,EVALUASI!$D$79:$D$132,$B10) -> 2 | H10: =IFERROR(1-G10/SUMIFS(DETAIL!$M$2:$M$137,DETAIL!$C$2:$C$137,$B10),0) -> 0.97058824 | I10: =SUMIFS(EVALUASI!$P$79:$P$132,EVALUASI!$D$79:$D$132,$B10) -> 5 | J10: =IFERROR(SUMIFS(DETAIL!$Q$2:$Q$137,DETAIL!$C$2:$C$137,$B10)/SUMIFS(DETAIL!$M$2:$M$137,DETAIL!$C$2:$C$137,$B10),0) -> 1 | K10: =ROUND(AVERAGEIF(EVALUASI!$D$79:$D$132,$B10,EVALUASI!$W$79:$W$132),1) -> 97.8 | L10: =IF(K10>=100*SUMMARY!$C$14,"Sangat Baik",IF(K10>=100*SUMMARY!$C$15,"Baik",IF(K10>=100*SUMMARY!$C$16,"Cukup","Perlu Pembinaan"))) -> Sangat Baik | M10: =MIN(EVALUASI!$W$100:$W$101) -> 96.9 | N10: =INDEX(EVALUASI!$C$100:$C$101,MATCH(M10,EVALUASI!$W$100:$W$101,0)) -> AHMAD NOVAN JUNIARDY | O10: =K10-ROW()/100000 -> 97.7999
A11: 8 | B11: =EVALUASI!D103 -> FETI MUBAIYINI | C11: =COUNTIF(EVALUASI!$D$79:$D$132,$B11) -> 2 | D11: =SUMIFS(EVALUASI!$I$79:$I$132,EVALUASI!$D$79:$D$132,$B11) -> 90 | E11: =SUMIFS(EVALUASI!$J$79:$J$132,EVALUASI!$D$79:$D$132,$B11) -> 85 | F11: =IFERROR(E11/D11,0) -> 0.94444444 | G11: =SUMIFS(EVALUASI!$M$79:$M$132,EVALUASI!$D$79:$D$132,$B11) -> 3 | H11: =IFERROR(1-G11/SUMIFS(DETAIL!$M$2:$M$137,DETAIL!$C$2:$C$137,$B11),0) -> 0.96470588 | I11: =SUMIFS(EVALUASI!$P$79:$P$132,EVALUASI!$D$79:$D$132,$B11) -> 8 | J11: =IFERROR(SUMIFS(DETAIL!$Q$2:$Q$137,DETAIL!$C$2:$C$137,$B11)/SUMIFS(DETAIL!$M$2:$M$137,DETAIL!$C$2:$C$137,$B11),0) -> 0.95294118 | K11: =ROUND(AVERAGEIF(EVALUASI!$D$79:$D$132,$B11,EVALUASI!$W$79:$W$132),1) -> 84.9 | L11: =IF(K11>=100*SUMMARY!$C$14,"Sangat Baik",IF(K11>=100*SUMMARY!$C$15,"Baik",IF(K11>=100*SUMMARY!$C$16,"Cukup","Perlu Pembinaan"))) -> Baik | M11: =MIN(EVALUASI!$W$103:$W$104) -> 76.7 | N11: =INDEX(EVALUASI!$C$103:$C$104,MATCH(M11,EVALUASI!$W$103:$W$104,0)) -> SYACHIRA FARA NABILA | O11: =K11-ROW()/100000 -> 84.89989
A12: 9 | B12: =EVALUASI!D106 -> GANANG MUSYAFFA FAHMI | C12: =COUNTIF(EVALUASI!$D$79:$D$132,$B12) -> 1 | D12: =SUMIFS(EVALUASI!$I$79:$I$132,EVALUASI!$D$79:$D$132,$B12) -> 75 | E12: =SUMIFS(EVALUASI!$J$79:$J$132,EVALUASI!$D$79:$D$132,$B12) -> 71 | F12: =IFERROR(E12/D12,0) -> 0.94666667 | G12: =SUMIFS(EVALUASI!$M$79:$M$132,EVALUASI!$D$79:$D$132,$B12) -> 0 | H12: =IFERROR(1-G12/SUMIFS(DETAIL!$M$2:$M$137,DETAIL!$C$2:$C$137,$B12),0) -> 1 | I12: =SUMIFS(EVALUASI!$P$79:$P$132,EVALUASI!$D$79:$D$132,$B12) -> 5 | J12: =IFERROR(SUMIFS(DETAIL!$Q$2:$Q$137,DETAIL!$C$2:$C$137,$B12)/SUMIFS(DETAIL!$M$2:$M$137,DETAIL!$C$2:$C$137,$B12),0) -> 0.97368421 | K12: =ROUND(AVERAGEIF(EVALUASI!$D$79:$D$132,$B12,EVALUASI!$W$79:$W$132),1) -> 97.9 | L12: =IF(K12>=100*SUMMARY!$C$14,"Sangat Baik",IF(K12>=100*SUMMARY!$C$15,"Baik",IF(K12>=100*SUMMARY!$C$16,"Cukup","Perlu Pembinaan"))) -> Sangat Baik | M12: =MIN(EVALUASI!$W$106:$W$106) -> 97.9 | N12: =INDEX(EVALUASI!$C$106:$C$106,MATCH(M12,EVALUASI!$W$106:$W$106,0)) -> SELVI NURUL HASANAH | O12: =K12-ROW()/100000 -> 97.89988
A13: 10 | B13: =EVALUASI!D108 -> HASKIN AVIONATA | C13: =COUNTIF(EVALUASI!$D$79:$D$132,$B13) -> 1 | D13: =SUMIFS(EVALUASI!$I$79:$I$132,EVALUASI!$D$79:$D$132,$B13) -> 75 | E13: =SUMIFS(EVALUASI!$J$79:$J$132,EVALUASI!$D$79:$D$132,$B13) -> 64 | F13: =IFERROR(E13/D13,0) -> 0.85333333 | G13: =SUMIFS(EVALUASI!$M$79:$M$132,EVALUASI!$D$79:$D$132,$B13) -> 17 | H13: =IFERROR(1-G13/SUMIFS(DETAIL!$M$2:$M$137,DETAIL!$C$2:$C$137,$B13),0) -> 0.73846154 | I13: =SUMIFS(EVALUASI!$P$79:$P$132,EVALUASI!$D$79:$D$132,$B13) -> 3 | J13: =IFERROR(SUMIFS(DETAIL!$Q$2:$Q$137,DETAIL!$C$2:$C$137,$B13)/SUMIFS(DETAIL!$M$2:$M$137,DETAIL!$C$2:$C$137,$B13),0) -> 0.96923077 | K13: =ROUND(AVERAGEIF(EVALUASI!$D$79:$D$132,$B13,EVALUASI!$W$79:$W$132),1) -> 78.1 | L13: =IF(K13>=100*SUMMARY!$C$14,"Sangat Baik",IF(K13>=100*SUMMARY!$C$15,"Baik",IF(K13>=100*SUMMARY!$C$16,"Cukup","Perlu Pembinaan"))) -> Cukup | M13: =MIN(EVALUASI!$W$108:$W$108) -> 78.1 | N13: =INDEX(EVALUASI!$C$108:$C$108,MATCH(M13,EVALUASI!$W$108:$W$108,0)) -> FARREL ALWIN RAHMADHAN | O13: =K13-ROW()/100000 -> 78.09987
A14: 11 | B14: =EVALUASI!D110 -> IMAM SUBEKTI | C14: =COUNTIF(EVALUASI!$D$79:$D$132,$B14) -> 1 | D14: =SUMIFS(EVALUASI!$I$79:$I$132,EVALUASI!$D$79:$D$132,$B14) -> 20 | E14: =SUMIFS(EVALUASI!$J$79:$J$132,EVALUASI!$D$79:$D$132,$B14) -> 15 | F14: =IFERROR(E14/D14,0) -> 0.75 | G14: =SUMIFS(EVALUASI!$M$79:$M$132,EVALUASI!$D$79:$D$132,$B14) -> 8 | H14: =IFERROR(1-G14/SUMIFS(DETAIL!$M$2:$M$137,DETAIL!$C$2:$C$137,$B14),0) -> 0.46666667 | I14: =SUMIFS(EVALUASI!$P$79:$P$132,EVALUASI!$D$79:$D$132,$B14) -> 12 | J14: =IFERROR(SUMIFS(DETAIL!$Q$2:$Q$137,DETAIL!$C$2:$C$137,$B14)/SUMIFS(DETAIL!$M$2:$M$137,DETAIL!$C$2:$C$137,$B14),0) -> 0 | K14: =ROUND(AVERAGEIF(EVALUASI!$D$79:$D$132,$B14,EVALUASI!$W$79:$W$132),1) -> 31.8 | L14: =IF(K14>=100*SUMMARY!$C$14,"Sangat Baik",IF(K14>=100*SUMMARY!$C$15,"Baik",IF(K14>=100*SUMMARY!$C$16,"Cukup","Perlu Pembinaan"))) -> Perlu Pembinaan | M14: =MIN(EVALUASI!$W$110:$W$110) -> 31.8 | N14: =INDEX(EVALUASI!$C$110:$C$110,MATCH(M14,EVALUASI!$W$110:$W$110,0)) -> MASDUQI MUHAMMAD | O14: =K14-ROW()/100000 -> 31.79986
A15: 12 | B15: =EVALUASI!D112 -> IMANIAR PUTRI UTAMI | C15: =COUNTIF(EVALUASI!$D$79:$D$132,$B15) -> 1 | D15: =SUMIFS(EVALUASI!$I$79:$I$132,EVALUASI!$D$79:$D$132,$B15) -> 13 | E15: =SUMIFS(EVALUASI!$J$79:$J$132,EVALUASI!$D$79:$D$132,$B15) -> 13 | F15: =IFERROR(E15/D15,0) -> 1 | G15: =SUMIFS(EVALUASI!$M$79:$M$132,EVALUASI!$D$79:$D$132,$B15) -> 1 | H15: =IFERROR(1-G15/SUMIFS(DETAIL!$M$2:$M$137,DETAIL!$C$2:$C$137,$B15),0) -> 0.92307692 | I15: =SUMIFS(EVALUASI!$P$79:$P$132,EVALUASI!$D$79:$D$132,$B15) -> 0 | J15: =IFERROR(SUMIFS(DETAIL!$Q$2:$Q$137,DETAIL!$C$2:$C$137,$B15)/SUMIFS(DETAIL!$M$2:$M$137,DETAIL!$C$2:$C$137,$B15),0) -> 1 | K15: =ROUND(AVERAGEIF(EVALUASI!$D$79:$D$132,$B15,EVALUASI!$W$79:$W$132),1) -> 91.8 | L15: =IF(K15>=100*SUMMARY!$C$14,"Sangat Baik",IF(K15>=100*SUMMARY!$C$15,"Baik",IF(K15>=100*SUMMARY!$C$16,"Cukup","Perlu Pembinaan"))) -> Sangat Baik | M15: =MIN(EVALUASI!$W$112:$W$112) -> 91.8 | N15: =INDEX(EVALUASI!$C$112:$C$112,MATCH(M15,EVALUASI!$W$112:$W$112,0)) -> CITRA ANGGRAINI | O15: =K15-ROW()/100000 -> 91.79985
A16: 13 | B16: =EVALUASI!D114 -> M. RIZAD FAHRURI | C16: =COUNTIF(EVALUASI!$D$79:$D$132,$B16) -> 1 | D16: =SUMIFS(EVALUASI!$I$79:$I$132,EVALUASI!$D$79:$D$132,$B16) -> 75 | E16: =SUMIFS(EVALUASI!$J$79:$J$132,EVALUASI!$D$79:$D$132,$B16) -> 72 | F16: =IFERROR(E16/D16,0) -> 0.96 | G16: =SUMIFS(EVALUASI!$M$79:$M$132,EVALUASI!$D$79:$D$132,$B16) -> 0 | H16: =IFERROR(1-G16/SUMIFS(DETAIL!$M$2:$M$137,DETAIL!$C$2:$C$137,$B16),0) -> 1 | I16: =SUMIFS(EVALUASI!$P$79:$P$132,EVALUASI!$D$79:$D$132,$B16) -> 3 | J16: =IFERROR(SUMIFS(DETAIL!$Q$2:$Q$137,DETAIL!$C$2:$C$137,$B16)/SUMIFS(DETAIL!$M$2:$M$137,DETAIL!$C$2:$C$137,$B16),0) -> 0.98717949 | K16: =ROUND(AVERAGEIF(EVALUASI!$D$79:$D$132,$B16,EVALUASI!$W$79:$W$132),1) -> 98.5 | L16: =IF(K16>=100*SUMMARY!$C$14,"Sangat Baik",IF(K16>=100*SUMMARY!$C$15,"Baik",IF(K16>=100*SUMMARY!$C$16,"Cukup","Perlu Pembinaan"))) -> Sangat Baik | M16: =MIN(EVALUASI!$W$114:$W$114) -> 98.5 | N16: =INDEX(EVALUASI!$C$114:$C$114,MATCH(M16,EVALUASI!$W$114:$W$114,0)) -> KHOFIFATUNNABILAH | O16: =K16-ROW()/100000 -> 98.49984
A17: 14 | B17: =EVALUASI!D116 -> MOH. AGUS EFENDI | C17: =COUNTIF(EVALUASI!$D$79:$D$132,$B17) -> 2 | D17: =SUMIFS(EVALUASI!$I$79:$I$132,EVALUASI!$D$79:$D$132,$B17) -> 134 | E17: =SUMIFS(EVALUASI!$J$79:$J$132,EVALUASI!$D$79:$D$132,$B17) -> 128 | F17: =IFERROR(E17/D17,0) -> 0.95522388 | G17: =SUMIFS(EVALUASI!$M$79:$M$132,EVALUASI!$D$79:$D$132,$B17) -> 3 | H17: =IFERROR(1-G17/SUMIFS(DETAIL!$M$2:$M$137,DETAIL!$C$2:$C$137,$B17),0) -> 0.97794118 | I17: =SUMIFS(EVALUASI!$P$79:$P$132,EVALUASI!$D$79:$D$132,$B17) -> 3 | J17: =IFERROR(SUMIFS(DETAIL!$Q$2:$Q$137,DETAIL!$C$2:$C$137,$B17)/SUMIFS(DETAIL!$M$2:$M$137,DETAIL!$C$2:$C$137,$B17),0) -> 0.99264706 | K17: =ROUND(AVERAGEIF(EVALUASI!$D$79:$D$132,$B17,EVALUASI!$W$79:$W$132),1) -> 92.3 | L17: =IF(K17>=100*SUMMARY!$C$14,"Sangat Baik",IF(K17>=100*SUMMARY!$C$15,"Baik",IF(K17>=100*SUMMARY!$C$16,"Cukup","Perlu Pembinaan"))) -> Sangat Baik | M17: =MIN(EVALUASI!$W$116:$W$117) -> 85.6 | N17: =INDEX(EVALUASI!$C$116:$C$117,MATCH(M17,EVALUASI!$W$116:$W$117,0)) -> MUHAMMAD FATCHUL ALAM | O17: =K17-ROW()/100000 -> 92.29983
A18: 15 | B18: =EVALUASI!D119 -> MUHAMMAD SADULLAH | C18: =COUNTIF(EVALUASI!$D$79:$D$132,$B18) -> 1 | D18: =SUMIFS(EVALUASI!$I$79:$I$132,EVALUASI!$D$79:$D$132,$B18) -> 38 | E18: =SUMIFS(EVALUASI!$J$79:$J$132,EVALUASI!$D$79:$D$132,$B18) -> 38 | F18: =IFERROR(E18/D18,0) -> 1 | G18: =SUMIFS(EVALUASI!$M$79:$M$132,EVALUASI!$D$79:$D$132,$B18) -> 7 | H18: =IFERROR(1-G18/SUMIFS(DETAIL!$M$2:$M$137,DETAIL!$C$2:$C$137,$B18),0) -> 0.83333333 | I18: =SUMIFS(EVALUASI!$P$79:$P$132,EVALUASI!$D$79:$D$132,$B18) -> 2 | J18: =IFERROR(SUMIFS(DETAIL!$Q$2:$Q$137,DETAIL!$C$2:$C$137,$B18)/SUMIFS(DETAIL!$M$2:$M$137,DETAIL!$C$2:$C$137,$B18),0) -> 0.95238095 | K18: =ROUND(AVERAGEIF(EVALUASI!$D$79:$D$132,$B18,EVALUASI!$W$79:$W$132),1) -> 84.5 | L18: =IF(K18>=100*SUMMARY!$C$14,"Sangat Baik",IF(K18>=100*SUMMARY!$C$15,"Baik",IF(K18>=100*SUMMARY!$C$16,"Cukup","Perlu Pembinaan"))) -> Baik | M18: =MIN(EVALUASI!$W$119:$W$119) -> 84.5 | N18: =INDEX(EVALUASI!$C$119:$C$119,MATCH(M18,EVALUASI!$W$119:$W$119,0)) -> ASA AGHNIA ZAHIDA | O18: =K18-ROW()/100000 -> 84.49982
A19: 16 | B19: =EVALUASI!D121 -> SITI MUJAYANAH | C19: =COUNTIF(EVALUASI!$D$79:$D$132,$B19) -> 4 | D19: =SUMIFS(EVALUASI!$I$79:$I$132,EVALUASI!$D$79:$D$132,$B19) -> 166 | E19: =SUMIFS(EVALUASI!$J$79:$J$132,EVALUASI!$D$79:$D$132,$B19) -> 160 | F19: =IFERROR(E19/D19,0) -> 0.96385542 | G19: =SUMIFS(EVALUASI!$M$79:$M$132,EVALUASI!$D$79:$D$132,$B19) -> 6 | H19: =IFERROR(1-G19/SUMIFS(DETAIL!$M$2:$M$137,DETAIL!$C$2:$C$137,$B19),0) -> 0.96363636 | I19: =SUMIFS(EVALUASI!$P$79:$P$132,EVALUASI!$D$79:$D$132,$B19) -> 11 | J19: =IFERROR(SUMIFS(DETAIL!$Q$2:$Q$137,DETAIL!$C$2:$C$137,$B19)/SUMIFS(DETAIL!$M$2:$M$137,DETAIL!$C$2:$C$137,$B19),0) -> 0.95757576 | K19: =ROUND(AVERAGEIF(EVALUASI!$D$79:$D$132,$B19,EVALUASI!$W$79:$W$132),1) -> 90.8 | L19: =IF(K19>=100*SUMMARY!$C$14,"Sangat Baik",IF(K19>=100*SUMMARY!$C$15,"Baik",IF(K19>=100*SUMMARY!$C$16,"Cukup","Perlu Pembinaan"))) -> Sangat Baik | M19: =MIN(EVALUASI!$W$121:$W$124) -> 77.9 | N19: =INDEX(EVALUASI!$C$121:$C$124,MATCH(M19,EVALUASI!$W$121:$W$124,0)) -> RIZAL AKBAR ARDIANSYAH | O19: =K19-ROW()/100000 -> 90.79981
A20: 17 | B20: =EVALUASI!D126 -> TRI HARTANTO | C20: =COUNTIF(EVALUASI!$D$79:$D$132,$B20) -> 1 | D20: =SUMIFS(EVALUASI!$I$79:$I$132,EVALUASI!$D$79:$D$132,$B20) -> 13 | E20: =SUMIFS(EVALUASI!$J$79:$J$132,EVALUASI!$D$79:$D$132,$B20) -> 9 | F20: =IFERROR(E20/D20,0) -> 0.69230769 | G20: =SUMIFS(EVALUASI!$M$79:$M$132,EVALUASI!$D$79:$D$132,$B20) -> 2 | H20: =IFERROR(1-G20/SUMIFS(DETAIL!$M$2:$M$137,DETAIL!$C$2:$C$137,$B20),0) -> 0.77777778 | I20: =SUMIFS(EVALUASI!$P$79:$P$132,EVALUASI!$D$79:$D$132,$B20) -> 3 | J20: =IFERROR(SUMIFS(DETAIL!$Q$2:$Q$137,DETAIL!$C$2:$C$137,$B20)/SUMIFS(DETAIL!$M$2:$M$137,DETAIL!$C$2:$C$137,$B20),0) -> 0.77777778 | K20: =ROUND(AVERAGEIF(EVALUASI!$D$79:$D$132,$B20,EVALUASI!$W$79:$W$132),1) -> 67.3 | L20: =IF(K20>=100*SUMMARY!$C$14,"Sangat Baik",IF(K20>=100*SUMMARY!$C$15,"Baik",IF(K20>=100*SUMMARY!$C$16,"Cukup","Perlu Pembinaan"))) -> Perlu Pembinaan | M20: =MIN(EVALUASI!$W$126:$W$126) -> 67.3 | N20: =INDEX(EVALUASI!$C$126:$C$126,MATCH(M20,EVALUASI!$W$126:$W$126,0)) -> ALFINA ZAKYA ULA | O20: =K20-ROW()/100000 -> 67.2998
A21: 18 | B21: =EVALUASI!D128 -> WATIN UTARI | C21: =COUNTIF(EVALUASI!$D$79:$D$132,$B21) -> 1 | D21: =SUMIFS(EVALUASI!$I$79:$I$132,EVALUASI!$D$79:$D$132,$B21) -> 7 | E21: =SUMIFS(EVALUASI!$J$79:$J$132,EVALUASI!$D$79:$D$132,$B21) -> 6 | F21: =IFERROR(E21/D21,0) -> 0.85714286 | G21: =SUMIFS(EVALUASI!$M$79:$M$132,EVALUASI!$D$79:$D$132,$B21) -> 1 | H21: =IFERROR(1-G21/SUMIFS(DETAIL!$M$2:$M$137,DETAIL!$C$2:$C$137,$B21),0) -> 0.83333333 | I21: =SUMIFS(EVALUASI!$P$79:$P$132,EVALUASI!$D$79:$D$132,$B21) -> 0 | J21: =IFERROR(SUMIFS(DETAIL!$Q$2:$Q$137,DETAIL!$C$2:$C$137,$B21)/SUMIFS(DETAIL!$M$2:$M$137,DETAIL!$C$2:$C$137,$B21),0) -> 1 | K21: =ROUND(AVERAGEIF(EVALUASI!$D$79:$D$132,$B21,EVALUASI!$W$79:$W$132),1) -> 92.4 | L21: =IF(K21>=100*SUMMARY!$C$14,"Sangat Baik",IF(K21>=100*SUMMARY!$C$15,"Baik",IF(K21>=100*SUMMARY!$C$16,"Cukup","Perlu Pembinaan"))) -> Sangat Baik | M21: =MIN(EVALUASI!$W$128:$W$128) -> 92.4 | N21: =INDEX(EVALUASI!$C$128:$C$128,MATCH(M21,EVALUASI!$W$128:$W$128,0)) -> AMELIA KURNIA FITRI | O21: =K21-ROW()/100000 -> 92.39979
A22: 19 | B22: =EVALUASI!D130 -> WAWAN SETIAWAN | C22: =COUNTIF(EVALUASI!$D$79:$D$132,$B22) -> 1 | D22: =SUMIFS(EVALUASI!$I$79:$I$132,EVALUASI!$D$79:$D$132,$B22) -> 75 | E22: =SUMIFS(EVALUASI!$J$79:$J$132,EVALUASI!$D$79:$D$132,$B22) -> 75 | F22: =IFERROR(E22/D22,0) -> 1 | G22: =SUMIFS(EVALUASI!$M$79:$M$132,EVALUASI!$D$79:$D$132,$B22) -> 12 | H22: =IFERROR(1-G22/SUMIFS(DETAIL!$M$2:$M$137,DETAIL!$C$2:$C$137,$B22),0) -> 0.85 | I22: =SUMIFS(EVALUASI!$P$79:$P$132,EVALUASI!$D$79:$D$132,$B22) -> 6 | J22: =IFERROR(SUMIFS(DETAIL!$Q$2:$Q$137,DETAIL!$C$2:$C$137,$B22)/SUMIFS(DETAIL!$M$2:$M$137,DETAIL!$C$2:$C$137,$B22),0) -> 0.9875 | K22: =ROUND(AVERAGEIF(EVALUASI!$D$79:$D$132,$B22,EVALUASI!$W$79:$W$132),1) -> 96.8 | L22: =IF(K22>=100*SUMMARY!$C$14,"Sangat Baik",IF(K22>=100*SUMMARY!$C$15,"Baik",IF(K22>=100*SUMMARY!$C$16,"Cukup","Perlu Pembinaan"))) -> Sangat Baik | M22: =MIN(EVALUASI!$W$130:$W$130) -> 96.8 | N22: =INDEX(EVALUASI!$C$130:$C$130,MATCH(M22,EVALUASI!$W$130:$W$130,0)) -> PUTRI WIDYOWATI | O22: =K22-ROW()/100000 -> 96.79978
A23: 20 | B23: =EVALUASI!D132 -> YUSUF REZA MUHAMMAD | C23: =COUNTIF(EVALUASI!$D$79:$D$132,$B23) -> 1 | D23: =SUMIFS(EVALUASI!$I$79:$I$132,EVALUASI!$D$79:$D$132,$B23) -> 36 | E23: =SUMIFS(EVALUASI!$J$79:$J$132,EVALUASI!$D$79:$D$132,$B23) -> 33 | F23: =IFERROR(E23/D23,0) -> 0.91666667 | G23: =SUMIFS(EVALUASI!$M$79:$M$132,EVALUASI!$D$79:$D$132,$B23) -> 3 | H23: =IFERROR(1-G23/SUMIFS(DETAIL!$M$2:$M$137,DETAIL!$C$2:$C$137,$B23),0) -> 0.90909091 | I23: =SUMIFS(EVALUASI!$P$79:$P$132,EVALUASI!$D$79:$D$132,$B23) -> 1 | J23: =IFERROR(SUMIFS(DETAIL!$Q$2:$Q$137,DETAIL!$C$2:$C$137,$B23)/SUMIFS(DETAIL!$M$2:$M$137,DETAIL!$C$2:$C$137,$B23),0) -> 0.90909091 | K23: =ROUND(AVERAGEIF(EVALUASI!$D$79:$D$132,$B23,EVALUASI!$W$79:$W$132),1) -> 93.9 | L23: =IF(K23>=100*SUMMARY!$C$14,"Sangat Baik",IF(K23>=100*SUMMARY!$C$15,"Baik",IF(K23>=100*SUMMARY!$C$16,"Cukup","Perlu Pembinaan"))) -> Sangat Baik | M23: =MIN(EVALUASI!$W$132:$W$132) -> 93.9 | N23: =INDEX(EVALUASI!$C$132:$C$132,MATCH(M23,EVALUASI!$W$132:$W$132,0)) -> MUHAMMAD QAIRUL UMAM | O23: =K23-ROW()/100000 -> 93.89977
B24: TOTAL / RATA-RATA | C24: =SUM(C4:C23) -> 34 | D24: =SUM(D4:D23) -> 1712 | E24: =SUM(E4:E23) -> 1621 | F24: =IFERROR(E24/D24,0) -> 0.94684579 | G24: =SUM(G4:G23) -> 226 | H24: =IFERROR(1-G24/SUM(DETAIL!$M$2:$M$137),0) -> 0.8676815 | I24: =SUM(I4:I23) -> 100 | J24: =IFERROR(SUM(DETAIL!$Q$2:$Q$137)/SUM(DETAIL!$M$2:$M$137),0) -> 0.93618267 | K24: =ROUND(AVERAGE(EVALUASI!$W$79:$W$132),1) -> 86.1
A26: ANALISIS EFEKTIVITAS PEMAGANG & REKOMENDASI KUOTA PER DEPARTEMEN
A27: Rekomendasi kuota dihitung dari beban kerja nyata (laporan aktivitas)
B28: Bobot jumlah entri laporan | C28: 0.5
B29: Bobot panjang laporan (karakter) | C29: 0.5
B30: Minimal hari hadir agar rekomendasi meyakinkan | C30: 20
B31: Kuota minimal per departemen | C31: 1
A33: No | B33: Departemen Penempatan | C33: Jumlah Pemagang (periode) | D33: Pemagang Aktif Akhir Periode | E33: Rata-rata Pemagang Aktif (bulan berjalan) | F33: Total Hari Hadir | G33: Total Entri Laporan | H33: Entri / Hari Hadir | I33: Karakter Laporan / Hari Hadir | J33: Indeks Beban per Pemagang | K33: % Hari dgn Laporan | L33: % Kehadiran | M33: Rata-rata Skor | N33: Kebutuhan Pemagang (hitungan) | O33: REKOMENDASI KUOTA | P33: Selisih vs Aktif Saat Ini | Q33: Indikasi | R33: Rekomendasi | S33: Keyakinan Data
A34: 1 | B34: CENTRAL JAVA CURAH ADMINISTRATION JR. OFFICER | C34: =COUNTIF(PEMAGANG!$F$3:$F$36,$B34) -> 2 | D34: =COUNTIFS(PEMAGANG!$F$3:$F$36,$B34,PEMAGANG!$K$3:$K$36,SUMMARY!$C$7) -> 1 | E34: =IFERROR(AVERAGEIF(G57:J57,">0"),0) -> 1.234375 | F34: =SUMIFS(DETAIL!$M$2:$M$137,DETAIL!$S$2:$S$137,$B34) -> 85 | G34: =SUMIFS(DETAIL!$R$2:$R$137,DETAIL!$S$2:$S$137,$B34) -> 195 | H34: =IFERROR(G34/F34,0) -> 2.2941176 | I34: =IFERROR(SUMIFS(DETAIL!$T$2:$T$137,DETAIL!$S$2:$S$137,$B34)/F34,0) -> 26.094118 | J34: =IFERROR($C$28*H34/$H$52+$C$29*I34/$I$52,0) -> 0.77643822 | K34: =IFERROR(SUMIFS(DETAIL!$Q$2:$Q$137,DETAIL!$S$2:$S$137,$B34)/F34,0) -> 0.95294118 | L34: =IFERROR(SUMIFS(DETAIL!$K$2:$K$137,DETAIL!$S$2:$S$137,$B34)/SUMIFS(DETAIL!$I$2:$I$137,DETAIL!$S$2:$S$137,$B34),0) -> 0.94444444 | M34: =IFERROR(ROUND(AVERAGEIF(EVALUASI!$F$79:$F$132,$B34,EVALUASI!$W$79:$W$132),1),"-") -> 84.9 | N34: =E34*J34 -> 0.95841593 | O34: =IF(OR(F34=0,G34=0),"-",MAX($C$31,ROUND(N34,0))) -> 1 | P34: =IF(ISNUMBER(O34),O34-D34,"-") -> 0 | Q34: =IF(F34=0,"Belum ada data",IF(G34=0,"Tidak dapat dihitung",IF(P34<0,"Kelebihan pemagang",IF(P34>0,"Kekurangan pemagang","Seimbang")))) -> Seimbang | R34: =IF(Q34="Kelebihan pemagang","Kuota disarankan "&O34&" (kurangi "&-P34&"). Beban per pemagang "&TEXT(J34,"0.00")&"x rata-rata; alihkan pemagang atau tambah variasi tugas.",IF(AND(Q34="Kekurangan pemagang",D34=0),"Saat ini tidak ada pemagang aktif; isi kembali "&O34&" pemagang.",IF(Q34="Kekurangan pemagang","Kuota disarankan "&O34&" (tambah "&P34&"). Beban per pemagang "&TEXT(J34,"0.00")&"x rata-rata.",IF(Q34="Seimbang","Pertahankan "&O34&" pemagang.",IF(Q34="Tidak dapat dihitung","Pemagang tidak mengisi laporan aktivitas; wajibkan laporan harian dulu.","-"))))) -> Pertahankan 1 pemagang. | S34: =IF(F34=0,"-",IF(F34<$C$30,"Rendah (hari hadir < "&$C$30&")","Cukup")) -> Cukup
A35: 2 | B35: EQUALISATION OFFICER (SID) | C35: =COUNTIF(PEMAGANG!$F$3:$F$36,$B35) -> 1 | D35: =COUNTIFS(PEMAGANG!$F$3:$F$36,$B35,PEMAGANG!$K$3:$K$36,SUMMARY!$C$7) -> 1 | E35: =IFERROR(AVERAGEIF(G58:J58,">0"),0) -> 1 | F35: =SUMIFS(DETAIL!$M$2:$M$137,DETAIL!$S$2:$S$137,$B35) -> 65 | G35: =SUMIFS(DETAIL!$R$2:$R$137,DETAIL!$S$2:$S$137,$B35) -> 108 | H35: =IFERROR(G35/F35,0) -> 1.6615385 | I35: =IFERROR(SUMIFS(DETAIL!$T$2:$T$137,DETAIL!$S$2:$S$137,$B35)/F35,0) -> 28.353846 | J35: =IFERROR($C$28*H35/$H$52+$C$29*I35/$I$52,0) -> 0.61100401 | K35: =IFERROR(SUMIFS(DETAIL!$Q$2:$Q$137,DETAIL!$S$2:$S$137,$B35)/F35,0) -> 0.96923077 | L35: =IFERROR(SUMIFS(DETAIL!$K$2:$K$137,DETAIL!$S$2:$S$137,$B35)/SUMIFS(DETAIL!$I$2:$I$137,DETAIL!$S$2:$S$137,$B35),0) -> 0.85333333 | M35: =IFERROR(ROUND(AVERAGEIF(EVALUASI!$F$79:$F$132,$B35,EVALUASI!$W$79:$W$132),1),"-") -> 78.1 | N35: =E35*J35 -> 0.61100401 | O35: =IF(OR(F35=0,G35=0),"-",MAX($C$31,ROUND(N35,0))) -> 1 | P35: =IF(ISNUMBER(O35),O35-D35,"-") -> 0 | Q35: =IF(F35=0,"Belum ada data",IF(G35=0,"Tidak dapat dihitung",IF(P35<0,"Kelebihan pemagang",IF(P35>0,"Kekurangan pemagang","Seimbang")))) -> Seimbang | R35: =IF(Q35="Kelebihan pemagang","Kuota disarankan "&O35&" (kurangi "&-P35&"). Beban per pemagang "&TEXT(J35,"0.00")&"x rata-rata; alihkan pemagang atau tambah variasi tugas.",IF(AND(Q35="Kekurangan pemagang",D35=0),"Saat ini tidak ada pemagang aktif; isi kembali "&O35&" pemagang.",IF(Q35="Kekurangan pemagang","Kuota disarankan "&O35&" (tambah "&P35&"). Beban per pemagang "&TEXT(J35,"0.00")&"x rata-rata.",IF(Q35="Seimbang","Pertahankan "&O35&" pemagang.",IF(Q35="Tidak dapat dihitung","Pemagang tidak mengisi laporan aktivitas; wajibkan laporan harian dulu.","-"))))) -> Pertahankan 1 pemagang. | S35: =IF(F35=0,"-",IF(F35<$C$30,"Rendah (hari hadir < "&$C$30&")","Cukup")) -> Cukup
A36: 3 | B36: GM OF TAX & ACCOUNTING | C36: =COUNTIF(PEMAGANG!$F$3:$F$36,$B36) -> 1 | D36: =COUNTIFS(PEMAGANG!$F$3:$F$36,$B36,PEMAGANG!$K$3:$K$36,SUMMARY!$C$7) -> 1 | E36: =IFERROR(AVERAGEIF(G59:J59,">0"),0) -> 0.86842105 | F36: =SUMIFS(DETAIL!$M$2:$M$137,DETAIL!$S$2:$S$137,$B36) -> 33 | G36: =SUMIFS(DETAIL!$R$2:$R$137,DETAIL!$S$2:$S$137,$B36) -> 49 | H36: =IFERROR(G36/F36,0) -> 1.4848485 | I36: =IFERROR(SUMIFS(DETAIL!$T$2:$T$137,DETAIL!$S$2:$S$137,$B36)/F36,0) -> 156.36364 | J36: =IFERROR($C$28*H36/$H$52+$C$29*I36/$I$52,0) -> 1.2203614 | K36: =IFERROR(SUMIFS(DETAIL!$Q$2:$Q$137,DETAIL!$S$2:$S$137,$B36)/F36,0) -> 0.90909091 | L36: =IFERROR(SUMIFS(DETAIL!$K$2:$K$137,DETAIL!$S$2:$S$137,$B36)/SUMIFS(DETAIL!$I$2:$I$137,DETAIL!$S$2:$S$137,$B36),0) -> 0.91666667 | M36: =IFERROR(ROUND(AVERAGEIF(EVALUASI!$F$79:$F$132,$B36,EVALUASI!$W$79:$W$132),1),"-") -> 93.9 | N36: =E36*J36 -> 1.0597875 | O36: =IF(OR(F36=0,G36=0),"-",MAX($C$31,ROUND(N36,0))) -> 1 | P36: =IF(ISNUMBER(O36),O36-D36,"-") -> 0 | Q36: =IF(F36=0,"Belum ada data",IF(G36=0,"Tidak dapat dihitung",IF(P36<0,"Kelebihan pemagang",IF(P36>0,"Kekurangan pemagang","Seimbang")))) -> Seimbang | R36: =IF(Q36="Kelebihan pemagang","Kuota disarankan "&O36&" (kurangi "&-P36&"). Beban per pemagang "&TEXT(J36,"0.00")&"x rata-rata; alihkan pemagang atau tambah variasi tugas.",IF(AND(Q36="Kekurangan pemagang",D36=0),"Saat ini tidak ada pemagang aktif; isi kembali "&O36&" pemagang.",IF(Q36="Kekurangan pemagang","Kuota disarankan "&O36&" (tambah "&P36&"). Beban per pemagang "&TEXT(J36,"0.00")&"x rata-rata.",IF(Q36="Seimbang","Pertahankan "&O36&" pemagang.",IF(Q36="Tidak dapat dihitung","Pemagang tidak mengisi laporan aktivitas; wajibkan laporan harian dulu.","-"))))) -> Pertahankan 1 pemagang. | S36: =IF(F36=0,"-",IF(F36<$C$30,"Rendah (hari hadir < "&$C$30&")","Cukup")) -> Cukup
A37: 4 | B37: MANAGER OF TRANSPORTATION | C37: =COUNTIF(PEMAGANG!$F$3:$F$36,$B37) -> 2 | D37: =COUNTIFS(PEMAGANG!$F$3:$F$36,$B37,PEMAGANG!$K$3:$K$36,SUMMARY!$C$7) -> 2 | E37: =IFERROR(AVERAGEIF(G60:J60,">0"),0) -> 1.75 | F37: =SUMIFS(DETAIL!$M$2:$M$137,DETAIL!$S$2:$S$137,$B37) -> 136 | G37: =SUMIFS(DETAIL!$R$2:$R$137,DETAIL!$S$2:$S$137,$B37) -> 296 | H37: =IFERROR(G37/F37,0) -> 2.1764706 | I37: =IFERROR(SUMIFS(DETAIL!$T$2:$T$137,DETAIL!$S$2:$S$137,$B37)/F37,0) -> 87.757353 | J37: =IFERROR($C$28*H37/$H$52+$C$29*I37/$I$52,0) -> 1.0608634 | K37: =IFERROR(SUMIFS(DETAIL!$Q$2:$Q$137,DETAIL!$S$2:$S$137,$B37)/F37,0) -> 0.99264706 | L37: =IFERROR(SUMIFS(DETAIL!$K$2:$K$137,DETAIL!$S$2:$S$137,$B37)/SUMIFS(DETAIL!$I$2:$I$137,DETAIL!$S$2:$S$137,$B37),0) -> 0.95522388 | M37: =IFERROR(ROUND(AVERAGEIF(EVALUASI!$F$79:$F$132,$B37,EVALUASI!$W$79:$W$132),1),"-") -> 92.3 | N37: =E37*J37 -> 1.856511 | O37: =IF(OR(F37=0,G37=0),"-",MAX($C$31,ROUND(N37,0))) -> 2 | P37: =IF(ISNUMBER(O37),O37-D37,"-") -> 0 | Q37: =IF(F37=0,"Belum ada data",IF(G37=0,"Tidak dapat dihitung",IF(P37<0,"Kelebihan pemagang",IF(P37>0,"Kekurangan pemagang","Seimbang")))) -> Seimbang | R37: =IF(Q37="Kelebihan pemagang","Kuota disarankan "&O37&" (kurangi "&-P37&"). Beban per pemagang "&TEXT(J37,"0.00")&"x rata-rata; alihkan pemagang atau tambah variasi tugas.",IF(AND(Q37="Kekurangan pemagang",D37=0),"Saat ini tidak ada pemagang aktif; isi kembali "&O37&" pemagang.",IF(Q37="Kekurangan pemagang","Kuota disarankan "&O37&" (tambah "&P37&"). Beban per pemagang "&TEXT(J37,"0.00")&"x rata-rata.",IF(Q37="Seimbang","Pertahankan "&O37&" pemagang.",IF(Q37="Tidak dapat dihitung","Pemagang tidak mengisi laporan aktivitas; wajibkan laporan harian dulu.","-"))))) -> Pertahankan 2 pemagang. | S37: =IF(F37=0,"-",IF(F37<$C$30,"Rendah (hari hadir < "&$C$30&")","Cukup")) -> Cukup
A38: 5 | B38: MANAGER OF VERIFICATION | C38: =COUNTIF(PEMAGANG!$F$3:$F$36,$B38) -> 1 | D38: =COUNTIFS(PEMAGANG!$F$3:$F$36,$B38,PEMAGANG!$K$3:$K$36,SUMMARY!$C$7) -> 1 | E38: =IFERROR(AVERAGEIF(G61:J61,">0"),0) -> 0.59090909 | F38: =SUMIFS(DETAIL!$M$2:$M$137,DETAIL!$S$2:$S$137,$B38) -> 13 | G38: =SUMIFS(DETAIL!$R$2:$R$137,DETAIL!$S$2:$S$137,$B38) -> 13 | H38: =IFERROR(G38/F38,0) -> 1 | I38: =IFERROR(SUMIFS(DETAIL!$T$2:$T$137,DETAIL!$S$2:$S$137,$B38)/F38,0) -> 97 | J38: =IFERROR($C$28*H38/$H$52+$C$29*I38/$I$52,0) -> 0.7791278 | K38: =IFERROR(SUMIFS(DETAIL!$Q$2:$Q$137,DETAIL!$S$2:$S$137,$B38)/F38,0) -> 1 | L38: =IFERROR(SUMIFS(DETAIL!$K$2:$K$137,DETAIL!$S$2:$S$137,$B38)/SUMIFS(DETAIL!$I$2:$I$137,DETAIL!$S$2:$S$137,$B38),0) -> 1 | M38: =IFERROR(ROUND(AVERAGEIF(EVALUASI!$F$79:$F$132,$B38,EVALUASI!$W$79:$W$132),1),"-") -> 91.8 | N38: =E38*J38 -> 0.4603937 | O38: =IF(OR(F38=0,G38=0),"-",MAX($C$31,ROUND(N38,0))) -> 1 | P38: =IF(ISNUMBER(O38),O38-D38,"-") -> 0 | Q38: =IF(F38=0,"Belum ada data",IF(G38=0,"Tidak dapat dihitung",IF(P38<0,"Kelebihan pemagang",IF(P38>0,"Kekurangan pemagang","Seimbang")))) -> Seimbang | R38: =IF(Q38="Kelebihan pemagang","Kuota disarankan "&O38&" (kurangi "&-P38&"). Beban per pemagang "&TEXT(J38,"0.00")&"x rata-rata; alihkan pemagang atau tambah variasi tugas.",IF(AND(Q38="Kekurangan pemagang",D38=0),"Saat ini tidak ada pemagang aktif; isi kembali "&O38&" pemagang.",IF(Q38="Kekurangan pemagang","Kuota disarankan "&O38&" (tambah "&P38&"). Beban per pemagang "&TEXT(J38,"0.00")&"x rata-rata.",IF(Q38="Seimbang","Pertahankan "&O38&" pemagang.",IF(Q38="Tidak dapat dihitung","Pemagang tidak mengisi laporan aktivitas; wajibkan laporan harian dulu.","-"))))) -> Pertahankan 1 pemagang. | S38: =IF(F38=0,"-",IF(F38<$C$30,"Rendah (hari hadir < "&$C$30&")","Cukup")) -> Rendah (hari hadir < 20)
A39: 6 | B39: MARKETING & EXPANSION MODERN RETAIL OFFICER | C39: =COUNTIF(PEMAGANG!$F$3:$F$36,$B39) -> 1 | D39: =COUNTIFS(PEMAGANG!$F$3:$F$36,$B39,PEMAGANG!$K$3:$K$36,SUMMARY!$C$7) -> 1 | E39: =IFERROR(AVERAGEIF(G62:J62,">0"),0) -> 1 | F39: =SUMIFS(DETAIL!$M$2:$M$137,DETAIL!$S$2:$S$137,$B39) -> 94 | G39: =SUMIFS(DETAIL!$R$2:$R$137,DETAIL!$S$2:$S$137,$B39) -> 154 | H39: =IFERROR(G39/F39,0) -> 1.6382979 | I39: =IFERROR(SUMIFS(DETAIL!$T$2:$T$137,DETAIL!$S$2:$S$137,$B39)/F39,0) -> 45.510638 | J39: =IFERROR($C$28*H39/$H$52+$C$29*I39/$I$52,0) -> 0.69279781 | K39: =IFERROR(SUMIFS(DETAIL!$Q$2:$Q$137,DETAIL!$S$2:$S$137,$B39)/F39,0) -> 0.91489362 | L39: =IFERROR(SUMIFS(DETAIL!$K$2:$K$137,DETAIL!$S$2:$S$137,$B39)/SUMIFS(DETAIL!$I$2:$I$137,DETAIL!$S$2:$S$137,$B39),0) -> 0.93333333 | M39: =IFERROR(ROUND(AVERAGEIF(EVALUASI!$F$79:$F$132,$B39,EVALUASI!$W$79:$W$132),1),"-") -> 74.5 | N39: =E39*J39 -> 0.69279781 | O39: =IF(OR(F39=0,G39=0),"-",MAX($C$31,ROUND(N39,0))) -> 1 | P39: =IF(ISNUMBER(O39),O39-D39,"-") -> 0 | Q39: =IF(F39=0,"Belum ada data",IF(G39=0,"Tidak dapat dihitung",IF(P39<0,"Kelebihan pemagang",IF(P39>0,"Kekurangan pemagang","Seimbang")))) -> Seimbang | R39: =IF(Q39="Kelebihan pemagang","Kuota disarankan "&O39&" (kurangi "&-P39&"). Beban per pemagang "&TEXT(J39,"0.00")&"x rata-rata; alihkan pemagang atau tambah variasi tugas.",IF(AND(Q39="Kekurangan pemagang",D39=0),"Saat ini tidak ada pemagang aktif; isi kembali "&O39&" pemagang.",IF(Q39="Kekurangan pemagang","Kuota disarankan "&O39&" (tambah "&P39&"). Beban per pemagang "&TEXT(J39,"0.00")&"x rata-rata.",IF(Q39="Seimbang","Pertahankan "&O39&" pemagang.",IF(Q39="Tidak dapat dihitung","Pemagang tidak mengisi laporan aktivitas; wajibkan laporan harian dulu.","-"))))) -> Pertahankan 1 pemagang. | S39: =IF(F39=0,"-",IF(F39<$C$30,"Rendah (hari hadir < "&$C$30&")","Cukup")) -> Cukup
A40: 7 | B40: PGS FINANCIAL ANALYSIS OFFICER | C40: =COUNTIF(PEMAGANG!$F$3:$F$36,$B40) -> 1 | D40: =COUNTIFS(PEMAGANG!$F$3:$F$36,$B40,PEMAGANG!$K$3:$K$36,SUMMARY!$C$7) -> 1 | E40: =IFERROR(AVERAGEIF(G63:J63,">0"),0) -> 1 | F40: =SUMIFS(DETAIL!$M$2:$M$137,DETAIL!$S$2:$S$137,$B40) -> 78 | G40: =SUMIFS(DETAIL!$R$2:$R$137,DETAIL!$S$2:$S$137,$B40) -> 248 | H40: =IFERROR(G40/F40,0) -> 3.1794872 | I40: =IFERROR(SUMIFS(DETAIL!$T$2:$T$137,DETAIL!$S$2:$S$137,$B40)/F40,0) -> 206.92308 | J40: =IFERROR($C$28*H40/$H$52+$C$29*I40/$I$52,0) -> 1.9549136 | K40: =IFERROR(SUMIFS(DETAIL!$Q$2:$Q$137,DETAIL!$S$2:$S$137,$B40)/F40,0) -> 0.98717949 | L40: =IFERROR(SUMIFS(DETAIL!$K$2:$K$137,DETAIL!$S$2:$S$137,$B40)/SUMIFS(DETAIL!$I$2:$I$137,DETAIL!$S$2:$S$137,$B40),0) -> 0.96 | M40: =IFERROR(ROUND(AVERAGEIF(EVALUASI!$F$79:$F$132,$B40,EVALUASI!$W$79:$W$132),1),"-") -> 98.5 | N40: =E40*J40 -> 1.9549136 | O40: =IF(OR(F40=0,G40=0),"-",MAX($C$31,ROUND(N40,0))) -> 2 | P40: =IF(ISNUMBER(O40),O40-D40,"-") -> 1 | Q40: =IF(F40=0,"Belum ada data",IF(G40=0,"Tidak dapat dihitung",IF(P40<0,"Kelebihan pemagang",IF(P40>0,"Kekurangan pemagang","Seimbang")))) -> Kekurangan pemagang | R40: =IF(Q40="Kelebihan pemagang","Kuota disarankan "&O40&" (kurangi "&-P40&"). Beban per pemagang "&TEXT(J40,"0.00")&"x rata-rata; alihkan pemagang atau tambah variasi tugas.",IF(AND(Q40="Kekurangan pemagang",D40=0),"Saat ini tidak ada pemagang aktif; isi kembali "&O40&" pemagang.",IF(Q40="Kekurangan pemagang","Kuota disarankan "&O40&" (tambah "&P40&"). Beban per pemagang "&TEXT(J40,"0.00")&"x rata-rata.",IF(Q40="Seimbang","Pertahankan "&O40&" pemagang.",IF(Q40="Tidak dapat dihitung","Pemagang tidak mengisi laporan aktivitas; wajibkan laporan harian dulu.","-"))))) -> Kuota disarankan 2 (tambah 1). Beban per pemagang 1.95x rata-rata. | S40: =IF(F40=0,"-",IF(F40<$C$30,"Rendah (hari hadir < "&$C$30&")","Cukup")) -> Cukup
A41: 8 | B41: PGS MANAGER OF LAMONGAN BRANCH | C41: =COUNTIF(PEMAGANG!$F$3:$F$36,$B41) -> 1 | D41: =COUNTIFS(PEMAGANG!$F$3:$F$36,$B41,PEMAGANG!$K$3:$K$36,SUMMARY!$C$7) -> 1 | E41: =IFERROR(AVERAGEIF(G64:J64,">0"),0) -> 0.90909091 | F41: =SUMIFS(DETAIL!$M$2:$M$137,DETAIL!$S$2:$S$137,$B41) -> 15 | G41: =SUMIFS(DETAIL!$R$2:$R$137,DETAIL!$S$2:$S$137,$B41) -> 0 | H41: =IFERROR(G41/F41,0) -> 0 | I41: =IFERROR(SUMIFS(DETAIL!$T$2:$T$137,DETAIL!$S$2:$S$137,$B41)/F41,0) -> 0 | J41: =IFERROR($C$28*H41/$H$52+$C$29*I41/$I$52,0) -> 0 | K41: =IFERROR(SUMIFS(DETAIL!$Q$2:$Q$137,DETAIL!$S$2:$S$137,$B41)/F41,0) -> 0 | L41: =IFERROR(SUMIFS(DETAIL!$K$2:$K$137,DETAIL!$S$2:$S$137,$B41)/SUMIFS(DETAIL!$I$2:$I$137,DETAIL!$S$2:$S$137,$B41),0) -> 0.75 | M41: =IFERROR(ROUND(AVERAGEIF(EVALUASI!$F$79:$F$132,$B41,EVALUASI!$W$79:$W$132),1),"-") -> 31.8 | N41: =E41*J41 -> 0 | O41: =IF(OR(F41=0,G41=0),"-",MAX($C$31,ROUND(N41,0))) -> - | P41: =IF(ISNUMBER(O41),O41-D41,"-") -> - | Q41: =IF(F41=0,"Belum ada data",IF(G41=0,"Tidak dapat dihitung",IF(P41<0,"Kelebihan pemagang",IF(P41>0,"Kekurangan pemagang","Seimbang")))) -> Tidak dapat dihitung | R41: =IF(Q41="Kelebihan pemagang","Kuota disarankan "&O41&" (kurangi "&-P41&"). Beban per pemagang "&TEXT(J41,"0.00")&"x rata-rata; alihkan pemagang atau tambah variasi tugas.",IF(AND(Q41="Kekurangan pemagang",D41=0),"Saat ini tidak ada pemagang aktif; isi kembali "&O41&" pemagang.",IF(Q41="Kekurangan pemagang","Kuota disarankan "&O41&" (tambah "&P41&"). Beban per pemagang "&TEXT(J41,"0.00")&"x rata-rata.",IF(Q41="Seimbang","Pertahankan "&O41&" pemagang.",IF(Q41="Tidak dapat dihitung","Pemagang tidak mengisi laporan aktivitas; wajibkan laporan harian dulu.","-"))))) -> Pemagang tidak mengisi laporan aktivitas; wajibkan laporan harian dulu. | S41: =IF(F41=0,"-",IF(F41<$C$30,"Rendah (hari hadir < "&$C$30&")","Cukup")) -> Rendah (hari hadir < 20)
A42: 9 | B42: PGS SM OF DIGITAL BUSSINES | C42: =COUNTIF(PEMAGANG!$F$3:$F$36,$B42) -> 8 | D42: =COUNTIFS(PEMAGANG!$F$3:$F$36,$B42,PEMAGANG!$K$3:$K$36,SUMMARY!$C$7) -> 8 | E42: =IFERROR(AVERAGEIF(G65:J65,">0"),0) -> 6.3026316 | F42: =SUMIFS(DETAIL!$M$2:$M$137,DETAIL!$S$2:$S$137,$B42) -> 493 | G42: =SUMIFS(DETAIL!$R$2:$R$137,DETAIL!$S$2:$S$137,$B42) -> 898 | H42: =IFERROR(G42/F42,0) -> 1.821501 | I42: =IFERROR(SUMIFS(DETAIL!$T$2:$T$137,DETAIL!$S$2:$S$137,$B42)/F42,0) -> 85.046653 | J42: =IFERROR($C$28*H42/$H$52+$C$29*I42/$I$52,0) -> 0.94755368 | K42: =IFERROR(SUMIFS(DETAIL!$Q$2:$Q$137,DETAIL!$S$2:$S$137,$B42)/F42,0) -> 0.89655172 | L42: =IFERROR(SUMIFS(DETAIL!$K$2:$K$137,DETAIL!$S$2:$S$137,$B42)/SUMIFS(DETAIL!$I$2:$I$137,DETAIL!$S$2:$S$137,$B42),0) -> 0.97308489 | M42: =IFERROR(ROUND(AVERAGEIF(EVALUASI!$F$79:$F$132,$B42,EVALUASI!$W$79:$W$132),1),"-") -> 85.8 | N42: =E42*J42 -> 5.9720817 | O42: =IF(OR(F42=0,G42=0),"-",MAX($C$31,ROUND(N42,0))) -> 6 | P42: =IF(ISNUMBER(O42),O42-D42,"-") -> -2 | Q42: =IF(F42=0,"Belum ada data",IF(G42=0,"Tidak dapat dihitung",IF(P42<0,"Kelebihan pemagang",IF(P42>0,"Kekurangan pemagang","Seimbang")))) -> Kelebihan pemagang | R42: =IF(Q42="Kelebihan pemagang","Kuota disarankan "&O42&" (kurangi "&-P42&"). Beban per pemagang "&TEXT(J42,"0.00")&"x rata-rata; alihkan pemagang atau tambah variasi tugas.",IF(AND(Q42="Kekurangan pemagang",D42=0),"Saat ini tidak ada pemagang aktif; isi kembali "&O42&" pemagang.",IF(Q42="Kekurangan pemagang","Kuota disarankan "&O42&" (tambah "&P42&"). Beban per pemagang "&TEXT(J42,"0.00")&"x rata-rata.",IF(Q42="Seimbang","Pertahankan "&O42&" pemagang.",IF(Q42="Tidak dapat dihitung","Pemagang tidak mengisi laporan aktivitas; wajibkan laporan harian dulu.","-"))))) -> Kuota disarankan 6 (kurangi 2). Beban per pemagang 0.95x rata-rata; alihkan pemagang atau tambah variasi tugas. | S42: =IF(F42=0,"-",IF(F42<$C$30,"Rendah (hari hadir < "&$C$30&")","Cukup")) -> Cukup
A43: 10 | B43: PGS TREASURY (SID) OFFICER | C43: =COUNTIF(PEMAGANG!$F$3:$F$36,$B43) -> 2 | D43: =COUNTIFS(PEMAGANG!$F$3:$F$36,$B43,PEMAGANG!$K$3:$K$36,SUMMARY!$C$7) -> 1 | E43: =IFERROR(AVERAGEIF(G66:J66,">0"),0) -> 0.86111111 | F43: =SUMIFS(DETAIL!$M$2:$M$137,DETAIL!$S$2:$S$137,$B43) -> 58 | G43: =SUMIFS(DETAIL!$R$2:$R$137,DETAIL!$S$2:$S$137,$B43) -> 60 | H43: =IFERROR(G43/F43,0) -> 1.0344828 | I43: =IFERROR(SUMIFS(DETAIL!$T$2:$T$137,DETAIL!$S$2:$S$137,$B43)/F43,0) -> 39.931034 | J43: =IFERROR($C$28*H43/$H$52+$C$29*I43/$I$52,0) -> 0.49506904 | K43: =IFERROR(SUMIFS(DETAIL!$Q$2:$Q$137,DETAIL!$S$2:$S$137,$B43)/F43,0) -> 0.98275862 | L43: =IFERROR(SUMIFS(DETAIL!$K$2:$K$137,DETAIL!$S$2:$S$137,$B43)/SUMIFS(DETAIL!$I$2:$I$137,DETAIL!$S$2:$S$137,$B43),0) -> 0.89230769 | M43: =IFERROR(ROUND(AVERAGEIF(EVALUASI!$F$79:$F$132,$B43,EVALUASI!$W$79:$W$132),1),"-") -> 81.4 | N43: =E43*J43 -> 0.42630945 | O43: =IF(OR(F43=0,G43=0),"-",MAX($C$31,ROUND(N43,0))) -> 1 | P43: =IF(ISNUMBER(O43),O43-D43,"-") -> 0 | Q43: =IF(F43=0,"Belum ada data",IF(G43=0,"Tidak dapat dihitung",IF(P43<0,"Kelebihan pemagang",IF(P43>0,"Kekurangan pemagang","Seimbang")))) -> Seimbang | R43: =IF(Q43="Kelebihan pemagang","Kuota disarankan "&O43&" (kurangi "&-P43&"). Beban per pemagang "&TEXT(J43,"0.00")&"x rata-rata; alihkan pemagang atau tambah variasi tugas.",IF(AND(Q43="Kekurangan pemagang",D43=0),"Saat ini tidak ada pemagang aktif; isi kembali "&O43&" pemagang.",IF(Q43="Kekurangan pemagang","Kuota disarankan "&O43&" (tambah "&P43&"). Beban per pemagang "&TEXT(J43,"0.00")&"x rata-rata.",IF(Q43="Seimbang","Pertahankan "&O43&" pemagang.",IF(Q43="Tidak dapat dihitung","Pemagang tidak mengisi laporan aktivitas; wajibkan laporan harian dulu.","-"))))) -> Pertahankan 1 pemagang. | S43: =IF(F43=0,"-",IF(F43<$C$30,"Rendah (hari hadir < "&$C$30&")","Cukup")) -> Cukup
A44: 11 | B44: PJ GM OF MARKETING (SID) | C44: =COUNTIF(PEMAGANG!$F$3:$F$36,$B44) -> 2 | D44: =COUNTIFS(PEMAGANG!$F$3:$F$36,$B44,PEMAGANG!$K$3:$K$36,SUMMARY!$C$7) -> 1 | E44: =IFERROR(AVERAGEIF(G67:J67,">0"),0) -> 0.81638756 | F44: =SUMIFS(DETAIL!$M$2:$M$137,DETAIL!$S$2:$S$137,$B44) -> 60 | G44: =SUMIFS(DETAIL!$R$2:$R$137,DETAIL!$S$2:$S$137,$B44) -> 104 | H44: =IFERROR(G44/F44,0) -> 1.7333333 | I44: =IFERROR(SUMIFS(DETAIL!$T$2:$T$137,DETAIL!$S$2:$S$137,$B44)/F44,0) -> 118.83333 | J44: =IFERROR($C$28*H44/$H$52+$C$29*I44/$I$52,0) -> 1.0967611 | K44: =IFERROR(SUMIFS(DETAIL!$Q$2:$Q$137,DETAIL!$S$2:$S$137,$B44)/F44,0) -> 0.95 | L44: =IFERROR(SUMIFS(DETAIL!$K$2:$K$137,DETAIL!$S$2:$S$137,$B44)/SUMIFS(DETAIL!$I$2:$I$137,DETAIL!$S$2:$S$137,$B44),0) -> 0.91525424 | M44: =IFERROR(ROUND(AVERAGEIF(EVALUASI!$F$79:$F$132,$B44,EVALUASI!$W$79:$W$132),1),"-") -> 94 | N44: =E44*J44 -> 0.89538214 | O44: =IF(OR(F44=0,G44=0),"-",MAX($C$31,ROUND(N44,0))) -> 1 | P44: =IF(ISNUMBER(O44),O44-D44,"-") -> 0 | Q44: =IF(F44=0,"Belum ada data",IF(G44=0,"Tidak dapat dihitung",IF(P44<0,"Kelebihan pemagang",IF(P44>0,"Kekurangan pemagang","Seimbang")))) -> Seimbang | R44: =IF(Q44="Kelebihan pemagang","Kuota disarankan "&O44&" (kurangi "&-P44&"). Beban per pemagang "&TEXT(J44,"0.00")&"x rata-rata; alihkan pemagang atau tambah variasi tugas.",IF(AND(Q44="Kekurangan pemagang",D44=0),"Saat ini tidak ada pemagang aktif; isi kembali "&O44&" pemagang.",IF(Q44="Kekurangan pemagang","Kuota disarankan "&O44&" (tambah "&P44&"). Beban per pemagang "&TEXT(J44,"0.00")&"x rata-rata.",IF(Q44="Seimbang","Pertahankan "&O44&" pemagang.",IF(Q44="Tidak dapat dihitung","Pemagang tidak mengisi laporan aktivitas; wajibkan laporan harian dulu.","-"))))) -> Pertahankan 1 pemagang. | S44: =IF(F44=0,"-",IF(F44<$C$30,"Rendah (hari hadir < "&$C$30&")","Cukup")) -> Cukup
A45: 12 | B45: PKSDM | C45: =COUNTIF(PEMAGANG!$F$3:$F$36,$B45) -> 1 | D45: =COUNTIFS(PEMAGANG!$F$3:$F$36,$B45,PEMAGANG!$K$3:$K$36,SUMMARY!$C$7) -> 1 | E45: =IFERROR(AVERAGEIF(G68:J68,">0"),0) -> 1 | F45: =SUMIFS(DETAIL!$M$2:$M$137,DETAIL!$S$2:$S$137,$B45) -> 76 | G45: =SUMIFS(DETAIL!$R$2:$R$137,DETAIL!$S$2:$S$137,$B45) -> 253 | H45: =IFERROR(G45/F45,0) -> 3.3289474 | I45: =IFERROR(SUMIFS(DETAIL!$T$2:$T$137,DETAIL!$S$2:$S$137,$B45)/F45,0) -> 248.92105 | J45: =IFERROR($C$28*H45/$H$52+$C$29*I45/$I$52,0) -> 2.2128952 | K45: =IFERROR(SUMIFS(DETAIL!$Q$2:$Q$137,DETAIL!$S$2:$S$137,$B45)/F45,0) -> 0.97368421 | L45: =IFERROR(SUMIFS(DETAIL!$K$2:$K$137,DETAIL!$S$2:$S$137,$B45)/SUMIFS(DETAIL!$I$2:$I$137,DETAIL!$S$2:$S$137,$B45),0) -> 0.94666667 | M45: =IFERROR(ROUND(AVERAGEIF(EVALUASI!$F$79:$F$132,$B45,EVALUASI!$W$79:$W$132),1),"-") -> 97.9 | N45: =E45*J45 -> 2.2128952 | O45: =IF(OR(F45=0,G45=0),"-",MAX($C$31,ROUND(N45,0))) -> 2 | P45: =IF(ISNUMBER(O45),O45-D45,"-") -> 1 | Q45: =IF(F45=0,"Belum ada data",IF(G45=0,"Tidak dapat dihitung",IF(P45<0,"Kelebihan pemagang",IF(P45>0,"Kekurangan pemagang","Seimbang")))) -> Kekurangan pemagang | R45: =IF(Q45="Kelebihan pemagang","Kuota disarankan "&O45&" (kurangi "&-P45&"). Beban per pemagang "&TEXT(J45,"0.00")&"x rata-rata; alihkan pemagang atau tambah variasi tugas.",IF(AND(Q45="Kekurangan pemagang",D45=0),"Saat ini tidak ada pemagang aktif; isi kembali "&O45&" pemagang.",IF(Q45="Kekurangan pemagang","Kuota disarankan "&O45&" (tambah "&P45&"). Beban per pemagang "&TEXT(J45,"0.00")&"x rata-rata.",IF(Q45="Seimbang","Pertahankan "&O45&" pemagang.",IF(Q45="Tidak dapat dihitung","Pemagang tidak mengisi laporan aktivitas; wajibkan laporan harian dulu.","-"))))) -> Kuota disarankan 2 (tambah 1). Beban per pemagang 2.21x rata-rata. | S45: =IF(F45=0,"-",IF(F45<$C$30,"Rendah (hari hadir < "&$C$30&")","Cukup")) -> Cukup
... A50: 17 | B50: VERIFICATION (SID) JR. OFFICER | C50: =COUNTIF(PEMAGANG!$F$3:$F$36,$B50) -> 5 | D50: =COUNTIFS(PEMAGANG!$F$3:$F$36,$B50,PEMAGANG!$K$3:$K$36,SUMMARY!$C$7) -> 3 | E50: =IFERROR(AVERAGEIF(G73:J73,">0"),0) -> 3.2457386 | F50: =SUMIFS(DETAIL!$M$2:$M$137,DETAIL!$S$2:$S$137,$B50) -> 245 | G50: =SUMIFS(DETAIL!$R$2:$R$137,DETAIL!$S$2:$S$137,$B50) -> 329 | H50: =IFERROR(G50/F50,0) -> 1.3428571 | I50: =IFERROR(SUMIFS(DETAIL!$T$2:$T$137,DETAIL!$S$2:$S$137,$B50)/F50,0) -> 146.4449 | J50: =IFERROR($C$28*H50/$H$52+$C$29*I50/$I$52,0) -> 1.1295691 | K50: =IFERROR(SUMIFS(DETAIL!$Q$2:$Q$137,DETAIL!$S$2:$S$137,$B50)/F50,0) -> 0.96734694 | L50: =IFERROR(SUMIFS(DETAIL!$K$2:$K$137,DETAIL!$S$2:$S$137,$B50)/SUMIFS(DETAIL!$I$2:$I$137,DETAIL!$S$2:$S$137,$B50),0) -> 0.97510373 | M50: =IFERROR(ROUND(AVERAGEIF(EVALUASI!$F$79:$F$132,$B50,EVALUASI!$W$79:$W$132),1),"-") -> 92 | N50: =E50*J50 -> 3.6662862 | O50: =IF(OR(F50=0,G50=0),"-",MAX($C$31,ROUND(N50,0))) -> 4 | P50: =IF(ISNUMBER(O50),O50-D50,"-") -> 1 | Q50: =IF(F50=0,"Belum ada data",IF(G50=0,"Tidak dapat dihitung",IF(P50<0,"Kelebihan pemagang",IF(P50>0,"Kekurangan pemagang","Seimbang")))) -> Kekurangan pemagang | R50: =IF(Q50="Kelebihan pemagang","Kuota disarankan "&O50&" (kurangi "&-P50&"). Beban per pemagang "&TEXT(J50,"0.00")&"x rata-rata; alihkan pemagang atau tambah variasi tugas.",IF(AND(Q50="Kekurangan pemagang",D50=0),"Saat ini tidak ada pemagang aktif; isi kembali "&O50&" pemagang.",IF(Q50="Kekurangan pemagang","Kuota disarankan "&O50&" (tambah "&P50&"). Beban per pemagang "&TEXT(J50,"0.00")&"x rata-rata.",IF(Q50="Seimbang","Pertahankan "&O50&" pemagang.",IF(Q50="Tidak dapat dihitung","Pemagang tidak mengisi laporan aktivitas; wajibkan laporan harian dulu.","-"))))) -> Kuota disarankan 4 (tambah 1). Beban per pemagang 1.13x rata-rata. | S50: =IF(F50=0,"-",IF(F50<$C$30,"Rendah (hari hadir < "&$C$30&")","Cukup")) -> Cukup
B52: TOTAL / RATA-RATA SEMUA DEPARTEMEN | C52: =SUM(C34:C51) -> 34 | D52: =SUM(D34:D51) -> 28 | E52: =SUM(E34:E51) -> 25.579114 | F52: =SUM(F34:F51) -> 1708 | G52: =SUM(G34:G51) -> 3051 | H52: =IFERROR(G52/F52,0) -> 1.7862998 | I52: =IFERROR(SUM(DETAIL!$T$2:$T$137)/F52,0) -> 97.151639 | J52: =1 -> 1 | K52: =IFERROR(SUM(DETAIL!$Q$2:$Q$137)/F52,0) -> 0.93618267 | L52: =IFERROR(SUM(DETAIL!$K$2:$K$137)/SUM(DETAIL!$I$2:$I$137),0) -> 0.94684579 | M52: =ROUND(AVERAGE(EVALUASI!$W$79:$W$132),1) -> 86.1 | N52: =SUM(N34:N51) -> 24.664948 | O52: =SUM(O34:O51) -> 28 | P52: =SUM(P34:P51) -> 1
A55: RINCIAN PER BULAN
A56: No | B56: Departemen Penempatan | C56: ="Pemagang: "&TREN!A4 -> Pemagang: Juni | D56: ="Pemagang: "&TREN!A5 -> Pemagang: Juli | E56: ="Pemagang: "&TREN!A6 -> Pemagang: Agustus | F56: ="Pemagang: "&TREN!A7 -> Pemagang: September | G56: ="Rata-rata aktif/hari: "&TREN!A4 -> Rata-rata aktif/hari: Juni | H56: ="Rata-rata aktif/hari: "&TREN!A5 -> Rata-rata aktif/hari: Juli | I56: ="Rata-rata aktif/hari: "&TREN!A6 -> Rata-rata aktif/hari: Agustus | J56: ="Rata-rata aktif/hari: "&TREN!A7 -> Rata-rata aktif/hari: September | K56: ="Entri/hari hadir: "&TREN!A4 -> Entri/hari hadir: Juni | L56: ="Entri/hari hadir: "&TREN!A5 -> Entri/hari hadir: Juli | M56: ="Entri/hari hadir: "&TREN!A6 -> Entri/hari hadir: Agustus | N56: ="Entri/hari hadir: "&TREN!A7 -> Entri/hari hadir: September
A57: 1 | B57: =B34 -> CENTRAL JAVA CURAH ADMINISTRATION JR. OFFICER | C57: =COUNTIFS(DETAIL!$S$2:$S$137,$B57,DETAIL!$F$2:$F$137,MONTH(DATE(YEAR(SUMMARY!$C$6),MONTH(SUMMARY!$C$6)+0,1)),DETAIL!$I$2:$I$137,">0") -> 2 | D57: =COUNTIFS(DETAIL!$S$2:$S$137,$B57,DETAIL!$F$2:$F$137,MONTH(DATE(YEAR(SUMMARY!$C$6),MONTH(SUMMARY!$C$6)+1,1)),DETAIL!$I$2:$I$137,">0") -> 1 | E57: =COUNTIFS(DETAIL!$S$2:$S$137,$B57,DETAIL!$F$2:$F$137,MONTH(DATE(YEAR(SUMMARY!$C$6),MONTH(SUMMARY!$C$6)+2,1)),DETAIL!$I$2:$I$137,">0") -> 1 | F57: =COUNTIFS(DETAIL!$S$2:$S$137,$B57,DETAIL!$F$2:$F$137,MONTH(DATE(YEAR(SUMMARY!$C$6),MONTH(SUMMARY!$C$6)+3,1)),DETAIL!$I$2:$I$137,">0") -> 1 | G57: =IFERROR(SUMIFS(DETAIL!$I$2:$I$137,DETAIL!$S$2:$S$137,$B57,DETAIL!$F$2:$F$137,MONTH(DATE(YEAR(SUMMARY!$C$6),MONTH(SUMMARY!$C$6)+0,1)))/COUNTIFS(KALENDER!$D$3:$D$132,"Hari Kerja",KALENDER!$C$3:$C$132,MONTH(DATE(YEAR(SUMMARY!$C$6),MONTH(SUMMARY!$C$6)+0,1))),0) -> 1.9375 | H57: =IFERROR(SUMIFS(DETAIL!$I$2:$I$137,DETAIL!$S$2:$S$137,$B57,DETAIL!$F$2:$F$137,MONTH(DATE(YEAR(SUMMARY!$C$6),MONTH(SUMMARY!$C$6)+1,1)))/COUNTIFS(KALENDER!$D$3:$D$132,"Hari Kerja",KALENDER!$C$3:$C$132,MONTH(DATE(YEAR(SUMMARY!$C$6),MONTH(SUMMARY!$C$6)+1,1))),0) -> 1 | I57: =IFERROR(SUMIFS(DETAIL!$I$2:$I$137,DETAIL!$S$2:$S$137,$B57,DETAIL!$F$2:$F$137,MONTH(DATE(YEAR(SUMMARY!$C$6),MONTH(SUMMARY!$C$6)+2,1)))/COUNTIFS(KALENDER!$D$3:$D$132,"Hari Kerja",KALENDER!$C$3:$C$132,MONTH(DATE(YEAR(SUMMARY!$C$6),MONTH(SUMMARY!$C$6)+2,1))),0) -> 1 | J57: =IFERROR(SUMIFS(DETAIL!$I$2:$I$137,DETAIL!$S$2:$S$137,$B57,DETAIL!$F$2:$F$137,MONTH(DATE(YEAR(SUMMARY!$C$6),MONTH(SUMMARY!$C$6)+3,1)))/COUNTIFS(KALENDER!$D$3:$D$132,"Hari Kerja",KALENDER!$C$3:$C$132,MONTH(DATE(YEAR(SUMMARY!$C$6),MONTH(SUMMARY!$C$6)+3,1))),0) -> 1 | K57: =IFERROR(SUMIFS(DETAIL!$R$2:$R$137,DETAIL!$S$2:$S$137,$B57,DETAIL!$F$2:$F$137,MONTH(DATE(YEAR(SUMMARY!$C$6),MONTH(SUMMARY!$C$6)+0,1)))/SUMIFS(DETAIL!$M$2:$M$137,DETAIL!$S$2:$S$137,$B57,DETAIL!$F$2:$F$137,MONTH(DATE(YEAR(SUMMARY!$C$6),MONTH(SUMMARY!$C$6)+0,1))),"-") -> 1.8666667 | L57: =IFERROR(SUMIFS(DETAIL!$R$2:$R$137,DETAIL!$S$2:$S$137,$B57,DETAIL!$F$2:$F$137,MONTH(DATE(YEAR(SUMMARY!$C$6),MONTH(SUMMARY!$C$6)+1,1)))/SUMIFS(DETAIL!$M$2:$M$137,DETAIL!$S$2:$S$137,$B57,DETAIL!$F$2:$F$137,MONTH(DATE(YEAR(SUMMARY!$C$6),MONTH(SUMMARY!$C$6)+1,1))),"-") -> 3.0555556 | M57: =IFERROR(SUMIFS(DETAIL!$R$2:$R$137,DETAIL!$S$2:$S$137,$B57,DETAIL!$F$2:$F$137,MONTH(DATE(YEAR(SUMMARY!$C$6),MONTH(SUMMARY!$C$6)+2,1)))/SUMIFS(DETAIL!$M$2:$M$137,DETAIL!$S$2:$S$137,$B57,DETAIL!$F$2:$F$137,MONTH(DATE(YEAR(SUMMARY!$C$6),MONTH(SUMMARY!$C$6)+2,1))),"-") -> 2.6842105 | N57: =IFERROR(SUMIFS(DETAIL!$R$2:$R$137,DETAIL!$S$2:$S$137,$B57,DETAIL!$F$2:$F$137,MONTH(DATE(YEAR(SUMMARY!$C$6),MONTH(SUMMARY!$C$6)+3,1)))/SUMIFS(DETAIL!$M$2:$M$137,DETAIL!$S$2:$S$137,$B57,DETAIL!$F$2:$F$137,MONTH(DATE(YEAR(SUMMARY!$C$6),MONTH(SUMMARY!$C$6)+3,1))),"-") -> 1.8333333
A58: 2 | B58: =B35 -> EQUALISATION OFFICER (SID) | C58: =COUNTIFS(DETAIL!$S$2:$S$137,$B58,DETAIL!$F$2:$F$137,MONTH(DATE(YEAR(SUMMARY!$C$6),MONTH(SUMMARY!$C$6)+0,1)),DETAIL!$I$2:$I$137,">0") -> 1 | D58: =COUNTIFS(DETAIL!$S$2:$S$137,$B58,DETAIL!$F$2:$F$137,MONTH(DATE(YEAR(SUMMARY!$C$6),MONTH(SUMMARY!$C$6)+1,1)),DETAIL!$I$2:$I$137,">0") -> 1 | E58: =COUNTIFS(DETAIL!$S$2:$S$137,$B58,DETAIL!$F$2:$F$137,MONTH(DATE(YEAR(SUMMARY!$C$6),MONTH(SUMMARY!$C$6)+2,1)),DETAIL!$I$2:$I$137,">0") -> 1 | F58: =COUNTIFS(DETAIL!$S$2:$S$137,$B58,DETAIL!$F$2:$F$137,MONTH(DATE(YEAR(SUMMARY!$C$6),MONTH(SUMMARY!$C$6)+3,1)),DETAIL!$I$2:$I$137,">0") -> 1 | G58: =IFERROR(SUMIFS(DETAIL!$I$2:$I$137,DETAIL!$S$2:$S$137,$B58,DETAIL!$F$2:$F$137,MONTH(DATE(YEAR(SUMMARY!$C$6),MONTH(SUMMARY!$C$6)+0,1)))/COUNTIFS(KALENDER!$D$3:$D$132,"Hari Kerja",KALENDER!$C$3:$C$132,MONTH(DATE(YEAR(SUMMARY!$C$6),MONTH(SUMMARY!$C$6)+0,1))),0) -> 1 | H58: =IFERROR(SUMIFS(DETAIL!$I$2:$I$137,DETAIL!$S$2:$S$137,$B58,DETAIL!$F$2:$F$137,MONTH(DATE(YEAR(SUMMARY!$C$6),MONTH(SUMMARY!$C$6)+1,1)))/COUNTIFS(KALENDER!$D$3:$D$132,"Hari Kerja",KALENDER!$C$3:$C$132,MONTH(DATE(YEAR(SUMMARY!$C$6),MONTH(SUMMARY!$C$6)+1,1))),0) -> 1 | I58: =IFERROR(SUMIFS(DETAIL!$I$2:$I$137,DETAIL!$S$2:$S$137,$B58,DETAIL!$F$2:$F$137,MONTH(DATE(YEAR(SUMMARY!$C$6),MONTH(SUMMARY!$C$6)+2,1)))/COUNTIFS(KALENDER!$D$3:$D$132,"Hari Kerja",KALENDER!$C$3:$C$132,MONTH(DATE(YEAR(SUMMARY!$C$6),MONTH(SUMMARY!$C$6)+2,1))),0) -> 1 | J58: =IFERROR(SUMIFS(DETAIL!$I$2:$I$137,DETAIL!$S$2:$S$137,$B58,DETAIL!$F$2:$F$137,MONTH(DATE(YEAR(SUMMARY!$C$6),MONTH(SUMMARY!$C$6)+3,1)))/COUNTIFS(KALENDER!$D$3:$D$132,"Hari Kerja",KALENDER!$C$3:$C$132,MONTH(DATE(YEAR(SUMMARY!$C$6),MONTH(SUMMARY!$C$6)+3,1))),0) -> 1 | K58: =IFERROR(SUMIFS(DETAIL!$R$2:$R$137,DETAIL!$S$2:$S$137,$B58,DETAIL!$F$2:$F$137,MONTH(DATE(YEAR(SUMMARY!$C$6),MONTH(SUMMARY!$C$6)+0,1)))/SUMIFS(DETAIL!$M$2:$M$137,DETAIL!$S$2:$S$137,$B58,DETAIL!$F$2:$F$137,MONTH(DATE(YEAR(SUMMARY!$C$6),MONTH(SUMMARY!$C$6)+0,1))),"-") -> 1.4444444 | L58: =IFERROR(SUMIFS(DETAIL!$R$2:$R$137,DETAIL!$S$2:$S$137,$B58,DETAIL!$F$2:$F$137,MONTH(DATE(YEAR(SUMMARY!$C$6),MONTH(SUMMARY!$C$6)+1,1)))/SUMIFS(DETAIL!$M$2:$M$137,DETAIL!$S$2:$S$137,$B58,DETAIL!$F$2:$F$137,MONTH(DATE(YEAR(SUMMARY!$C$6),MONTH(SUMMARY!$C$6)+1,1))),"-") -> 1.375 | M58: =IFERROR(SUMIFS(DETAIL!$R$2:$R$137,DETAIL!$S$2:$S$137,$B58,DETAIL!$F$2:$F$137,MONTH(DATE(YEAR(SUMMARY!$C$6),MONTH(SUMMARY!$C$6)+2,1)))/SUMIFS(DETAIL!$M$2:$M$137,DETAIL!$S$2:$S$137,$B58,DETAIL!$F$2:$F$137,MONTH(DATE(YEAR(SUMMARY!$C$6),MONTH(SUMMARY!$C$6)+2,1))),"-") -> 1.5555556 | N58: =IFERROR(SUMIFS(DETAIL!$R$2:$R$137,DETAIL!$S$2:$S$137,$B58,DETAIL!$F$2:$F$137,MONTH(DATE(YEAR(SUMMARY!$C$6),MONTH(SUMMARY!$C$6)+3,1)))/SUMIFS(DETAIL!$M$2:$M$137,DETAIL!$S$2:$S$137,$B58,DETAIL!$F$2:$F$137,MONTH(DATE(YEAR(SUMMARY!$C$6),MONTH(SUMMARY!$C$6)+3,1))),"-") -> 2.0454545
A59: 3 | B59: =B36 -> GM OF TAX & ACCOUNTING | C59: =COUNTIFS(DETAIL!$S$2:$S$137,$B59,DETAIL!$F$2:$F$137,MONTH(DATE(YEAR(SUMMARY!$C$6),MONTH(SUMMARY!$C$6)+0,1)),DETAIL!$I$2:$I$137,">0") -> 0 | D59: =COUNTIFS(DETAIL!$S$2:$S$137,$B59,DETAIL!$F$2:$F$137,MONTH(DATE(YEAR(SUMMARY!$C$6),MONTH(SUMMARY!$C$6)+1,1)),DETAIL!$I$2:$I$137,">0") -> 0 | E59: =COUNTIFS(DETAIL!$S$2:$S$137,$B59,DETAIL!$F$2:$F$137,MONTH(DATE(YEAR(SUMMARY!$C$6),MONTH(SUMMARY!$C$6)+2,1)),DETAIL!$I$2:$I$137,">0") -> 1 | F59: =COUNTIFS(DETAIL!$S$2:$S$137,$B59,DETAIL!$F$2:$F$137,MONTH(DATE(YEAR(SUMMARY!$C$6),MONTH(SUMMARY!$C$6)+3,1)),DETAIL!$I$2:$I$137,">0") -> 1 | G59: =IFERROR(SUMIFS(DETAIL!$I$2:$I$137,DETAIL!$S$2:$S$137,$B59,DETAIL!$F$2:$F$137,MONTH(DATE(YEAR(SUMMARY!$C$6),MONTH(SUMMARY!$C$6)+0,1)))/COUNTIFS(KALENDER!$D$3:$D$132,"Hari Kerja",KALENDER!$C$3:$C$132,MONTH(DATE(YEAR(SUMMARY!$C$6),MONTH(SUMMARY!$C$6)+0,1))),0) -> 0 | H59: =IFERROR(SUMIFS(DETAIL!$I$2:$I$137,DETAIL!$S$2:$S$137,$B59,DETAIL!$F$2:$F$137,MONTH(DATE(YEAR(SUMMARY!$C$6),MONTH(SUMMARY!$C$6)+1,1)))/COUNTIFS(KALENDER!$D$3:$D$132,"Hari Kerja",KALENDER!$C$3:$C$132,MONTH(DATE(YEAR(SUMMARY!$C$6),MONTH(SUMMARY!$C$6)+1,1))),0) -> 0 | I59: =IFERROR(SUMIFS(DETAIL!$I$2:$I$137,DETAIL!$S$2:$S$137,$B59,DETAIL!$F$2:$F$137,MONTH(DATE(YEAR(SUMMARY!$C$6),MONTH(SUMMARY!$C$6)+2,1)))/COUNTIFS(KALENDER!$D$3:$D$132,"Hari Kerja",KALENDER!$C$3:$C$132,MONTH(DATE(YEAR(SUMMARY!$C$6),MONTH(SUMMARY!$C$6)+2,1))),0) -> 0.73684211 | J59: =IFERROR(SUMIFS(DETAIL!$I$2:$I$137,DETAIL!$S$2:$S$137,$B59,DETAIL!$F$2:$F$137,MONTH(DATE(YEAR(SUMMARY!$C$6),MONTH(SUMMARY!$C$6)+3,1)))/COUNTIFS(KALENDER!$D$3:$D$132,"Hari Kerja",KALENDER!$C$3:$C$132,MONTH(DATE(YEAR(SUMMARY!$C$6),MONTH(SUMMARY!$C$6)+3,1))),0) -> 1 | K59: =IFERROR(SUMIFS(DETAIL!$R$2:$R$137,DETAIL!$S$2:$S$137,$B59,DETAIL!$F$2:$F$137,MONTH(DATE(YEAR(SUMMARY!$C$6),MONTH(SUMMARY!$C$6)+0,1)))/SUMIFS(DETAIL!$M$2:$M$137,DETAIL!$S$2:$S$137,$B59,DETAIL!$F$2:$F$137,MONTH(DATE(YEAR(SUMMARY!$C$6),MONTH(SUMMARY!$C$6)+0,1))),"-") -> - | L59: =IFERROR(SUMIFS(DETAIL!$R$2:$R$137,DETAIL!$S$2:$S$137,$B59,DETAIL!$F$2:$F$137,MONTH(DATE(YEAR(SUMMARY!$C$6),MONTH(SUMMARY!$C$6)+1,1)))/SUMIFS(DETAIL!$M$2:$M$137,DETAIL!$S$2:$S$137,$B59,DETAIL!$F$2:$F$137,MONTH(DATE(YEAR(SUMMARY!$C$6),MONTH(SUMMARY!$C$6)+1,1))),"-") -> - | M59: =IFERROR(SUMIFS(DETAIL!$R$2:$R$137,DETAIL!$S$2:$S$137,$B59,DETAIL!$F$2:$F$137,MONTH(DATE(YEAR(SUMMARY!$C$6),MONTH(SUMMARY!$C$6)+2,1)))/SUMIFS(DETAIL!$M$2:$M$137,DETAIL!$S$2:$S$137,$B59,DETAIL!$F$2:$F$137,MONTH(DATE(YEAR(SUMMARY!$C$6),MONTH(SUMMARY!$C$6)+2,1))),"-") -> 1.3846154 | N59: =IFERROR(SUMIFS(DETAIL!$R$2:$R$137,DETAIL!$S$2:$S$137,$B59,DETAIL!$F$2:$F$137,MONTH(DATE(YEAR(SUMMARY!$C$6),MONTH(SUMMARY!$C$6)+3,1)))/SUMIFS(DETAIL!$M$2:$M$137,DETAIL!$S$2:$S$137,$B59,DETAIL!$F$2:$F$137,MONTH(DATE(YEAR(SUMMARY!$C$6),MONTH(SUMMARY!$C$6)+3,1))),"-") -> 1.55
A60: 4 | B60: =B37 -> MANAGER OF TRANSPORTATION | C60: =COUNTIFS(DETAIL!$S$2:$S$137,$B60,DETAIL!$F$2:$F$137,MONTH(DATE(YEAR(SUMMARY!$C$6),MONTH(SUMMARY!$C$6)+0,1)),DETAIL!$I$2:$I$137,">0") -> 1 | D60: =COUNTIFS(DETAIL!$S$2:$S$137,$B60,DETAIL!$F$2:$F$137,MONTH(DATE(YEAR(SUMMARY!$C$6),MONTH(SUMMARY!$C$6)+1,1)),DETAIL!$I$2:$I$137,">0") -> 2 | E60: =COUNTIFS(DETAIL!$S$2:$S$137,$B60,DETAIL!$F$2:$F$137,MONTH(DATE(YEAR(SUMMARY!$C$6),MONTH(SUMMARY!$C$6)+2,1)),DETAIL!$I$2:$I$137,">0") -> 2 | F60: =COUNTIFS(DETAIL!$S$2:$S$137,$B60,DETAIL!$F$2:$F$137,MONTH(DATE(YEAR(SUMMARY!$C$6),MONTH(SUMMARY!$C$6)+3,1)),DETAIL!$I$2:$I$137,">0") -> 2 | G60: =IFERROR(SUMIFS(DETAIL!$I$2:$I$137,DETAIL!$S$2:$S$137,$B60,DETAIL!$F$2:$F$137,MONTH(DATE(YEAR(SUMMARY!$C$6),MONTH(SUMMARY!$C$6)+0,1)))/COUNTIFS(KALENDER!$D$3:$D$132,"Hari Kerja",KALENDER!$C$3:$C$132,MONTH(DATE(YEAR(SUMMARY!$C$6),MONTH(SUMMARY!$C$6)+0,1))),0) -> 1 | H60: =IFERROR(SUMIFS(DETAIL!$I$2:$I$137,DETAIL!$S$2:$S$137,$B60,DETAIL!$F$2:$F$137,MONTH(DATE(YEAR(SUMMARY!$C$6),MONTH(SUMMARY!$C$6)+1,1)))/COUNTIFS(KALENDER!$D$3:$D$132,"Hari Kerja",KALENDER!$C$3:$C$132,MONTH(DATE(YEAR(SUMMARY!$C$6),MONTH(SUMMARY!$C$6)+1,1))),0) -> 2 | I60: =IFERROR(SUMIFS(DETAIL!$I$2:$I$137,DETAIL!$S$2:$S$137,$B60,DETAIL!$F$2:$F$137,MONTH(DATE(YEAR(SUMMARY!$C$6),MONTH(SUMMARY!$C$6)+2,1)))/COUNTIFS(KALENDER!$D$3:$D$132,"Hari Kerja",KALENDER!$C$3:$C$132,MONTH(DATE(YEAR(SUMMARY!$C$6),MONTH(SUMMARY!$C$6)+2,1))),0) -> 2 | J60: =IFERROR(SUMIFS(DETAIL!$I$2:$I$137,DETAIL!$S$2:$S$137,$B60,DETAIL!$F$2:$F$137,MONTH(DATE(YEAR(SUMMARY!$C$6),MONTH(SUMMARY!$C$6)+3,1)))/COUNTIFS(KALENDER!$D$3:$D$132,"Hari Kerja",KALENDER!$C$3:$C$132,MONTH(DATE(YEAR(SUMMARY!$C$6),MONTH(SUMMARY!$C$6)+3,1))),0) -> 2 | K60: =IFERROR(SUMIFS(DETAIL!$R$2:$R$137,DETAIL!$S$2:$S$137,$B60,DETAIL!$F$2:$F$137,MONTH(DATE(YEAR(SUMMARY!$C$6),MONTH(SUMMARY!$C$6)+0,1)))/SUMIFS(DETAIL!$M$2:$M$137,DETAIL!$S$2:$S$137,$B60,DETAIL!$F$2:$F$137,MONTH(DATE(YEAR(SUMMARY!$C$6),MONTH(SUMMARY!$C$6)+0,1))),"-") -> 2.6 | L60: =IFERROR(SUMIFS(DETAIL!$R$2:$R$137,DETAIL!$S$2:$S$137,$B60,DETAIL!$F$2:$F$137,MONTH(DATE(YEAR(SUMMARY!$C$6),MONTH(SUMMARY!$C$6)+1,1)))/SUMIFS(DETAIL!$M$2:$M$137,DETAIL!$S$2:$S$137,$B60,DETAIL!$F$2:$F$137,MONTH(DATE(YEAR(SUMMARY!$C$6),MONTH(SUMMARY!$C$6)+1,1))),"-") -> 2.0789474 | M60: =IFERROR(SUMIFS(DETAIL!$R$2:$R$137,DETAIL!$S$2:$S$137,$B60,DETAIL!$F$2:$F$137,MONTH(DATE(YEAR(SUMMARY!$C$6),MONTH(SUMMARY!$C$6)+2,1)))/SUMIFS(DETAIL!$M$2:$M$137,DETAIL!$S$2:$S$137,$B60,DETAIL!$F$2:$F$137,MONTH(DATE(YEAR(SUMMARY!$C$6),MONTH(SUMMARY!$C$6)+2,1))),"-") -> 2.3142857 | N60: =IFERROR(SUMIFS(DETAIL!$R$2:$R$137,DETAIL!$S$2:$S$137,$B60,DETAIL!$F$2:$F$137,MONTH(DATE(YEAR(SUMMARY!$C$6),MONTH(SUMMARY!$C$6)+3,1)))/SUMIFS(DETAIL!$M$2:$M$137,DETAIL!$S$2:$S$137,$B60,DETAIL!$F$2:$F$137,MONTH(DATE(YEAR(SUMMARY!$C$6),MONTH(SUMMARY!$C$6)+3,1))),"-") -> 1.9534884
A61: 5 | B61: =B38 -> MANAGER OF VERIFICATION | C61: =COUNTIFS(DETAIL!$S$2:$S$137,$B61,DETAIL!$F$2:$F$137,MONTH(DATE(YEAR(SUMMARY!$C$6),MONTH(SUMMARY!$C$6)+0,1)),DETAIL!$I$2:$I$137,">0") -> 0 | D61: =COUNTIFS(DETAIL!$S$2:$S$137,$B61,DETAIL!$F$2:$F$137,MONTH(DATE(YEAR(SUMMARY!$C$6),MONTH(SUMMARY!$C$6)+1,1)),DETAIL!$I$2:$I$137,">0") -> 0 | E61: =COUNTIFS(DETAIL!$S$2:$S$137,$B61,DETAIL!$F$2:$F$137,MONTH(DATE(YEAR(SUMMARY!$C$6),MONTH(SUMMARY!$C$6)+2,1)),DETAIL!$I$2:$I$137,">0") -> 0 | F61: =COUNTIFS(DETAIL!$S$2:$S$137,$B61,DETAIL!$F$2:$F$137,MONTH(DATE(YEAR(SUMMARY!$C$6),MONTH(SUMMARY!$C$6)+3,1)),DETAIL!$I$2:$I$137,">0") -> 1 | G61: =IFERROR(SUMIFS(DETAIL!$I$2:$I$137,DETAIL!$S$2:$S$137,$B61,DETAIL!$F$2:$F$137,MONTH(DATE(YEAR(SUMMARY!$C$6),MONTH(SUMMARY!$C$6)+0,1)))/COUNTIFS(KALENDER!$D$3:$D$132,"Hari Kerja",KALENDER!$C$3:$C$132,MONTH(DATE(YEAR(SUMMARY!$C$6),MONTH(SUMMARY!$C$6)+0,1))),0) -> 0 | H61: =IFERROR(SUMIFS(DETAIL!$I$2:$I$137,DETAIL!$S$2:$S$137,$B61,DETAIL!$F$2:$F$137,MONTH(DATE(YEAR(SUMMARY!$C$6),MONTH(SUMMARY!$C$6)+1,1)))/COUNTIFS(KALENDER!$D$3:$D$132,"Hari Kerja",KALENDER!$C$3:$C$132,MONTH(DATE(YEAR(SUMMARY!$C$6),MONTH(SUMMARY!$C$6)+1,1))),0) -> 0 | I61: =IFERROR(SUMIFS(DETAIL!$I$2:$I$137,DETAIL!$S$2:$S$137,$B61,DETAIL!$F$2:$F$137,MONTH(DATE(YEAR(SUMMARY!$C$6),MONTH(SUMMARY!$C$6)+2,1)))/COUNTIFS(KALENDER!$D$3:$D$132,"Hari Kerja",KALENDER!$C$3:$C$132,MONTH(DATE(YEAR(SUMMARY!$C$6),MONTH(SUMMARY!$C$6)+2,1))),0) -> 0 | J61: =IFERROR(SUMIFS(DETAIL!$I$2:$I$137,DETAIL!$S$2:$S$137,$B61,DETAIL!$F$2:$F$137,MONTH(DATE(YEAR(SUMMARY!$C$6),MONTH(SUMMARY!$C$6)+3,1)))/COUNTIFS(KALENDER!$D$3:$D$132,"Hari Kerja",KALENDER!$C$3:$C$132,MONTH(DATE(YEAR(SUMMARY!$C$6),MONTH(SUMMARY!$C$6)+3,1))),0) -> 0.59090909 | K61: =IFERROR(SUMIFS(DETAIL!$R$2:$R$137,DETAIL!$S$2:$S$137,$B61,DETAIL!$F$2:$F$137,MONTH(DATE(YEAR(SUMMARY!$C$6),MONTH(SUMMARY!$C$6)+0,1)))/SUMIFS(DETAIL!$M$2:$M$137,DETAIL!$S$2:$S$137,$B61,DETAIL!$F$2:$F$137,MONTH(DATE(YEAR(SUMMARY!$C$6),MONTH(SUMMARY!$C$6)+0,1))),"-") -> - | L61: =IFERROR(SUMIFS(DETAIL!$R$2:$R$137,DETAIL!$S$2:$S$137,$B61,DETAIL!$F$2:$F$137,MONTH(DATE(YEAR(SUMMARY!$C$6),MONTH(SUMMARY!$C$6)+1,1)))/SUMIFS(DETAIL!$M$2:$M$137,DETAIL!$S$2:$S$137,$B61,DETAIL!$F$2:$F$137,MONTH(DATE(YEAR(SUMMARY!$C$6),MONTH(SUMMARY!$C$6)+1,1))),"-") -> - | M61: =IFERROR(SUMIFS(DETAIL!$R$2:$R$137,DETAIL!$S$2:$S$137,$B61,DETAIL!$F$2:$F$137,MONTH(DATE(YEAR(SUMMARY!$C$6),MONTH(SUMMARY!$C$6)+2,1)))/SUMIFS(DETAIL!$M$2:$M$137,DETAIL!$S$2:$S$137,$B61,DETAIL!$F$2:$F$137,MONTH(DATE(YEAR(SUMMARY!$C$6),MONTH(SUMMARY!$C$6)+2,1))),"-") -> - | N61: =IFERROR(SUMIFS(DETAIL!$R$2:$R$137,DETAIL!$S$2:$S$137,$B61,DETAIL!$F$2:$F$137,MONTH(DATE(YEAR(SUMMARY!$C$6),MONTH(SUMMARY!$C$6)+3,1)))/SUMIFS(DETAIL!$M$2:$M$137,DETAIL!$S$2:$S$137,$B61,DETAIL!$F$2:$F$137,MONTH(DATE(YEAR(SUMMARY!$C$6),MONTH(SUMMARY!$C$6)+3,1))),"-") -> 1
A62: 6 | B62: =B39 -> MARKETING & EXPANSION MODERN RETAIL OFFICER | C62: =COUNTIFS(DETAIL!$S$2:$S$137,$B62,DETAIL!$F$2:$F$137,MONTH(DATE(YEAR(SUMMARY!$C$6),MONTH(SUMMARY!$C$6)+0,1)),DETAIL!$I$2:$I$137,">0") -> 1 | D62: =COUNTIFS(DETAIL!$S$2:$S$137,$B62,DETAIL!$F$2:$F$137,MONTH(DATE(YEAR(SUMMARY!$C$6),MONTH(SUMMARY!$C$6)+1,1)),DETAIL!$I$2:$I$137,">0") -> 1 | E62: =COUNTIFS(DETAIL!$S$2:$S$137,$B62,DETAIL!$F$2:$F$137,MONTH(DATE(YEAR(SUMMARY!$C$6),MONTH(SUMMARY!$C$6)+2,1)),DETAIL!$I$2:$I$137,">0") -> 1 | F62: =COUNTIFS(DETAIL!$S$2:$S$137,$B62,DETAIL!$F$2:$F$137,MONTH(DATE(YEAR(SUMMARY!$C$6),MONTH(SUMMARY!$C$6)+3,1)),DETAIL!$I$2:$I$137,">0") -> 1 | G62: =IFERROR(SUMIFS(DETAIL!$I$2:$I$137,DETAIL!$S$2:$S$137,$B62,DETAIL!$F$2:$F$137,MONTH(DATE(YEAR(SUMMARY!$C$6),MONTH(SUMMARY!$C$6)+0,1)))/COUNTIFS(KALENDER!$D$3:$D$132,"Hari Kerja",KALENDER!$C$3:$C$132,MONTH(DATE(YEAR(SUMMARY!$C$6),MONTH(SUMMARY!$C$6)+0,1))),0) -> 1 | H62: =IFERROR(SUMIFS(DETAIL!$I$2:$I$137,DETAIL!$S$2:$S$137,$B62,DETAIL!$F$2:$F$137,MONTH(DATE(YEAR(SUMMARY!$C$6),MONTH(SUMMARY!$C$6)+1,1)))/COUNTIFS(KALENDER!$D$3:$D$132,"Hari Kerja",KALENDER!$C$3:$C$132,MONTH(DATE(YEAR(SUMMARY!$C$6),MONTH(SUMMARY!$C$6)+1,1))),0) -> 1 | I62: =IFERROR(SUMIFS(DETAIL!$I$2:$I$137,DETAIL!$S$2:$S$137,$B62,DETAIL!$F$2:$F$137,MONTH(DATE(YEAR(SUMMARY!$C$6),MONTH(SUMMARY!$C$6)+2,1)))/COUNTIFS(KALENDER!$D$3:$D$132,"Hari Kerja",KALENDER!$C$3:$C$132,MONTH(DATE(YEAR(SUMMARY!$C$6),MONTH(SUMMARY!$C$6)+2,1))),0) -> 1 | J62: =IFERROR(SUMIFS(DETAIL!$I$2:$I$137,DETAIL!$S$2:$S$137,$B62,DETAIL!$F$2:$F$137,MONTH(DATE(YEAR(SUMMARY!$C$6),MONTH(SUMMARY!$C$6)+3,1)))/COUNTIFS(KALENDER!$D$3:$D$132,"Hari Kerja",KALENDER!$C$3:$C$132,MONTH(DATE(YEAR(SUMMARY!$C$6),MONTH(SUMMARY!$C$6)+3,1))),0) -> 1 | K62: =IFERROR(SUMIFS(DETAIL!$R$2:$R$137,DETAIL!$S$2:$S$137,$B62,DETAIL!$F$2:$F$137,MONTH(DATE(YEAR(SUMMARY!$C$6),MONTH(SUMMARY!$C$6)+0,1)))/SUMIFS(DETAIL!$M$2:$M$137,DETAIL!$S$2:$S$137,$B62,DETAIL!$F$2:$F$137,MONTH(DATE(YEAR(SUMMARY!$C$6),MONTH(SUMMARY!$C$6)+0,1))),"-") -> 1.6190476 | L62: =IFERROR(SUMIFS(DETAIL!$R$2:$R$137,DETAIL!$S$2:$S$137,$B62,DETAIL!$F$2:$F$137,MONTH(DATE(YEAR(SUMMARY!$C$6),MONTH(SUMMARY!$C$6)+1,1)))/SUMIFS(DETAIL!$M$2:$M$137,DETAIL!$S$2:$S$137,$B62,DETAIL!$F$2:$F$137,MONTH(DATE(YEAR(SUMMARY!$C$6),MONTH(SUMMARY!$C$6)+1,1))),"-") -> 2.0384615 | M62: =IFERROR(SUMIFS(DETAIL!$R$2:$R$137,DETAIL!$S$2:$S$137,$B62,DETAIL!$F$2:$F$137,MONTH(DATE(YEAR(SUMMARY!$C$6),MONTH(SUMMARY!$C$6)+2,1)))/SUMIFS(DETAIL!$M$2:$M$137,DETAIL!$S$2:$S$137,$B62,DETAIL!$F$2:$F$137,MONTH(DATE(YEAR(SUMMARY!$C$6),MONTH(SUMMARY!$C$6)+2,1))),"-") -> 1.5 | N62: =IFERROR(SUMIFS(DETAIL!$R$2:$R$137,DETAIL!$S$2:$S$137,$B62,DETAIL!$F$2:$F$137,MONTH(DATE(YEAR(SUMMARY!$C$6),MONTH(SUMMARY!$C$6)+3,1)))/SUMIFS(DETAIL!$M$2:$M$137,DETAIL!$S$2:$S$137,$B62,DETAIL!$F$2:$F$137,MONTH(DATE(YEAR(SUMMARY!$C$6),MONTH(SUMMARY!$C$6)+3,1))),"-") -> 1.36
A63: 7 | B63: =B40 -> PGS FINANCIAL ANALYSIS OFFICER | C63: =COUNTIFS(DETAIL!$S$2:$S$137,$B63,DETAIL!$F$2:$F$137,MONTH(DATE(YEAR(SUMMARY!$C$6),MONTH(SUMMARY!$C$6)+0,1)),DETAIL!$I$2:$I$137,">0") -> 1 | D63: =COUNTIFS(DETAIL!$S$2:$S$137,$B63,DETAIL!$F$2:$F$137,MONTH(DATE(YEAR(SUMMARY!$C$6),MONTH(SUMMARY!$C$6)+1,1)),DETAIL!$I$2:$I$137,">0") -> 1 | E63: =COUNTIFS(DETAIL!$S$2:$S$137,$B63,DETAIL!$F$2:$F$137,MONTH(DATE(YEAR(SUMMARY!$C$6),MONTH(SUMMARY!$C$6)+2,1)),DETAIL!$I$2:$I$137,">0") -> 1 | F63: =COUNTIFS(DETAIL!$S$2:$S$137,$B63,DETAIL!$F$2:$F$137,MONTH(DATE(YEAR(SUMMARY!$C$6),MONTH(SUMMARY!$C$6)+3,1)),DETAIL!$I$2:$I$137,">0") -> 1 | G63: =IFERROR(SUMIFS(DETAIL!$I$2:$I$137,DETAIL!$S$2:$S$137,$B63,DETAIL!$F$2:$F$137,MONTH(DATE(YEAR(SUMMARY!$C$6),MONTH(SUMMARY!$C$6)+0,1)))/COUNTIFS(KALENDER!$D$3:$D$132,"Hari Kerja",KALENDER!$C$3:$C$132,MONTH(DATE(YEAR(SUMMARY!$C$6),MONTH(SUMMARY!$C$6)+0,1))),0) -> 1 | H63: =IFERROR(SUMIFS(DETAIL!$I$2:$I$137,DETAIL!$S$2:$S$137,$B63,DETAIL!$F$2:$F$137,MONTH(DATE(YEAR(SUMMARY!$C$6),MONTH(SUMMARY!$C$6)+1,1)))/COUNTIFS(KALENDER!$D$3:$D$132,"Hari Kerja",KALENDER!$C$3:$C$132,MONTH(DATE(YEAR(SUMMARY!$C$6),MONTH(SUMMARY!$C$6)+1,1))),0) -> 1 | I63: =IFERROR(SUMIFS(DETAIL!$I$2:$I$137,DETAIL!$S$2:$S$137,$B63,DETAIL!$F$2:$F$137,MONTH(DATE(YEAR(SUMMARY!$C$6),MONTH(SUMMARY!$C$6)+2,1)))/COUNTIFS(KALENDER!$D$3:$D$132,"Hari Kerja",KALENDER!$C$3:$C$132,MONTH(DATE(YEAR(SUMMARY!$C$6),MONTH(SUMMARY!$C$6)+2,1))),0) -> 1 | J63: =IFERROR(SUMIFS(DETAIL!$I$2:$I$137,DETAIL!$S$2:$S$137,$B63,DETAIL!$F$2:$F$137,MONTH(DATE(YEAR(SUMMARY!$C$6),MONTH(SUMMARY!$C$6)+3,1)))/COUNTIFS(KALENDER!$D$3:$D$132,"Hari Kerja",KALENDER!$C$3:$C$132,MONTH(DATE(YEAR(SUMMARY!$C$6),MONTH(SUMMARY!$C$6)+3,1))),0) -> 1 | K63: =IFERROR(SUMIFS(DETAIL!$R$2:$R$137,DETAIL!$S$2:$S$137,$B63,DETAIL!$F$2:$F$137,MONTH(DATE(YEAR(SUMMARY!$C$6),MONTH(SUMMARY!$C$6)+0,1)))/SUMIFS(DETAIL!$M$2:$M$137,DETAIL!$S$2:$S$137,$B63,DETAIL!$F$2:$F$137,MONTH(DATE(YEAR(SUMMARY!$C$6),MONTH(SUMMARY!$C$6)+0,1))),"-") -> 2.6 | L63: =IFERROR(SUMIFS(DETAIL!$R$2:$R$137,DETAIL!$S$2:$S$137,$B63,DETAIL!$F$2:$F$137,MONTH(DATE(YEAR(SUMMARY!$C$6),MONTH(SUMMARY!$C$6)+1,1)))/SUMIFS(DETAIL!$M$2:$M$137,DETAIL!$S$2:$S$137,$B63,DETAIL!$F$2:$F$137,MONTH(DATE(YEAR(SUMMARY!$C$6),MONTH(SUMMARY!$C$6)+1,1))),"-") -> 3.7058824 | M63: =IFERROR(SUMIFS(DETAIL!$R$2:$R$137,DETAIL!$S$2:$S$137,$B63,DETAIL!$F$2:$F$137,MONTH(DATE(YEAR(SUMMARY!$C$6),MONTH(SUMMARY!$C$6)+2,1)))/SUMIFS(DETAIL!$M$2:$M$137,DETAIL!$S$2:$S$137,$B63,DETAIL!$F$2:$F$137,MONTH(DATE(YEAR(SUMMARY!$C$6),MONTH(SUMMARY!$C$6)+2,1))),"-") -> 3.2631579 | N63: =IFERROR(SUMIFS(DETAIL!$R$2:$R$137,DETAIL!$S$2:$S$137,$B63,DETAIL!$F$2:$F$137,MONTH(DATE(YEAR(SUMMARY!$C$6),MONTH(SUMMARY!$C$6)+3,1)))/SUMIFS(DETAIL!$M$2:$M$137,DETAIL!$S$2:$S$137,$B63,DETAIL!$F$2:$F$137,MONTH(DATE(YEAR(SUMMARY!$C$6),MONTH(SUMMARY!$C$6)+3,1))),"-") -> 3.2272727
A64: 8 | B64: =B41 -> PGS MANAGER OF LAMONGAN BRANCH | C64: =COUNTIFS(DETAIL!$S$2:$S$137,$B64,DETAIL!$F$2:$F$137,MONTH(DATE(YEAR(SUMMARY!$C$6),MONTH(SUMMARY!$C$6)+0,1)),DETAIL!$I$2:$I$137,">0") -> 0 | D64: =COUNTIFS(DETAIL!$S$2:$S$137,$B64,DETAIL!$F$2:$F$137,MONTH(DATE(YEAR(SUMMARY!$C$6),MONTH(SUMMARY!$C$6)+1,1)),DETAIL!$I$2:$I$137,">0") -> 0 | E64: =COUNTIFS(DETAIL!$S$2:$S$137,$B64,DETAIL!$F$2:$F$137,MONTH(DATE(YEAR(SUMMARY!$C$6),MONTH(SUMMARY!$C$6)+2,1)),DETAIL!$I$2:$I$137,">0") -> 0 | F64: =COUNTIFS(DETAIL!$S$2:$S$137,$B64,DETAIL!$F$2:$F$137,MONTH(DATE(YEAR(SUMMARY!$C$6),MONTH(SUMMARY!$C$6)+3,1)),DETAIL!$I$2:$I$137,">0") -> 1 | G64: =IFERROR(SUMIFS(DETAIL!$I$2:$I$137,DETAIL!$S$2:$S$137,$B64,DETAIL!$F$2:$F$137,MONTH(DATE(YEAR(SUMMARY!$C$6),MONTH(SUMMARY!$C$6)+0,1)))/COUNTIFS(KALENDER!$D$3:$D$132,"Hari Kerja",KALENDER!$C$3:$C$132,MONTH(DATE(YEAR(SUMMARY!$C$6),MONTH(SUMMARY!$C$6)+0,1))),0) -> 0 | H64: =IFERROR(SUMIFS(DETAIL!$I$2:$I$137,DETAIL!$S$2:$S$137,$B64,DETAIL!$F$2:$F$137,MONTH(DATE(YEAR(SUMMARY!$C$6),MONTH(SUMMARY!$C$6)+1,1)))/COUNTIFS(KALENDER!$D$3:$D$132,"Hari Kerja",KALENDER!$C$3:$C$132,MONTH(DATE(YEAR(SUMMARY!$C$6),MONTH(SUMMARY!$C$6)+1,1))),0) -> 0 | I64: =IFERROR(SUMIFS(DETAIL!$I$2:$I$137,DETAIL!$S$2:$S$137,$B64,DETAIL!$F$2:$F$137,MONTH(DATE(YEAR(SUMMARY!$C$6),MONTH(SUMMARY!$C$6)+2,1)))/COUNTIFS(KALENDER!$D$3:$D$132,"Hari Kerja",KALENDER!$C$3:$C$132,MONTH(DATE(YEAR(SUMMARY!$C$6),MONTH(SUMMARY!$C$6)+2,1))),0) -> 0 | J64: =IFERROR(SUMIFS(DETAIL!$I$2:$I$137,DETAIL!$S$2:$S$137,$B64,DETAIL!$F$2:$F$137,MONTH(DATE(YEAR(SUMMARY!$C$6),MONTH(SUMMARY!$C$6)+3,1)))/COUNTIFS(KALENDER!$D$3:$D$132,"Hari Kerja",KALENDER!$C$3:$C$132,MONTH(DATE(YEAR(SUMMARY!$C$6),MONTH(SUMMARY!$C$6)+3,1))),0) -> 0.90909091 | K64: =IFERROR(SUMIFS(DETAIL!$R$2:$R$137,DETAIL!$S$2:$S$137,$B64,DETAIL!$F$2:$F$137,MONTH(DATE(YEAR(SUMMARY!$C$6),MONTH(SUMMARY!$C$6)+0,1)))/SUMIFS(DETAIL!$M$2:$M$137,DETAIL!$S$2:$S$137,$B64,DETAIL!$F$2:$F$137,MONTH(DATE(YEAR(SUMMARY!$C$6),MONTH(SUMMARY!$C$6)+0,1))),"-") -> - | L64: =IFERROR(SUMIFS(DETAIL!$R$2:$R$137,DETAIL!$S$2:$S$137,$B64,DETAIL!$F$2:$F$137,MONTH(DATE(YEAR(SUMMARY!$C$6),MONTH(SUMMARY!$C$6)+1,1)))/SUMIFS(DETAIL!$M$2:$M$137,DETAIL!$S$2:$S$137,$B64,DETAIL!$F$2:$F$137,MONTH(DATE(YEAR(SUMMARY!$C$6),MONTH(SUMMARY!$C$6)+1,1))),"-") -> - | M64: =IFERROR(SUMIFS(DETAIL!$R$2:$R$137,DETAIL!$S$2:$S$137,$B64,DETAIL!$F$2:$F$137,MONTH(DATE(YEAR(SUMMARY!$C$6),MONTH(SUMMARY!$C$6)+2,1)))/SUMIFS(DETAIL!$M$2:$M$137,DETAIL!$S$2:$S$137,$B64,DETAIL!$F$2:$F$137,MONTH(DATE(YEAR(SUMMARY!$C$6),MONTH(SUMMARY!$C$6)+2,1))),"-") -> - | N64: =IFERROR(SUMIFS(DETAIL!$R$2:$R$137,DETAIL!$S$2:$S$137,$B64,DETAIL!$F$2:$F$137,MONTH(DATE(YEAR(SUMMARY!$C$6),MONTH(SUMMARY!$C$6)+3,1)))/SUMIFS(DETAIL!$M$2:$M$137,DETAIL!$S$2:$S$137,$B64,DETAIL!$F$2:$F$137,MONTH(DATE(YEAR(SUMMARY!$C$6),MONTH(SUMMARY!$C$6)+3,1))),"-") -> 0
A65: 9 | B65: =B42 -> PGS SM OF DIGITAL BUSSINES | C65: =COUNTIFS(DETAIL!$S$2:$S$137,$B65,DETAIL!$F$2:$F$137,MONTH(DATE(YEAR(SUMMARY!$C$6),MONTH(SUMMARY!$C$6)+0,1)),DETAIL!$I$2:$I$137,">0") -> 5 | D65: =COUNTIFS(DETAIL!$S$2:$S$137,$B65,DETAIL!$F$2:$F$137,MONTH(DATE(YEAR(SUMMARY!$C$6),MONTH(SUMMARY!$C$6)+1,1)),DETAIL!$I$2:$I$137,">0") -> 5 | E65: =COUNTIFS(DETAIL!$S$2:$S$137,$B65,DETAIL!$F$2:$F$137,MONTH(DATE(YEAR(SUMMARY!$C$6),MONTH(SUMMARY!$C$6)+2,1)),DETAIL!$I$2:$I$137,">0") -> 8 | F65: =COUNTIFS(DETAIL!$S$2:$S$137,$B65,DETAIL!$F$2:$F$137,MONTH(DATE(YEAR(SUMMARY!$C$6),MONTH(SUMMARY!$C$6)+3,1)),DETAIL!$I$2:$I$137,">0") -> 8 | G65: =IFERROR(SUMIFS(DETAIL!$I$2:$I$137,DETAIL!$S$2:$S$137,$B65,DETAIL!$F$2:$F$137,MONTH(DATE(YEAR(SUMMARY!$C$6),MONTH(SUMMARY!$C$6)+0,1)))/COUNTIFS(KALENDER!$D$3:$D$132,"Hari Kerja",KALENDER!$C$3:$C$132,MONTH(DATE(YEAR(SUMMARY!$C$6),MONTH(SUMMARY!$C$6)+0,1))),0) -> 5 | H65: =IFERROR(SUMIFS(DETAIL!$I$2:$I$137,DETAIL!$S$2:$S$137,$B65,DETAIL!$F$2:$F$137,MONTH(DATE(YEAR(SUMMARY!$C$6),MONTH(SUMMARY!$C$6)+1,1)))/COUNTIFS(KALENDER!$D$3:$D$132,"Hari Kerja",KALENDER!$C$3:$C$132,MONTH(DATE(YEAR(SUMMARY!$C$6),MONTH(SUMMARY!$C$6)+1,1))),0) -> 5 | I65: =IFERROR(SUMIFS(DETAIL!$I$2:$I$137,DETAIL!$S$2:$S$137,$B65,DETAIL!$F$2:$F$137,MONTH(DATE(YEAR(SUMMARY!$C$6),MONTH(SUMMARY!$C$6)+2,1)))/COUNTIFS(KALENDER!$D$3:$D$132,"Hari Kerja",KALENDER!$C$3:$C$132,MONTH(DATE(YEAR(SUMMARY!$C$6),MONTH(SUMMARY!$C$6)+2,1))),0) -> 7.2105263 | J65: =IFERROR(SUMIFS(DETAIL!$I$2:$I$137,DETAIL!$S$2:$S$137,$B65,DETAIL!$F$2:$F$137,MONTH(DATE(YEAR(SUMMARY!$C$6),MONTH(SUMMARY!$C$6)+3,1)))/COUNTIFS(KALENDER!$D$3:$D$132,"Hari Kerja",KALENDER!$C$3:$C$132,MONTH(DATE(YEAR(SUMMARY!$C$6),MONTH(SUMMARY!$C$6)+3,1))),0) -> 8 | K65: =IFERROR(SUMIFS(DETAIL!$R$2:$R$137,DETAIL!$S$2:$S$137,$B65,DETAIL!$F$2:$F$137,MONTH(DATE(YEAR(SUMMARY!$C$6),MONTH(SUMMARY!$C$6)+0,1)))/SUMIFS(DETAIL!$M$2:$M$137,DETAIL!$S$2:$S$137,$B65,DETAIL!$F$2:$F$137,MONTH(DATE(YEAR(SUMMARY!$C$6),MONTH(SUMMARY!$C$6)+0,1))),"-") -> 1.5054945 | L65: =IFERROR(SUMIFS(DETAIL!$R$2:$R$137,DETAIL!$S$2:$S$137,$B65,DETAIL!$F$2:$F$137,MONTH(DATE(YEAR(SUMMARY!$C$6),MONTH(SUMMARY!$C$6)+1,1)))/SUMIFS(DETAIL!$M$2:$M$137,DETAIL!$S$2:$S$137,$B65,DETAIL!$F$2:$F$137,MONTH(DATE(YEAR(SUMMARY!$C$6),MONTH(SUMMARY!$C$6)+1,1))),"-") -> 1.8659794 | M65: =IFERROR(SUMIFS(DETAIL!$R$2:$R$137,DETAIL!$S$2:$S$137,$B65,DETAIL!$F$2:$F$137,MONTH(DATE(YEAR(SUMMARY!$C$6),MONTH(SUMMARY!$C$6)+2,1)))/SUMIFS(DETAIL!$M$2:$M$137,DETAIL!$S$2:$S$137,$B65,DETAIL!$F$2:$F$137,MONTH(DATE(YEAR(SUMMARY!$C$6),MONTH(SUMMARY!$C$6)+2,1))),"-") -> 1.8432836 | N65: =IFERROR(SUMIFS(DETAIL!$R$2:$R$137,DETAIL!$S$2:$S$137,$B65,DETAIL!$F$2:$F$137,MONTH(DATE(YEAR(SUMMARY!$C$6),MONTH(SUMMARY!$C$6)+3,1)))/SUMIFS(DETAIL!$M$2:$M$137,DETAIL!$S$2:$S$137,$B65,DETAIL!$F$2:$F$137,MONTH(DATE(YEAR(SUMMARY!$C$6),MONTH(SUMMARY!$C$6)+3,1))),"-") -> 1.9473684
A66: 10 | B66: =B43 -> PGS TREASURY (SID) OFFICER | C66: =COUNTIFS(DETAIL!$S$2:$S$137,$B66,DETAIL!$F$2:$F$137,MONTH(DATE(YEAR(SUMMARY!$C$6),MONTH(SUMMARY!$C$6)+0,1)),DETAIL!$I$2:$I$137,">0") -> 1 | D66: =COUNTIFS(DETAIL!$S$2:$S$137,$B66,DETAIL!$F$2:$F$137,MONTH(DATE(YEAR(SUMMARY!$C$6),MONTH(SUMMARY!$C$6)+1,1)),DETAIL!$I$2:$I$137,">0") -> 1 | E66: =COUNTIFS(DETAIL!$S$2:$S$137,$B66,DETAIL!$F$2:$F$137,MONTH(DATE(YEAR(SUMMARY!$C$6),MONTH(SUMMARY!$C$6)+2,1)),DETAIL!$I$2:$I$137,">0") -> 1 | F66: =COUNTIFS(DETAIL!$S$2:$S$137,$B66,DETAIL!$F$2:$F$137,MONTH(DATE(YEAR(SUMMARY!$C$6),MONTH(SUMMARY!$C$6)+3,1)),DETAIL!$I$2:$I$137,">0") -> 1 | G66: =IFERROR(SUMIFS(DETAIL!$I$2:$I$137,DETAIL!$S$2:$S$137,$B66,DETAIL!$F$2:$F$137,MONTH(DATE(YEAR(SUMMARY!$C$6),MONTH(SUMMARY!$C$6)+0,1)))/COUNTIFS(KALENDER!$D$3:$D$132,"Hari Kerja",KALENDER!$C$3:$C$132,MONTH(DATE(YEAR(SUMMARY!$C$6),MONTH(SUMMARY!$C$6)+0,1))),0) -> 1 | H66: =IFERROR(SUMIFS(DETAIL!$I$2:$I$137,DETAIL!$S$2:$S$137,$B66,DETAIL!$F$2:$F$137,MONTH(DATE(YEAR(SUMMARY!$C$6),MONTH(SUMMARY!$C$6)+1,1)))/COUNTIFS(KALENDER!$D$3:$D$132,"Hari Kerja",KALENDER!$C$3:$C$132,MONTH(DATE(YEAR(SUMMARY!$C$6),MONTH(SUMMARY!$C$6)+1,1))),0) -> 0.44444444 | I66: =IFERROR(SUMIFS(DETAIL!$I$2:$I$137,DETAIL!$S$2:$S$137,$B66,DETAIL!$F$2:$F$137,MONTH(DATE(YEAR(SUMMARY!$C$6),MONTH(SUMMARY!$C$6)+2,1)))/COUNTIFS(KALENDER!$D$3:$D$132,"Hari Kerja",KALENDER!$C$3:$C$132,MONTH(DATE(YEAR(SUMMARY!$C$6),MONTH(SUMMARY!$C$6)+2,1))),0) -> 1 | J66: =IFERROR(SUMIFS(DETAIL!$I$2:$I$137,DETAIL!$S$2:$S$137,$B66,DETAIL!$F$2:$F$137,MONTH(DATE(YEAR(SUMMARY!$C$6),MONTH(SUMMARY!$C$6)+3,1)))/COUNTIFS(KALENDER!$D$3:$D$132,"Hari Kerja",KALENDER!$C$3:$C$132,MONTH(DATE(YEAR(SUMMARY!$C$6),MONTH(SUMMARY!$C$6)+3,1))),0) -> 1 | K66: =IFERROR(SUMIFS(DETAIL!$R$2:$R$137,DETAIL!$S$2:$S$137,$B66,DETAIL!$F$2:$F$137,MONTH(DATE(YEAR(SUMMARY!$C$6),MONTH(SUMMARY!$C$6)+0,1)))/SUMIFS(DETAIL!$M$2:$M$137,DETAIL!$S$2:$S$137,$B66,DETAIL!$F$2:$F$137,MONTH(DATE(YEAR(SUMMARY!$C$6),MONTH(SUMMARY!$C$6)+0,1))),"-") -> 1.0625 | L66: =IFERROR(SUMIFS(DETAIL!$R$2:$R$137,DETAIL!$S$2:$S$137,$B66,DETAIL!$F$2:$F$137,MONTH(DATE(YEAR(SUMMARY!$C$6),MONTH(SUMMARY!$C$6)+1,1)))/SUMIFS(DETAIL!$M$2:$M$137,DETAIL!$S$2:$S$137,$B66,DETAIL!$F$2:$F$137,MONTH(DATE(YEAR(SUMMARY!$C$6),MONTH(SUMMARY!$C$6)+1,1))),"-") -> 1.1428571 | M66: =IFERROR(SUMIFS(DETAIL!$R$2:$R$137,DETAIL!$S$2:$S$137,$B66,DETAIL!$F$2:$F$137,MONTH(DATE(YEAR(SUMMARY!$C$6),MONTH(SUMMARY!$C$6)+2,1)))/SUMIFS(DETAIL!$M$2:$M$137,DETAIL!$S$2:$S$137,$B66,DETAIL!$F$2:$F$137,MONTH(DATE(YEAR(SUMMARY!$C$6),MONTH(SUMMARY!$C$6)+2,1))),"-") -> 1 | N66: =IFERROR(SUMIFS(DETAIL!$R$2:$R$137,DETAIL!$S$2:$S$137,$B66,DETAIL!$F$2:$F$137,MONTH(DATE(YEAR(SUMMARY!$C$6),MONTH(SUMMARY!$C$6)+3,1)))/SUMIFS(DETAIL!$M$2:$M$137,DETAIL!$S$2:$S$137,$B66,DETAIL!$F$2:$F$137,MONTH(DATE(YEAR(SUMMARY!$C$6),MONTH(SUMMARY!$C$6)+3,1))),"-") -> 1
A67: 11 | B67: =B44 -> PJ GM OF MARKETING (SID) | C67: =COUNTIFS(DETAIL!$S$2:$S$137,$B67,DETAIL!$F$2:$F$137,MONTH(DATE(YEAR(SUMMARY!$C$6),MONTH(SUMMARY!$C$6)+0,1)),DETAIL!$I$2:$I$137,">0") -> 1 | D67: =COUNTIFS(DETAIL!$S$2:$S$137,$B67,DETAIL!$F$2:$F$137,MONTH(DATE(YEAR(SUMMARY!$C$6),MONTH(SUMMARY!$C$6)+1,1)),DETAIL!$I$2:$I$137,">0") -> 1 | E67: =COUNTIFS(DETAIL!$S$2:$S$137,$B67,DETAIL!$F$2:$F$137,MONTH(DATE(YEAR(SUMMARY!$C$6),MONTH(SUMMARY!$C$6)+2,1)),DETAIL!$I$2:$I$137,">0") -> 1 | F67: =COUNTIFS(DETAIL!$S$2:$S$137,$B67,DETAIL!$F$2:$F$137,MONTH(DATE(YEAR(SUMMARY!$C$6),MONTH(SUMMARY!$C$6)+3,1)),DETAIL!$I$2:$I$137,">0") -> 1 | G67: =IFERROR(SUMIFS(DETAIL!$I$2:$I$137,DETAIL!$S$2:$S$137,$B67,DETAIL!$F$2:$F$137,MONTH(DATE(YEAR(SUMMARY!$C$6),MONTH(SUMMARY!$C$6)+0,1)))/COUNTIFS(KALENDER!$D$3:$D$132,"Hari Kerja",KALENDER!$C$3:$C$132,MONTH(DATE(YEAR(SUMMARY!$C$6),MONTH(SUMMARY!$C$6)+0,1))),0) -> 1 | H67: =IFERROR(SUMIFS(DETAIL!$I$2:$I$137,DETAIL!$S$2:$S$137,$B67,DETAIL!$F$2:$F$137,MONTH(DATE(YEAR(SUMMARY!$C$6),MONTH(SUMMARY!$C$6)+1,1)))/COUNTIFS(KALENDER!$D$3:$D$132,"Hari Kerja",KALENDER!$C$3:$C$132,MONTH(DATE(YEAR(SUMMARY!$C$6),MONTH(SUMMARY!$C$6)+1,1))),0) -> 1 | I67: =IFERROR(SUMIFS(DETAIL!$I$2:$I$137,DETAIL!$S$2:$S$137,$B67,DETAIL!$F$2:$F$137,MONTH(DATE(YEAR(SUMMARY!$C$6),MONTH(SUMMARY!$C$6)+2,1)))/COUNTIFS(KALENDER!$D$3:$D$132,"Hari Kerja",KALENDER!$C$3:$C$132,MONTH(DATE(YEAR(SUMMARY!$C$6),MONTH(SUMMARY!$C$6)+2,1))),0) -> 0.94736842 | J67: =IFERROR(SUMIFS(DETAIL!$I$2:$I$137,DETAIL!$S$2:$S$137,$B67,DETAIL!$F$2:$F$137,MONTH(DATE(YEAR(SUMMARY!$C$6),MONTH(SUMMARY!$C$6)+3,1)))/COUNTIFS(KALENDER!$D$3:$D$132,"Hari Kerja",KALENDER!$C$3:$C$132,MONTH(DATE(YEAR(SUMMARY!$C$6),MONTH(SUMMARY!$C$6)+3,1))),0) -> 0.31818182 | K67: =IFERROR(SUMIFS(DETAIL!$R$2:$R$137,DETAIL!$S$2:$S$137,$B67,DETAIL!$F$2:$F$137,MONTH(DATE(YEAR(SUMMARY!$C$6),MONTH(SUMMARY!$C$6)+0,1)))/SUMIFS(DETAIL!$M$2:$M$137,DETAIL!$S$2:$S$137,$B67,DETAIL!$F$2:$F$137,MONTH(DATE(YEAR(SUMMARY!$C$6),MONTH(SUMMARY!$C$6)+0,1))),"-") -> 0.9375 | L67: =IFERROR(SUMIFS(DETAIL!$R$2:$R$137,DETAIL!$S$2:$S$137,$B67,DETAIL!$F$2:$F$137,MONTH(DATE(YEAR(SUMMARY!$C$6),MONTH(SUMMARY!$C$6)+1,1)))/SUMIFS(DETAIL!$M$2:$M$137,DETAIL!$S$2:$S$137,$B67,DETAIL!$F$2:$F$137,MONTH(DATE(YEAR(SUMMARY!$C$6),MONTH(SUMMARY!$C$6)+1,1))),"-") -> 2.1818182 | M67: =IFERROR(SUMIFS(DETAIL!$R$2:$R$137,DETAIL!$S$2:$S$137,$B67,DETAIL!$F$2:$F$137,MONTH(DATE(YEAR(SUMMARY!$C$6),MONTH(SUMMARY!$C$6)+2,1)))/SUMIFS(DETAIL!$M$2:$M$137,DETAIL!$S$2:$S$137,$B67,DETAIL!$F$2:$F$137,MONTH(DATE(YEAR(SUMMARY!$C$6),MONTH(SUMMARY!$C$6)+2,1))),"-") -> 1.75 | N67: =IFERROR(SUMIFS(DETAIL!$R$2:$R$137,DETAIL!$S$2:$S$137,$B67,DETAIL!$F$2:$F$137,MONTH(DATE(YEAR(SUMMARY!$C$6),MONTH(SUMMARY!$C$6)+3,1)))/SUMIFS(DETAIL!$M$2:$M$137,DETAIL!$S$2:$S$137,$B67,DETAIL!$F$2:$F$137,MONTH(DATE(YEAR(SUMMARY!$C$6),MONTH(SUMMARY!$C$6)+3,1))),"-") -> 2.1666667
A68: 12 | B68: =B45 -> PKSDM | C68: =COUNTIFS(DETAIL!$S$2:$S$137,$B68,DETAIL!$F$2:$F$137,MONTH(DATE(YEAR(SUMMARY!$C$6),MONTH(SUMMARY!$C$6)+0,1)),DETAIL!$I$2:$I$137,">0") -> 1 | D68: =COUNTIFS(DETAIL!$S$2:$S$137,$B68,DETAIL!$F$2:$F$137,MONTH(DATE(YEAR(SUMMARY!$C$6),MONTH(SUMMARY!$C$6)+1,1)),DETAIL!$I$2:$I$137,">0") -> 1 | E68: =COUNTIFS(DETAIL!$S$2:$S$137,$B68,DETAIL!$F$2:$F$137,MONTH(DATE(YEAR(SUMMARY!$C$6),MONTH(SUMMARY!$C$6)+2,1)),DETAIL!$I$2:$I$137,">0") -> 1 | F68: =COUNTIFS(DETAIL!$S$2:$S$137,$B68,DETAIL!$F$2:$F$137,MONTH(DATE(YEAR(SUMMARY!$C$6),MONTH(SUMMARY!$C$6)+3,1)),DETAIL!$I$2:$I$137,">0") -> 1 | G68: =IFERROR(SUMIFS(DETAIL!$I$2:$I$137,DETAIL!$S$2:$S$137,$B68,DETAIL!$F$2:$F$137,MONTH(DATE(YEAR(SUMMARY!$C$6),MONTH(SUMMARY!$C$6)+0,1)))/COUNTIFS(KALENDER!$D$3:$D$132,"Hari Kerja",KALENDER!$C$3:$C$132,MONTH(DATE(YEAR(SUMMARY!$C$6),MONTH(SUMMARY!$C$6)+0,1))),0) -> 1 | H68: =IFERROR(SUMIFS(DETAIL!$I$2:$I$137,DETAIL!$S$2:$S$137,$B68,DETAIL!$F$2:$F$137,MONTH(DATE(YEAR(SUMMARY!$C$6),MONTH(SUMMARY!$C$6)+1,1)))/COUNTIFS(KALENDER!$D$3:$D$132,"Hari Kerja",KALENDER!$C$3:$C$132,MONTH(DATE(YEAR(SUMMARY!$C$6),MONTH(SUMMARY!$C$6)+1,1))),0) -> 1 | I68: =IFERROR(SUMIFS(DETAIL!$I$2:$I$137,DETAIL!$S$2:$S$137,$B68,DETAIL!$F$2:$F$137,MONTH(DATE(YEAR(SUMMARY!$C$6),MONTH(SUMMARY!$C$6)+2,1)))/COUNTIFS(KALENDER!$D$3:$D$132,"Hari Kerja",KALENDER!$C$3:$C$132,MONTH(DATE(YEAR(SUMMARY!$C$6),MONTH(SUMMARY!$C$6)+2,1))),0) -> 1 | J68: =IFERROR(SUMIFS(DETAIL!$I$2:$I$137,DETAIL!$S$2:$S$137,$B68,DETAIL!$F$2:$F$137,MONTH(DATE(YEAR(SUMMARY!$C$6),MONTH(SUMMARY!$C$6)+3,1)))/COUNTIFS(KALENDER!$D$3:$D$132,"Hari Kerja",KALENDER!$C$3:$C$132,MONTH(DATE(YEAR(SUMMARY!$C$6),MONTH(SUMMARY!$C$6)+3,1))),0) -> 1 | K68: =IFERROR(SUMIFS(DETAIL!$R$2:$R$137,DETAIL!$S$2:$S$137,$B68,DETAIL!$F$2:$F$137,MONTH(DATE(YEAR(SUMMARY!$C$6),MONTH(SUMMARY!$C$6)+0,1)))/SUMIFS(DETAIL!$M$2:$M$137,DETAIL!$S$2:$S$137,$B68,DETAIL!$F$2:$F$137,MONTH(DATE(YEAR(SUMMARY!$C$6),MONTH(SUMMARY!$C$6)+0,1))),"-") -> 3.4705882 | L68: =IFERROR(SUMIFS(DETAIL!$R$2:$R$137,DETAIL!$S$2:$S$137,$B68,DETAIL!$F$2:$F$137,MONTH(DATE(YEAR(SUMMARY!$C$6),MONTH(SUMMARY!$C$6)+1,1)))/SUMIFS(DETAIL!$M$2:$M$137,DETAIL!$S$2:$S$137,$B68,DETAIL!$F$2:$F$137,MONTH(DATE(YEAR(SUMMARY!$C$6),MONTH(SUMMARY!$C$6)+1,1))),"-") -> 3.85 | M68: =IFERROR(SUMIFS(DETAIL!$R$2:$R$137,DETAIL!$S$2:$S$137,$B68,DETAIL!$F$2:$F$137,MONTH(DATE(YEAR(SUMMARY!$C$6),MONTH(SUMMARY!$C$6)+2,1)))/SUMIFS(DETAIL!$M$2:$M$137,DETAIL!$S$2:$S$137,$B68,DETAIL!$F$2:$F$137,MONTH(DATE(YEAR(SUMMARY!$C$6),MONTH(SUMMARY!$C$6)+2,1))),"-") -> 3.5 | N68: =IFERROR(SUMIFS(DETAIL!$R$2:$R$137,DETAIL!$S$2:$S$137,$B68,DETAIL!$F$2:$F$137,MONTH(DATE(YEAR(SUMMARY!$C$6),MONTH(SUMMARY!$C$6)+3,1)))/SUMIFS(DETAIL!$M$2:$M$137,DETAIL!$S$2:$S$137,$B68,DETAIL!$F$2:$F$137,MONTH(DATE(YEAR(SUMMARY!$C$6),MONTH(SUMMARY!$C$6)+3,1))),"-") -> 2.5714286
... A73: 17 | B73: =B50 -> VERIFICATION (SID) JR. OFFICER | C73: =COUNTIFS(DETAIL!$S$2:$S$137,$B73,DETAIL!$F$2:$F$137,MONTH(DATE(YEAR(SUMMARY!$C$6),MONTH(SUMMARY!$C$6)+0,1)),DETAIL!$I$2:$I$137,">0") -> 4 | D73: =COUNTIFS(DETAIL!$S$2:$S$137,$B73,DETAIL!$F$2:$F$137,MONTH(DATE(YEAR(SUMMARY!$C$6),MONTH(SUMMARY!$C$6)+1,1)),DETAIL!$I$2:$I$137,">0") -> 3 | E73: =COUNTIFS(DETAIL!$S$2:$S$137,$B73,DETAIL!$F$2:$F$137,MONTH(DATE(YEAR(SUMMARY!$C$6),MONTH(SUMMARY!$C$6)+2,1)),DETAIL!$I$2:$I$137,">0") -> 3 | F73: =COUNTIFS(DETAIL!$S$2:$S$137,$B73,DETAIL!$F$2:$F$137,MONTH(DATE(YEAR(SUMMARY!$C$6),MONTH(SUMMARY!$C$6)+3,1)),DETAIL!$I$2:$I$137,">0") -> 4 | G73: =IFERROR(SUMIFS(DETAIL!$I$2:$I$137,DETAIL!$S$2:$S$137,$B73,DETAIL!$F$2:$F$137,MONTH(DATE(YEAR(SUMMARY!$C$6),MONTH(SUMMARY!$C$6)+0,1)))/COUNTIFS(KALENDER!$D$3:$D$132,"Hari Kerja",KALENDER!$C$3:$C$132,MONTH(DATE(YEAR(SUMMARY!$C$6),MONTH(SUMMARY!$C$6)+0,1))),0) -> 3.9375 | H73: =IFERROR(SUMIFS(DETAIL!$I$2:$I$137,DETAIL!$S$2:$S$137,$B73,DETAIL!$F$2:$F$137,MONTH(DATE(YEAR(SUMMARY!$C$6),MONTH(SUMMARY!$C$6)+1,1)))/COUNTIFS(KALENDER!$D$3:$D$132,"Hari Kerja",KALENDER!$C$3:$C$132,MONTH(DATE(YEAR(SUMMARY!$C$6),MONTH(SUMMARY!$C$6)+1,1))),0) -> 3 | I73: =IFERROR(SUMIFS(DETAIL!$I$2:$I$137,DETAIL!$S$2:$S$137,$B73,DETAIL!$F$2:$F$137,MONTH(DATE(YEAR(SUMMARY!$C$6),MONTH(SUMMARY!$C$6)+2,1)))/COUNTIFS(KALENDER!$D$3:$D$132,"Hari Kerja",KALENDER!$C$3:$C$132,MONTH(DATE(YEAR(SUMMARY!$C$6),MONTH(SUMMARY!$C$6)+2,1))),0) -> 3 | J73: =IFERROR(SUMIFS(DETAIL!$I$2:$I$137,DETAIL!$S$2:$S$137,$B73,DETAIL!$F$2:$F$137,MONTH(DATE(YEAR(SUMMARY!$C$6),MONTH(SUMMARY!$C$6)+3,1)))/COUNTIFS(KALENDER!$D$3:$D$132,"Hari Kerja",KALENDER!$C$3:$C$132,MONTH(DATE(YEAR(SUMMARY!$C$6),MONTH(SUMMARY!$C$6)+3,1))),0) -> 3.0454545 | K73: =IFERROR(SUMIFS(DETAIL!$R$2:$R$137,DETAIL!$S$2:$S$137,$B73,DETAIL!$F$2:$F$137,MONTH(DATE(YEAR(SUMMARY!$C$6),MONTH(SUMMARY!$C$6)+0,1)))/SUMIFS(DETAIL!$M$2:$M$137,DETAIL!$S$2:$S$137,$B73,DETAIL!$F$2:$F$137,MONTH(DATE(YEAR(SUMMARY!$C$6),MONTH(SUMMARY!$C$6)+0,1))),"-") -> 1.421875 | L73: =IFERROR(SUMIFS(DETAIL!$R$2:$R$137,DETAIL!$S$2:$S$137,$B73,DETAIL!$F$2:$F$137,MONTH(DATE(YEAR(SUMMARY!$C$6),MONTH(SUMMARY!$C$6)+1,1)))/SUMIFS(DETAIL!$M$2:$M$137,DETAIL!$S$2:$S$137,$B73,DETAIL!$F$2:$F$137,MONTH(DATE(YEAR(SUMMARY!$C$6),MONTH(SUMMARY!$C$6)+1,1))),"-") -> 1.3278689 | M73: =IFERROR(SUMIFS(DETAIL!$R$2:$R$137,DETAIL!$S$2:$S$137,$B73,DETAIL!$F$2:$F$137,MONTH(DATE(YEAR(SUMMARY!$C$6),MONTH(SUMMARY!$C$6)+2,1)))/SUMIFS(DETAIL!$M$2:$M$137,DETAIL!$S$2:$S$137,$B73,DETAIL!$F$2:$F$137,MONTH(DATE(YEAR(SUMMARY!$C$6),MONTH(SUMMARY!$C$6)+2,1))),"-") -> 1.1403509 | N73: =IFERROR(SUMIFS(DETAIL!$R$2:$R$137,DETAIL!$S$2:$S$137,$B73,DETAIL!$F$2:$F$137,MONTH(DATE(YEAR(SUMMARY!$C$6),MONTH(SUMMARY!$C$6)+3,1)))/SUMIFS(DETAIL!$M$2:$M$137,DETAIL!$S$2:$S$137,$B73,DETAIL!$F$2:$F$137,MONTH(DATE(YEAR(SUMMARY!$C$6),MONTH(SUMMARY!$C$6)+3,1))),"-") -> 1.4603175
A76: ="REKAP EVALUASI PER PEMAGANG. dikelompokkan per Pembimbing ("&TEXT(SUMMARY!$C$6,"dd-mm-yyyy")&" s.d. "&TEXT(SUMMARY!$C$7,"dd-mm-yyyy")&")" -> REKAP EVALUASI PER PEMAGANG. dikelompokkan per Pembimbing (01-06-2026 s.d. 30-09-2026)
A78: No | B78: Kode | C78: Nama Pemagang | D78: Pembimbing | E78: Kategori | F78: Departemen Penempatan | G78: Tgl Masuk Magang | H78: Tgl Selesai Magang | I78: Hari Kerja Dinilai | J78: Hadir | K78: % Kehadiran | L78: Tidak Hadir | M78: Hari Terlambat | N78: % Tepat Waktu | O78: Rata-rata Telat (menit) | P78: Tanpa Absen Pulang | Q78: Hari dgn Laporan | R78: % Laporan Aktivitas | S78: Jun % Hadir | T78: Jul % Hadir | U78: Agu % Hadir | V78: Sep % Hadir | W78: Skor | X78: Predikat | Y78: Hari WFH (dlm masa magang) | Z78: Hadir saat WFH/Libur/Luar Masa | AA78: key telat | AB78: key skor | AC78: key hadir | AD78: Periode Dinilai | AE78: Status Masa Magang | AF78: Indeks Produktivitas | AG78: Nilai Produktivitas
A79: ="Pembimbing: "&D80&" ("&COUNTIF($D$79:$D$133,D80)&" pemagang)" -> Pembimbing: AHMAD JALALUDDIN BASYAR (7 pemagang)
A80: =ROW()-ROW($A$78)-1 -> 1 | B80: =PEMAGANG!B3 -> MG4226 | C80: =PEMAGANG!C3 -> ARINDA PUTRI AULIA | D80: =PEMAGANG!D3 -> AHMAD JALALUDDIN BASYAR | E80: =PEMAGANG!E3 -> MANDIRI | F80: =PEMAGANG!F3 -> PGS SM OF DIGITAL BUSSINES | G80: =IF(PEMAGANG!H3="","Tidak tercatat",PEMAGANG!H3) -> 46175 | H80: =IF(PEMAGANG!I3="","Tidak tercatat",PEMAGANG!I3) -> 46358 | I80: =SUMIFS(DETAIL!$I$2:$I$137,DETAIL!$B$2:$B$137,$C80) -> 75 | J80: =SUMIFS(DETAIL!$K$2:$K$137,DETAIL!$B$2:$B$137,$C80) -> 74 | K80: =IFERROR(J80/I80,0) -> 0.98666667 | L80: =I80-J80 -> 1 | M80: =SUMIFS(DETAIL!$N$2:$N$137,DETAIL!$B$2:$B$137,$C80) -> 15 | N80: =IFERROR(1-M80/SUMIFS(DETAIL!$M$2:$M$137,DETAIL!$B$2:$B$137,$C80),0) -> 0.8 | O80: =IFERROR(SUMIFS(DETAIL!$O$2:$O$137,DETAIL!$B$2:$B$137,$C80)/M80,0) -> 49.266667 | P80: =SUMIFS(DETAIL!$P$2:$P$137,DETAIL!$B$2:$B$137,$C80) -> 2 | Q80: =SUMIFS(DETAIL!$Q$2:$Q$137,DETAIL!$B$2:$B$137,$C80) -> 62 | R80: =IFERROR(Q80/SUMIFS(DETAIL!$M$2:$M$137,DETAIL!$B$2:$B$137,$C80),0) -> 0.82666667 | S80: =IFERROR(SUMIFS(DETAIL!$K$2:$K$137,DETAIL!$B$2:$B$137,$C80,DETAIL!$F$2:$F$137,MONTH(DATE(YEAR(SUMMARY!$C$6),MONTH(SUMMARY!$C$6)+0,1)))/SUMIFS(DETAIL!$I$2:$I$137,DETAIL!$B$2:$B$137,$C80,DETAIL!$F$2:$F$137,MONTH(DATE(YEAR(SUMMARY!$C$6),MONTH(SUMMARY!$C$6)+0,1))),"-") -> 0.9375 | T80: =IFERROR(SUMIFS(DETAIL!$K$2:$K$137,DETAIL!$B$2:$B$137,$C80,DETAIL!$F$2:$F$137,MONTH(DATE(YEAR(SUMMARY!$C$6),MONTH(SUMMARY!$C$6)+1,1)))/SUMIFS(DETAIL!$I$2:$I$137,DETAIL!$B$2:$B$137,$C80,DETAIL!$F$2:$F$137,MONTH(DATE(YEAR(SUMMARY!$C$6),MONTH(SUMMARY!$C$6)+1,1))),"-") -> 1 | U80: =IFERROR(SUMIFS(DETAIL!$K$2:$K$137,DETAIL!$B$2:$B$137,$C80,DETAIL!$F$2:$F$137,MONTH(DATE(YEAR(SUMMARY!$C$6),MONTH(SUMMARY!$C$6)+2,1)))/SUMIFS(DETAIL!$I$2:$I$137,DETAIL!$B$2:$B$137,$C80,DETAIL!$F$2:$F$137,MONTH(DATE(YEAR(SUMMARY!$C$6),MONTH(SUMMARY!$C$6)+2,1))),"-") -> 1 | V80: =IFERROR(SUMIFS(DETAIL!$K$2:$K$137,DETAIL!$B$2:$B$137,$C80,DETAIL!$F$2:$F$137,MONTH(DATE(YEAR(SUMMARY!$C$6),MONTH(SUMMARY!$C$6)+3,1)))/SUMIFS(DETAIL!$I$2:$I$137,DETAIL!$B$2:$B$137,$C80,DETAIL!$F$2:$F$137,MONTH(DATE(YEAR(SUMMARY!$C$6),MONTH(SUMMARY!$C$6)+3,1))),"-") -> 1 | W80: =ROUND(100*(K80*SUMMARY!$C$11+N80*SUMMARY!$C$12+R80*SUMMARY!$C$13+AG80*SUMMARY!$C$17),1) -> 75.5 | X80: =IF(W80>=100*SUMMARY!$C$14,"Sangat Baik",IF(W80>=100*SUMMARY!$C$15,"Baik",IF(W80>=100*SUMMARY!$C$16,"Cukup","Perlu Pembinaan"))) -> Cukup | Y80: =SUMIFS(DETAIL!$J$2:$J$137,DETAIL!$B$2:$B$137,$C80) -> 9 | Z80: =SUMIFS(DETAIL!$L$2:$L$137,DETAIL!$B$2:$B$137,$C80) -> 1 | AA80: =M80+ROW()/100000 -> 15.0008 | AB80: =W80-ROW()/100000 -> 75.4992 | AC80: =IF(I80>=40,K80-ROW()/10000000,"") -> 0.98665867 | AD80: =TEXT(PEMAGANG!J3,"dd-mm-yy")&" s.d. "&TEXT(PEMAGANG!K3,"dd-mm-yy") -> 02-06-26 s.d. 30-09-26 | AE80: =PEMAGANG!N3 -> Masuk 02-06-2026 | AF80: =IFERROR(INDEX(PRODUKTIVITAS!$J$10:$J$43,MATCH($C80,PRODUKTIVITAS!$B$10:$B$43,0)),0) -> 0.44441106 | AG80: =IFERROR(INDEX(PRODUKTIVITAS!$K$10:$K$43,MATCH($C80,PRODUKTIVITAS!$B$10:$B$43,0)),0) -> 0.44441106
A81: =ROW()-ROW($A$78)-1 -> 2 | B81: =PEMAGANG!B4 -> MG/KH/4326 | C81: =PEMAGANG!C4 -> BERLIAN AURELYA RAHMA | D81: =PEMAGANG!D4 -> AHMAD JALALUDDIN BASYAR | E81: =PEMAGANG!E4 -> KEMNAKER | F81: =PEMAGANG!F4 -> PGS SM OF DIGITAL BUSSINES | G81: =IF(PEMAGANG!H4="","Tidak tercatat",PEMAGANG!H4) -> 46244 | H81: =IF(PEMAGANG!I4="","Tidak tercatat",PEMAGANG!I4) -> 46427 | I81: =SUMIFS(DETAIL!$I$2:$I$137,DETAIL!$B$2:$B$137,$C81) -> 36 | J81: =SUMIFS(DETAIL!$K$2:$K$137,DETAIL!$B$2:$B$137,$C81) -> 36 | K81: =IFERROR(J81/I81,0) -> 1 | L81: =I81-J81 -> 0 | M81: =SUMIFS(DETAIL!$N$2:$N$137,DETAIL!$B$2:$B$137,$C81) -> 4 | N81: =IFERROR(1-M81/SUMIFS(DETAIL!$M$2:$M$137,DETAIL!$B$2:$B$137,$C81),0) -> 0.88888889 | O81: =IFERROR(SUMIFS(DETAIL!$O$2:$O$137,DETAIL!$B$2:$B$137,$C81)/M81,0) -> 67.75 | P81: =SUMIFS(DETAIL!$P$2:$P$137,DETAIL!$B$2:$B$137,$C81) -> 2 | Q81: =SUMIFS(DETAIL!$Q$2:$Q$137,DETAIL!$B$2:$B$137,$C81) -> 28 | R81: =IFERROR(Q81/SUMIFS(DETAIL!$M$2:$M$137,DETAIL!$B$2:$B$137,$C81),0) -> 0.77777778 | S81: =IFERROR(SUMIFS(DETAIL!$K$2:$K$137,DETAIL!$B$2:$B$137,$C81,DETAIL!$F$2:$F$137,MONTH(DATE(YEAR(SUMMARY!$C$6),MONTH(SUMMARY!$C$6)+0,1)))/SUMIFS(DETAIL!$I$2:$I$137,DETAIL!$B$2:$B$137,$C81,DETAIL!$F$2:$F$137,MONTH(DATE(YEAR(SUMMARY!$C$6),MONTH(SUMMARY!$C$6)+0,1))),"-") -> - | T81: =IFERROR(SUMIFS(DETAIL!$K$2:$K$137,DETAIL!$B$2:$B$137,$C81,DETAIL!$F$2:$F$137,MONTH(DATE(YEAR(SUMMARY!$C$6),MONTH(SUMMARY!$C$6)+1,1)))/SUMIFS(DETAIL!$I$2:$I$137,DETAIL!$B$2:$B$137,$C81,DETAIL!$F$2:$F$137,MONTH(DATE(YEAR(SUMMARY!$C$6),MONTH(SUMMARY!$C$6)+1,1))),"-") -> - | U81: =IFERROR(SUMIFS(DETAIL!$K$2:$K$137,DETAIL!$B$2:$B$137,$C81,DETAIL!$F$2:$F$137,MONTH(DATE(YEAR(SUMMARY!$C$6),MONTH(SUMMARY!$C$6)+2,1)))/SUMIFS(DETAIL!$I$2:$I$137,DETAIL!$B$2:$B$137,$C81,DETAIL!$F$2:$F$137,MONTH(DATE(YEAR(SUMMARY!$C$6),MONTH(SUMMARY!$C$6)+2,1))),"-") -> 1 | V81: =IFERROR(SUMIFS(DETAIL!$K$2:$K$137,DETAIL!$B$2:$B$137,$C81,DETAIL!$F$2:$F$137,MONTH(DATE(YEAR(SUMMARY!$C$6),MONTH(SUMMARY!$C$6)+3,1)))/SUMIFS(DETAIL!$I$2:$I$137,DETAIL!$B$2:$B$137,$C81,DETAIL!$F$2:$F$137,MONTH(DATE(YEAR(SUMMARY!$C$6),MONTH(SUMMARY!$C$6)+3,1))),"-") -> 1 | W81: =ROUND(100*(K81*SUMMARY!$C$11+N81*SUMMARY!$C$12+R81*SUMMARY!$C$13+AG81*SUMMARY!$C$17),1) -> 89.8 | X81: =IF(W81>=100*SUMMARY!$C$14,"Sangat Baik",IF(W81>=100*SUMMARY!$C$15,"Baik",IF(W81>=100*SUMMARY!$C$16,"Cukup","Perlu Pembinaan"))) -> Baik | Y81: =SUMIFS(DETAIL!$J$2:$J$137,DETAIL!$B$2:$B$137,$C81) -> 0 | Z81: =SUMIFS(DETAIL!$L$2:$L$137,DETAIL!$B$2:$B$137,$C81) -> 0 | AA81: =M81+ROW()/100000 -> 4.00081 | AB81: =W81-ROW()/100000 -> 89.79919 | AC81: =IF(I81>=40,K81-ROW()/10000000,"") | AD81: =TEXT(PEMAGANG!J4,"dd-mm-yy")&" s.d. "&TEXT(PEMAGANG!K4,"dd-mm-yy") -> 10-08-26 s.d. 30-09-26 | AE81: =PEMAGANG!N4 -> Masuk 10-08-2026 | AF81: =IFERROR(INDEX(PRODUKTIVITAS!$J$10:$J$43,MATCH($C81,PRODUKTIVITAS!$B$10:$B$43,0)),0) -> 0.88319872 | AG81: =IFERROR(INDEX(PRODUKTIVITAS!$K$10:$K$43,MATCH($C81,PRODUKTIVITAS!$B$10:$B$43,0)),0) -> 0.88319872
A82: =ROW()-ROW($A$78)-1 -> 3 | B82: =PEMAGANG!B5 -> MG/KH/4226 | C82: =PEMAGANG!C5 -> CLARA OKTAVIA FIRDAUS | D82: =PEMAGANG!D5 -> AHMAD JALALUDDIN BASYAR | E82: =PEMAGANG!E5 -> KEMNAKER | F82: =PEMAGANG!F5 -> PGS SM OF DIGITAL BUSSINES | G82: =IF(PEMAGANG!H5="","Tidak tercatat",PEMAGANG!H5) -> 46244 | H82: =IF(PEMAGANG!I5="","Tidak tercatat",PEMAGANG!I5) -> 46427 | I82: =SUMIFS(DETAIL!$I$2:$I$137,DETAIL!$B$2:$B$137,$C82) -> 36 | J82: =SUMIFS(DETAIL!$K$2:$K$137,DETAIL!$B$2:$B$137,$C82) -> 33 | K82: =IFERROR(J82/I82,0) -> 0.91666667 | L82: =I82-J82 -> 3 | M82: =SUMIFS(DETAIL!$N$2:$N$137,DETAIL!$B$2:$B$137,$C82) -> 5 | N82: =IFERROR(1-M82/SUMIFS(DETAIL!$M$2:$M$137,DETAIL!$B$2:$B$137,$C82),0) -> 0.84848485 | O82: =IFERROR(SUMIFS(DETAIL!$O$2:$O$137,DETAIL!$B$2:$B$137,$C82)/M82,0) -> 56.6 | P82: =SUMIFS(DETAIL!$P$2:$P$137,DETAIL!$B$2:$B$137,$C82) -> 2 | Q82: =SUMIFS(DETAIL!$Q$2:$Q$137,DETAIL!$B$2:$B$137,$C82) -> 28 | R82: =IFERROR(Q82/SUMIFS(DETAIL!$M$2:$M$137,DETAIL!$B$2:$B$137,$C82),0) -> 0.84848485 | S82: =IFERROR(SUMIFS(DETAIL!$K$2:$K$137,DETAIL!$B$2:$B$137,$C82,DETAIL!$F$2:$F$137,MONTH(DATE(YEAR(SUMMARY!$C$6),MONTH(SUMMARY!$C$6)+0,1)))/SUMIFS(DETAIL!$I$2:$I$137,DETAIL!$B$2:$B$137,$C82,DETAIL!$F$2:$F$137,MONTH(DATE(YEAR(SUMMARY!$C$6),MONTH(SUMMARY!$C$6)+0,1))),"-") -> - | T82: =IFERROR(SUMIFS(DETAIL!$K$2:$K$137,DETAIL!$B$2:$B$137,$C82,DETAIL!$F$2:$F$137,MONTH(DATE(YEAR(SUMMARY!$C$6),MONTH(SUMMARY!$C$6)+1,1)))/SUMIFS(DETAIL!$I$2:$I$137,DETAIL!$B$2:$B$137,$C82,DETAIL!$F$2:$F$137,MONTH(DATE(YEAR(SUMMARY!$C$6),MONTH(SUMMARY!$C$6)+1,1))),"-") -> - | U82: =IFERROR(SUMIFS(DETAIL!$K$2:$K$137,DETAIL!$B$2:$B$137,$C82,DETAIL!$F$2:$F$137,MONTH(DATE(YEAR(SUMMARY!$C$6),MONTH(SUMMARY!$C$6)+2,1)))/SUMIFS(DETAIL!$I$2:$I$137,DETAIL!$B$2:$B$137,$C82,DETAIL!$F$2:$F$137,MONTH(DATE(YEAR(SUMMARY!$C$6),MONTH(SUMMARY!$C$6)+2,1))),"-") -> 0.92857143 | V82: =IFERROR(SUMIFS(DETAIL!$K$2:$K$137,DETAIL!$B$2:$B$137,$C82,DETAIL!$F$2:$F$137,MONTH(DATE(YEAR(SUMMARY!$C$6),MONTH(SUMMARY!$C$6)+3,1)))/SUMIFS(DETAIL!$I$2:$I$137,DETAIL!$B$2:$B$137,$C82,DETAIL!$F$2:$F$137,MONTH(DATE(YEAR(SUMMARY!$C$6),MONTH(SUMMARY!$C$6)+3,1))),"-") -> 0.90909091 | W82: =ROUND(100*(K82*SUMMARY!$C$11+N82*SUMMARY!$C$12+R82*SUMMARY!$C$13+AG82*SUMMARY!$C$17),1) -> 82.7 | X82: =IF(W82>=100*SUMMARY!$C$14,"Sangat Baik",IF(W82>=100*SUMMARY!$C$15,"Baik",IF(W82>=100*SUMMARY!$C$16,"Cukup","Perlu Pembinaan"))) -> Baik | Y82: =SUMIFS(DETAIL!$J$2:$J$137,DETAIL!$B$2:$B$137,$C82) -> 0 | Z82: =SUMIFS(DETAIL!$L$2:$L$137,DETAIL!$B$2:$B$137,$C82) -> 0 | AA82: =M82+ROW()/100000 -> 5.00082 | AB82: =W82-ROW()/100000 -> 82.69918 | AC82: =IF(I82>=40,K82-ROW()/10000000,"") | AD82: =TEXT(PEMAGANG!J5,"dd-mm-yy")&" s.d. "&TEXT(PEMAGANG!K5,"dd-mm-yy") -> 10-08-26 s.d. 30-09-26 | AE82: =PEMAGANG!N5 -> Masuk 10-08-2026 | AF82: =IFERROR(INDEX(PRODUKTIVITAS!$J$10:$J$43,MATCH($C82,PRODUKTIVITAS!$B$10:$B$43,0)),0) -> 0.70710565 | AG82: =IFERROR(INDEX(PRODUKTIVITAS!$K$10:$K$43,MATCH($C82,PRODUKTIVITAS!$B$10:$B$43,0)),0) -> 0.70710565
A83: =ROW()-ROW($A$78)-1 -> 4 | B83: =PEMAGANG!B6 -> MG3625 | C83: =PEMAGANG!C6 -> NELLA DIFA SALSABILAH | D83: =PEMAGANG!D6 -> AHMAD JALALUDDIN BASYAR | E83: =PEMAGANG!E6 -> Kontrak Project | F83: =PEMAGANG!F6 -> PGS SM OF DIGITAL BUSSINES | G83: =IF(PEMAGANG!H6="","Tidak tercatat",PEMAGANG!H6) -> 45985 | H83: =IF(PEMAGANG!I6="","Tidak tercatat",PEMAGANG!I6) -> 46349 | I83: =SUMIFS(DETAIL!$I$2:$I$137,DETAIL!$B$2:$B$137,$C83) -> 75 | J83: =SUMIFS(DETAIL!$K$2:$K$137,DETAIL!$B$2:$B$137,$C83) -> 75 | K83: =IFERROR(J83/I83,0) -> 1 | L83: =I83-J83 -> 0 | M83: =SUMIFS(DETAIL!$N$2:$N$137,DETAIL!$B$2:$B$137,$C83) -> 4 | N83: =IFERROR(1-M83/SUMIFS(DETAIL!$M$2:$M$137,DETAIL!$B$2:$B$137,$C83),0) -> 0.95238095 | O83: =IFERROR(SUMIFS(DETAIL!$O$2:$O$137,DETAIL!$B$2:$B$137,$C83)/M83,0) -> 2 | P83: =SUMIFS(DETAIL!$P$2:$P$137,DETAIL!$B$2:$B$137,$C83) -> 1 | Q83: =SUMIFS(DETAIL!$Q$2:$Q$137,DETAIL!$B$2:$B$137,$C83) -> 83 | R83: =IFERROR(Q83/SUMIFS(DETAIL!$M$2:$M$137,DETAIL!$B$2:$B$137,$C83),0) -> 0.98809524 | S83: =IFERROR(SUMIFS(DETAIL!$K$2:$K$137,DETAIL!$B$2:$B$137,$C83,DETAIL!$F$2:$F$137,MONTH(DATE(YEAR(SUMMARY!$C$6),MONTH(SUMMARY!$C$6)+0,1)))/SUMIFS(DETAIL!$I$2:$I$137,DETAIL!$B$2:$B$137,$C83,DETAIL!$F$2:$F$137,MONTH(DATE(YEAR(SUMMARY!$C$6),MONTH(SUMMARY!$C$6)+0,1))),"-") -> 1 | T83: =IFERROR(SUMIFS(DETAIL!$K$2:$K$137,DETAIL!$B$2:$B$137,$C83,DETAIL!$F$2:$F$137,MONTH(DATE(YEAR(SUMMARY!$C$6),MONTH(SUMMARY!$C$6)+1,1)))/SUMIFS(DETAIL!$I$2:$I$137,DETAIL!$B$2:$B$137,$C83,DETAIL!$F$2:$F$137,MONTH(DATE(YEAR(SUMMARY!$C$6),MONTH(SUMMARY!$C$6)+1,1))),"-") -> 1 | U83: =IFERROR(SUMIFS(DETAIL!$K$2:$K$137,DETAIL!$B$2:$B$137,$C83,DETAIL!$F$2:$F$137,MONTH(DATE(YEAR(SUMMARY!$C$6),MONTH(SUMMARY!$C$6)+2,1)))/SUMIFS(DETAIL!$I$2:$I$137,DETAIL!$B$2:$B$137,$C83,DETAIL!$F$2:$F$137,MONTH(DATE(YEAR(SUMMARY!$C$6),MONTH(SUMMARY!$C$6)+2,1))),"-") -> 1 | V83: =IFERROR(SUMIFS(DETAIL!$K$2:$K$137,DETAIL!$B$2:$B$137,$C83,DETAIL!$F$2:$F$137,MONTH(DATE(YEAR(SUMMARY!$C$6),MONTH(SUMMARY!$C$6)+3,1)))/SUMIFS(DETAIL!$I$2:$I$137,DETAIL!$B$2:$B$137,$C83,DETAIL!$F$2:$F$137,MONTH(DATE(YEAR(SUMMARY!$C$6),MONTH(SUMMARY!$C$6)+3,1))),"-") -> 1 | W83: =ROUND(100*(K83*SUMMARY!$C$11+N83*SUMMARY!$C$12+R83*SUMMARY!$C$13+AG83*SUMMARY!$C$17),1) -> 88.2 | X83: =IF(W83>=100*SUMMARY!$C$14,"Sangat Baik",IF(W83>=100*SUMMARY!$C$15,"Baik",IF(W83>=100*SUMMARY!$C$16,"Cukup","Perlu Pembinaan"))) -> Baik | Y83: =SUMIFS(DETAIL!$J$2:$J$137,DETAIL!$B$2:$B$137,$C83) -> 9 | Z83: =SUMIFS(DETAIL!$L$2:$L$137,DETAIL!$B$2:$B$137,$C83) -> 9 | AA83: =M83+ROW()/100000 -> 4.00083 | AB83: =W83-ROW()/100000 -> 88.19917 | AC83: =IF(I83>=40,K83-ROW()/10000000,"") -> 0.9999917 | AD83: =TEXT(PEMAGANG!J6,"dd-mm-yy")&" s.d. "&TEXT(PEMAGANG!K6,"dd-mm-yy") -> 01-06-26 s.d. 30-09-26 | AE83: =PEMAGANG!N6 -> Aktif sepanjang periode | AF83: =IFERROR(INDEX(PRODUKTIVITAS!$J$10:$J$43,MATCH($C83,PRODUKTIVITAS!$B$10:$B$43,0)),0) -> 0.64718601 | AG83: =IFERROR(INDEX(PRODUKTIVITAS!$K$10:$K$43,MATCH($C83,PRODUKTIVITAS!$B$10:$B$43,0)),0) -> 0.64718601
A84: =ROW()-ROW($A$78)-1 -> 5 | B84: =PEMAGANG!B7 -> MG/KH/4526 | C84: =PEMAGANG!C7 -> SYAKIRAH TSALTSA FITRIAH | D84: =PEMAGANG!D7 -> AHMAD JALALUDDIN BASYAR | E84: =PEMAGANG!E7 -> KEMNAKER | F84: =PEMAGANG!F7 -> PGS SM OF DIGITAL BUSSINES | G84: =IF(PEMAGANG!H7="","Tidak tercatat",PEMAGANG!H7) -> 46244 | H84: =IF(PEMAGANG!I7="","Tidak tercatat",PEMAGANG!I7) -> 46427 | I84: =SUMIFS(DETAIL!$I$2:$I$137,DETAIL!$B$2:$B$137,$C84) -> 36 | J84: =SUMIFS(DETAIL!$K$2:$K$137,DETAIL!$B$2:$B$137,$C84) -> 36 | K84: =IFERROR(J84/I84,0) -> 1 | L84: =I84-J84 -> 0 | M84: =SUMIFS(DETAIL!$N$2:$N$137,DETAIL!$B$2:$B$137,$C84) -> 2 | N84: =IFERROR(1-M84/SUMIFS(DETAIL!$M$2:$M$137,DETAIL!$B$2:$B$137,$C84),0) -> 0.94444444 | O84: =IFERROR(SUMIFS(DETAIL!$O$2:$O$137,DETAIL!$B$2:$B$137,$C84)/M84,0) -> 131 | P84: =SUMIFS(DETAIL!$P$2:$P$137,DETAIL!$B$2:$B$137,$C84) -> 3 | Q84: =SUMIFS(DETAIL!$Q$2:$Q$137,DETAIL!$B$2:$B$137,$C84) -> 34 | R84: =IFERROR(Q84/SUMIFS(DETAIL!$M$2:$M$137,DETAIL!$B$2:$B$137,$C84),0) -> 0.94444444 | S84: =IFERROR(SUMIFS(DETAIL!$K$2:$K$137,DETAIL!$B$2:$B$137,$C84,DETAIL!$F$2:$F$137,MONTH(DATE(YEAR(SUMMARY!$C$6),MONTH(SUMMARY!$C$6)+0,1)))/SUMIFS(DETAIL!$I$2:$I$137,DETAIL!$B$2:$B$137,$C84,DETAIL!$F$2:$F$137,MONTH(DATE(YEAR(SUMMARY!$C$6),MONTH(SUMMARY!$C$6)+0,1))),"-") -> - | T84: =IFERROR(SUMIFS(DETAIL!$K$2:$K$137,DETAIL!$B$2:$B$137,$C84,DETAIL!$F$2:$F$137,MONTH(DATE(YEAR(SUMMARY!$C$6),MONTH(SUMMARY!$C$6)+1,1)))/SUMIFS(DETAIL!$I$2:$I$137,DETAIL!$B$2:$B$137,$C84,DETAIL!$F$2:$F$137,MONTH(DATE(YEAR(SUMMARY!$C$6),MONTH(SUMMARY!$C$6)+1,1))),"-") -> - | U84: =IFERROR(SUMIFS(DETAIL!$K$2:$K$137,DETAIL!$B$2:$B$137,$C84,DETAIL!$F$2:$F$137,MONTH(DATE(YEAR(SUMMARY!$C$6),MONTH(SUMMARY!$C$6)+2,1)))/SUMIFS(DETAIL!$I$2:$I$137,DETAIL!$B$2:$B$137,$C84,DETAIL!$F$2:$F$137,MONTH(DATE(YEAR(SUMMARY!$C$6),MONTH(SUMMARY!$C$6)+2,1))),"-") -> 1 | V84: =IFERROR(SUMIFS(DETAIL!$K$2:$K$137,DETAIL!$B$2:$B$137,$C84,DETAIL!$F$2:$F$137,MONTH(DATE(YEAR(SUMMARY!$C$6),MONTH(SUMMARY!$C$6)+3,1)))/SUMIFS(DETAIL!$I$2:$I$137,DETAIL!$B$2:$B$137,$C84,DETAIL!$F$2:$F$137,MONTH(DATE(YEAR(SUMMARY!$C$6),MONTH(SUMMARY!$C$6)+3,1))),"-") -> 1 | W84: =ROUND(100*(K84*SUMMARY!$C$11+N84*SUMMARY!$C$12+R84*SUMMARY!$C$13+AG84*SUMMARY!$C$17),1) -> 97.8 | X84: =IF(W84>=100*SUMMARY!$C$14,"Sangat Baik",IF(W84>=100*SUMMARY!$C$15,"Baik",IF(W84>=100*SUMMARY!$C$16,"Cukup","Perlu Pembinaan"))) -> Sangat Baik | Y84: =SUMIFS(DETAIL!$J$2:$J$137,DETAIL!$B$2:$B$137,$C84) -> 0 | Z84: =SUMIFS(DETAIL!$L$2:$L$137,DETAIL!$B$2:$B$137,$C84) -> 0 | AA84: =M84+ROW()/100000 -> 2.00084 | AB84: =W84-ROW()/100000 -> 97.79916 | AC84: =IF(I84>=40,K84-ROW()/10000000,"") | AD84: =TEXT(PEMAGANG!J7,"dd-mm-yy")&" s.d. "&TEXT(PEMAGANG!K7,"dd-mm-yy") -> 10-08-26 s.d. 30-09-26 | AE84: =PEMAGANG!N7 -> Masuk 10-08-2026 | AF84: =IFERROR(INDEX(PRODUKTIVITAS!$J$10:$J$43,MATCH($C84,PRODUKTIVITAS!$B$10:$B$43,0)),0) -> 2.0590616 | AG84: =IFERROR(INDEX(PRODUKTIVITAS!$K$10:$K$43,MATCH($C84,PRODUKTIVITAS!$B$10:$B$43,0)),0) -> 1
A85: =ROW()-ROW($A$78)-1 -> 6 | B85: =PEMAGANG!B8 -> MG/KH/3325 | C85: =PEMAGANG!C8 -> TIARA MARTHA ASNADHINATA | D85: =PEMAGANG!D8 -> AHMAD JALALUDDIN BASYAR | E85: =PEMAGANG!E8 -> Kontrak Project | F85: =PEMAGANG!F8 -> PGS SM OF DIGITAL BUSSINES | G85: =IF(PEMAGANG!H8="","Tidak tercatat",PEMAGANG!H8) -> 45985 | H85: =IF(PEMAGANG!I8="","Tidak tercatat",PEMAGANG!I8) -> 46356 | I85: =SUMIFS(DETAIL!$I$2:$I$137,DETAIL!$B$2:$B$137,$C85) -> 75 | J85: =SUMIFS(DETAIL!$K$2:$K$137,DETAIL!$B$2:$B$137,$C85) -> 72 | K85: =IFERROR(J85/I85,0) -> 0.96 | L85: =I85-J85 -> 3 | M85: =SUMIFS(DETAIL!$N$2:$N$137,DETAIL!$B$2:$B$137,$C85) -> 5 | N85: =IFERROR(1-M85/SUMIFS(DETAIL!$M$2:$M$137,DETAIL!$B$2:$B$137,$C85),0) -> 0.93589744 | O85: =IFERROR(SUMIFS(DETAIL!$O$2:$O$137,DETAIL!$B$2:$B$137,$C85)/M85,0) -> 14.8 | P85: =SUMIFS(DETAIL!$P$2:$P$137,DETAIL!$B$2:$B$137,$C85) -> 5 | Q85: =SUMIFS(DETAIL!$Q$2:$Q$137,DETAIL!$B$2:$B$137,$C85) -> 73 | R85: =IFERROR(Q85/SUMIFS(DETAIL!$M$2:$M$137,DETAIL!$B$2:$B$137,$C85),0) -> 0.93589744 | S85: =IFERROR(SUMIFS(DETAIL!$K$2:$K$137,DETAIL!$B$2:$B$137,$C85,DETAIL!$F$2:$F$137,MONTH(DATE(YEAR(SUMMARY!$C$6),MONTH(SUMMARY!$C$6)+0,1)))/SUMIFS(DETAIL!$I$2:$I$137,DETAIL!$B$2:$B$137,$C85,DETAIL!$F$2:$F$137,MONTH(DATE(YEAR(SUMMARY!$C$6),MONTH(SUMMARY!$C$6)+0,1))),"-") -> 1 | T85: =IFERROR(SUMIFS(DETAIL!$K$2:$K$137,DETAIL!$B$2:$B$137,$C85,DETAIL!$F$2:$F$137,MONTH(DATE(YEAR(SUMMARY!$C$6),MONTH(SUMMARY!$C$6)+1,1)))/SUMIFS(DETAIL!$I$2:$I$137,DETAIL!$B$2:$B$137,$C85,DETAIL!$F$2:$F$137,MONTH(DATE(YEAR(SUMMARY!$C$6),MONTH(SUMMARY!$C$6)+1,1))),"-") -> 0.88888889 | U85: =IFERROR(SUMIFS(DETAIL!$K$2:$K$137,DETAIL!$B$2:$B$137,$C85,DETAIL!$F$2:$F$137,MONTH(DATE(YEAR(SUMMARY!$C$6),MONTH(SUMMARY!$C$6)+2,1)))/SUMIFS(DETAIL!$I$2:$I$137,DETAIL!$B$2:$B$137,$C85,DETAIL!$F$2:$F$137,MONTH(DATE(YEAR(SUMMARY!$C$6),MONTH(SUMMARY!$C$6)+2,1))),"-") -> 0.94736842 | V85: =IFERROR(SUMIFS(DETAIL!$K$2:$K$137,DETAIL!$B$2:$B$137,$C85,DETAIL!$F$2:$F$137,MONTH(DATE(YEAR(SUMMARY!$C$6),MONTH(SUMMARY!$C$6)+3,1)))/SUMIFS(DETAIL!$I$2:$I$137,DETAIL!$B$2:$B$137,$C85,DETAIL!$F$2:$F$137,MONTH(DATE(YEAR(SUMMARY!$C$6),MONTH(SUMMARY!$C$6)+3,1))),"-") -> 1 | W85: =ROUND(100*(K85*SUMMARY!$C$11+N85*SUMMARY!$C$12+R85*SUMMARY!$C$13+AG85*SUMMARY!$C$17),1) -> 96.2 | X85: =IF(W85>=100*SUMMARY!$C$14,"Sangat Baik",IF(W85>=100*SUMMARY!$C$15,"Baik",IF(W85>=100*SUMMARY!$C$16,"Cukup","Perlu Pembinaan"))) -> Sangat Baik | Y85: =SUMIFS(DETAIL!$J$2:$J$137,DETAIL!$B$2:$B$137,$C85) -> 9 | Z85: =SUMIFS(DETAIL!$L$2:$L$137,DETAIL!$B$2:$B$137,$C85) -> 6 | AA85: =M85+ROW()/100000 -> 5.00085 | AB85: =W85-ROW()/100000 -> 96.19915 | AC85: =IF(I85>=40,K85-ROW()/10000000,"") -> 0.9599915 | AD85: =TEXT(PEMAGANG!J8,"dd-mm-yy")&" s.d. "&TEXT(PEMAGANG!K8,"dd-mm-yy") -> 01-06-26 s.d. 30-09-26 | AE85: =PEMAGANG!N8 -> Aktif sepanjang periode | AF85: =IFERROR(INDEX(PRODUKTIVITAS!$J$10:$J$43,MATCH($C85,PRODUKTIVITAS!$B$10:$B$43,0)),0) -> 1.4297844 | AG85: =IFERROR(INDEX(PRODUKTIVITAS!$K$10:$K$43,MATCH($C85,PRODUKTIVITAS!$B$10:$B$43,0)),0) -> 1
A86: =ROW()-ROW($A$78)-1 -> 7 | B86: =PEMAGANG!B9 -> MG4326 | C86: =PEMAGANG!C9 -> WIDIYA DESY MAWAR SARI | D86: =PEMAGANG!D9 -> AHMAD JALALUDDIN BASYAR | E86: =PEMAGANG!E9 -> MANDIRI | F86: =PEMAGANG!F9 -> PGS SM OF DIGITAL BUSSINES | G86: =IF(PEMAGANG!H9="","Tidak tercatat",PEMAGANG!H9) -> 46175 | H86: =IF(PEMAGANG!I9="","Tidak tercatat",PEMAGANG!I9) -> 46358 | I86: =SUMIFS(DETAIL!$I$2:$I$137,DETAIL!$B$2:$B$137,$C86) -> 75 | J86: =SUMIFS(DETAIL!$K$2:$K$137,DETAIL!$B$2:$B$137,$C86) -> 73 | K86: =IFERROR(J86/I86,0) -> 0.97333333 | L86: =I86-J86 -> 2 | M86: =SUMIFS(DETAIL!$N$2:$N$137,DETAIL!$B$2:$B$137,$C86) -> 29 | N86: =IFERROR(1-M86/SUMIFS(DETAIL!$M$2:$M$137,DETAIL!$B$2:$B$137,$C86),0) -> 0.60810811 | O86: =IFERROR(SUMIFS(DETAIL!$O$2:$O$137,DETAIL!$B$2:$B$137,$C86)/M86,0) -> 64.793103 | P86: =SUMIFS(DETAIL!$P$2:$P$137,DETAIL!$B$2:$B$137,$C86) -> 5 | Q86: =SUMIFS(DETAIL!$Q$2:$Q$137,DETAIL!$B$2:$B$137,$C86) -> 58 | R86: =IFERROR(Q86/SUMIFS(DETAIL!$M$2:$M$137,DETAIL!$B$2:$B$137,$C86),0) -> 0.78378378 | S86: =IFERROR(SUMIFS(DETAIL!$K$2:$K$137,DETAIL!$B$2:$B$137,$C86,DETAIL!$F$2:$F$137,MONTH(DATE(YEAR(SUMMARY!$C$6),MONTH(SUMMARY!$C$6)+0,1)))/SUMIFS(DETAIL!$I$2:$I$137,DETAIL!$B$2:$B$137,$C86,DETAIL!$F$2:$F$137,MONTH(DATE(YEAR(SUMMARY!$C$6),MONTH(SUMMARY!$C$6)+0,1))),"-") -> 1 | T86: =IFERROR(SUMIFS(DETAIL!$K$2:$K$137,DETAIL!$B$2:$B$137,$C86,DETAIL!$F$2:$F$137,MONTH(DATE(YEAR(SUMMARY!$C$6),MONTH(SUMMARY!$C$6)+1,1)))/SUMIFS(DETAIL!$I$2:$I$137,DETAIL!$B$2:$B$137,$C86,DETAIL!$F$2:$F$137,MONTH(DATE(YEAR(SUMMARY!$C$6),MONTH(SUMMARY!$C$6)+1,1))),"-") -> 1 | U86: =IFERROR(SUMIFS(DETAIL!$K$2:$K$137,DETAIL!$B$2:$B$137,$C86,DETAIL!$F$2:$F$137,MONTH(DATE(YEAR(SUMMARY!$C$6),MONTH(SUMMARY!$C$6)+2,1)))/SUMIFS(DETAIL!$I$2:$I$137,DETAIL!$B$2:$B$137,$C86,DETAIL!$F$2:$F$137,MONTH(DATE(YEAR(SUMMARY!$C$6),MONTH(SUMMARY!$C$6)+2,1))),"-") -> 1 | V86: =IFERROR(SUMIFS(DETAIL!$K$2:$K$137,DETAIL!$B$2:$B$137,$C86,DETAIL!$F$2:$F$137,MONTH(DATE(YEAR(SUMMARY!$C$6),MONTH(SUMMARY!$C$6)+3,1)))/SUMIFS(DETAIL!$I$2:$I$137,DETAIL!$B$2:$B$137,$C86,DETAIL!$F$2:$F$137,MONTH(DATE(YEAR(SUMMARY!$C$6),MONTH(SUMMARY!$C$6)+3,1))),"-") -> 0.90909091 | W86: =ROUND(100*(K86*SUMMARY!$C$11+N86*SUMMARY!$C$12+R86*SUMMARY!$C$13+AG86*SUMMARY!$C$17),1) -> 65.4 | X86: =IF(W86>=100*SUMMARY!$C$14,"Sangat Baik",IF(W86>=100*SUMMARY!$C$15,"Baik",IF(W86>=100*SUMMARY!$C$16,"Cukup","Perlu Pembinaan"))) -> Perlu Pembinaan | Y86: =SUMIFS(DETAIL!$J$2:$J$137,DETAIL!$B$2:$B$137,$C86) -> 9 | Z86: =SUMIFS(DETAIL!$L$2:$L$137,DETAIL!$B$2:$B$137,$C86) -> 1 | AA86: =M86+ROW()/100000 -> 29.00086 | AB86: =W86-ROW()/100000 -> 65.39914 | AC86: =IF(I86>=40,K86-ROW()/10000000,"") -> 0.97332473 | AD86: =TEXT(PEMAGANG!J9,"dd-mm-yy")&" s.d. "&TEXT(PEMAGANG!K9,"dd-mm-yy") -> 02-06-26 s.d. 30-09-26 | AE86: =PEMAGANG!N9 -> Masuk 02-06-2026 | AF86: =IFERROR(INDEX(PRODUKTIVITAS!$J$10:$J$43,MATCH($C86,PRODUKTIVITAS!$B$10:$B$43,0)),0) -> 0.27972427 | AG86: =IFERROR(INDEX(PRODUKTIVITAS!$K$10:$K$43,MATCH($C86,PRODUKTIVITAS!$B$10:$B$43,0)),0) -> 0.27972427
A87: ="Pembimbing: "&D88&" ("&COUNTIF($D$79:$D$133,D88)&" pemagang)" -> Pembimbing: AKHMAT ABIDIN (1 pemagang)
A88: =ROW()-ROW($A$78)-2 -> 8 | B88: =PEMAGANG!B10 -> MG4126 | C88: =PEMAGANG!C10 -> NURIKA AMELIA ROSYIDAH | D88: =PEMAGANG!D10 -> AKHMAT ABIDIN | E88: =PEMAGANG!E10 -> MANDIRI | F88: =PEMAGANG!F10 -> PJ GM OF MARKETING (SID) | G88: =IF(PEMAGANG!H10="","Tidak tercatat",PEMAGANG!H10) -> 46062 | H88: =IF(PEMAGANG!I10="","Tidak tercatat",PEMAGANG!I10) -> 46263 | I88: =SUMIFS(DETAIL!$I$2:$I$137,DETAIL!$B$2:$B$137,$C88) -> 52 | J88: =SUMIFS(DETAIL!$K$2:$K$137,DETAIL!$B$2:$B$137,$C88) -> 48 | K88: =IFERROR(J88/I88,0) -> 0.92307692 | L88: =I88-J88 -> 4 | M88: =SUMIFS(DETAIL!$N$2:$N$137,DETAIL!$B$2:$B$137,$C88) -> 3 | N88: =IFERROR(1-M88/SUMIFS(DETAIL!$M$2:$M$137,DETAIL!$B$2:$B$137,$C88),0) -> 0.94444444 | O88: =IFERROR(SUMIFS(DETAIL!$O$2:$O$137,DETAIL!$B$2:$B$137,$C88)/M88,0) -> 3.3333333 | P88: =SUMIFS(DETAIL!$P$2:$P$137,DETAIL!$B$2:$B$137,$C88) -> 5 | Q88: =SUMIFS(DETAIL!$Q$2:$Q$137,DETAIL!$B$2:$B$137,$C88) -> 51 | R88: =IFERROR(Q88/SUMIFS(DETAIL!$M$2:$M$137,DETAIL!$B$2:$B$137,$C88),0) -> 0.94444444 | S88: =IFERROR(SUMIFS(DETAIL!$K$2:$K$137,DETAIL!$B$2:$B$137,$C88,DETAIL!$F$2:$F$137,MONTH(DATE(YEAR(SUMMARY!$C$6),MONTH(SUMMARY!$C$6)+0,1)))/SUMIFS(DETAIL!$I$2:$I$137,DETAIL!$B$2:$B$137,$C88,DETAIL!$F$2:$F$137,MONTH(DATE(YEAR(SUMMARY!$C$6),MONTH(SUMMARY!$C$6)+0,1))),"-") -> 0.875 | T88: =IFERROR(SUMIFS(DETAIL!$K$2:$K$137,DETAIL!$B$2:$B$137,$C88,DETAIL!$F$2:$F$137,MONTH(DATE(YEAR(SUMMARY!$C$6),MONTH(SUMMARY!$C$6)+1,1)))/SUMIFS(DETAIL!$I$2:$I$137,DETAIL!$B$2:$B$137,$C88,DETAIL!$F$2:$F$137,MONTH(DATE(YEAR(SUMMARY!$C$6),MONTH(SUMMARY!$C$6)+1,1))),"-") -> 1 | U88: =IFERROR(SUMIFS(DETAIL!$K$2:$K$137,DETAIL!$B$2:$B$137,$C88,DETAIL!$F$2:$F$137,MONTH(DATE(YEAR(SUMMARY!$C$6),MONTH(SUMMARY!$C$6)+2,1)))/SUMIFS(DETAIL!$I$2:$I$137,DETAIL!$B$2:$B$137,$C88,DETAIL!$F$2:$F$137,MONTH(DATE(YEAR(SUMMARY!$C$6),MONTH(SUMMARY!$C$6)+2,1))),"-") -> 0.88888889 | V88: =IFERROR(SUMIFS(DETAIL!$K$2:$K$137,DETAIL!$B$2:$B$137,$C88,DETAIL!$F$2:$F$137,MONTH(DATE(YEAR(SUMMARY!$C$6),MONTH(SUMMARY!$C$6)+3,1)))/SUMIFS(DETAIL!$I$2:$I$137,DETAIL!$B$2:$B$137,$C88,DETAIL!$F$2:$F$137,MONTH(DATE(YEAR(SUMMARY!$C$6),MONTH(SUMMARY!$C$6)+3,1))),"-") -> - | W88: =ROUND(100*(K88*SUMMARY!$C$11+N88*SUMMARY!$C$12+R88*SUMMARY!$C$13+AG88*SUMMARY!$C$17),1) -> 95.5 | X88: =IF(W88>=100*SUMMARY!$C$14,"Sangat Baik",IF(W88>=100*SUMMARY!$C$15,"Baik",IF(W88>=100*SUMMARY!$C$16,"Cukup","Perlu Pembinaan"))) -> Sangat Baik | Y88: =SUMIFS(DETAIL!$J$2:$J$137,DETAIL!$B$2:$B$137,$C88) -> 9 | Z88: =SUMIFS(DETAIL!$L$2:$L$137,DETAIL!$B$2:$B$137,$C88) -> 7 | AA88: =M88+ROW()/100000 -> 3.00088 | AB88: =W88-ROW()/100000 -> 95.49912 | AC88: =IF(I88>=40,K88-ROW()/10000000,"") -> 0.92306812 | AD88: =TEXT(PEMAGANG!J10,"dd-mm-yy")&" s.d. "&TEXT(PEMAGANG!K10,"dd-mm-yy") -> 01-06-26 s.d. 29-08-26 | AE88: =PEMAGANG!N10 -> Selesai 29-08-2026 | AF88: =IFERROR(INDEX(PRODUKTIVITAS!$J$10:$J$43,MATCH($C88,PRODUKTIVITAS!$B$10:$B$43,0)),0) -> 1.1054907 | AG88: =IFERROR(INDEX(PRODUKTIVITAS!$K$10:$K$43,MATCH($C88,PRODUKTIVITAS!$B$10:$B$43,0)),0) -> 1
A89: ="Pembimbing: "&D90&" ("&COUNTIF($D$79:$D$133,D90)&" pemagang)" -> Pembimbing: ARIFANO KUSUMA BAYU (1 pemagang)
A90: =ROW()-ROW($A$78)-3 -> 9 | B90: =PEMAGANG!B11 -> MG/KH/3525 | C90: =PEMAGANG!C11 -> JANU PRASTYO | D90: =PEMAGANG!D11 -> ARIFANO KUSUMA BAYU | E90: =PEMAGANG!E11 -> Kontrak Project | F90: =PEMAGANG!F11 -> PGS SM OF DIGITAL BUSSINES | G90: =IF(PEMAGANG!H11="","Tidak tercatat",PEMAGANG!H11) -> 45985 | H90: =IF(PEMAGANG!I11="","Tidak tercatat",PEMAGANG!I11) -> 46356 | I90: =SUMIFS(DETAIL!$I$2:$I$137,DETAIL!$B$2:$B$137,$C90) -> 75 | J90: =SUMIFS(DETAIL!$K$2:$K$137,DETAIL!$B$2:$B$137,$C90) -> 71 | K90: =IFERROR(J90/I90,0) -> 0.94666667 | L90: =I90-J90 -> 4 | M90: =SUMIFS(DETAIL!$N$2:$N$137,DETAIL!$B$2:$B$137,$C90) -> 28 | N90: =IFERROR(1-M90/SUMIFS(DETAIL!$M$2:$M$137,DETAIL!$B$2:$B$137,$C90),0) -> 0.63636364 | O90: =IFERROR(SUMIFS(DETAIL!$O$2:$O$137,DETAIL!$B$2:$B$137,$C90)/M90,0) -> 6.6071429 | P90: =SUMIFS(DETAIL!$P$2:$P$137,DETAIL!$B$2:$B$137,$C90) -> 3 | Q90: =SUMIFS(DETAIL!$Q$2:$Q$137,DETAIL!$B$2:$B$137,$C90) -> 76 | R90: =IFERROR(Q90/SUMIFS(DETAIL!$M$2:$M$137,DETAIL!$B$2:$B$137,$C90),0) -> 0.98701299 | S90: =IFERROR(SUMIFS(DETAIL!$K$2:$K$137,DETAIL!$B$2:$B$137,$C90,DETAIL!$F$2:$F$137,MONTH(DATE(YEAR(SUMMARY!$C$6),MONTH(SUMMARY!$C$6)+0,1)))/SUMIFS(DETAIL!$I$2:$I$137,DETAIL!$B$2:$B$137,$C90,DETAIL!$F$2:$F$137,MONTH(DATE(YEAR(SUMMARY!$C$6),MONTH(SUMMARY!$C$6)+0,1))),"-") -> 1 | T90: =IFERROR(SUMIFS(DETAIL!$K$2:$K$137,DETAIL!$B$2:$B$137,$C90,DETAIL!$F$2:$F$137,MONTH(DATE(YEAR(SUMMARY!$C$6),MONTH(SUMMARY!$C$6)+1,1)))/SUMIFS(DETAIL!$I$2:$I$137,DETAIL!$B$2:$B$137,$C90,DETAIL!$F$2:$F$137,MONTH(DATE(YEAR(SUMMARY!$C$6),MONTH(SUMMARY!$C$6)+1,1))),"-") -> 0.88888889 | U90: =IFERROR(SUMIFS(DETAIL!$K$2:$K$137,DETAIL!$B$2:$B$137,$C90,DETAIL!$F$2:$F$137,MONTH(DATE(YEAR(SUMMARY!$C$6),MONTH(SUMMARY!$C$6)+2,1)))/SUMIFS(DETAIL!$I$2:$I$137,DETAIL!$B$2:$B$137,$C90,DETAIL!$F$2:$F$137,MONTH(DATE(YEAR(SUMMARY!$C$6),MONTH(SUMMARY!$C$6)+2,1))),"-") -> 0.94736842 | V90: =IFERROR(SUMIFS(DETAIL!$K$2:$K$137,DETAIL!$B$2:$B$137,$C90,DETAIL!$F$2:$F$137,MONTH(DATE(YEAR(SUMMARY!$C$6),MONTH(SUMMARY!$C$6)+3,1)))/SUMIFS(DETAIL!$I$2:$I$137,DETAIL!$B$2:$B$137,$C90,DETAIL!$F$2:$F$137,MONTH(DATE(YEAR(SUMMARY!$C$6),MONTH(SUMMARY!$C$6)+3,1))),"-") -> 0.95454545 | W90: =ROUND(100*(K90*SUMMARY!$C$11+N90*SUMMARY!$C$12+R90*SUMMARY!$C$13+AG90*SUMMARY!$C$17),1) -> 90.9 | X90: =IF(W90>=100*SUMMARY!$C$14,"Sangat Baik",IF(W90>=100*SUMMARY!$C$15,"Baik",IF(W90>=100*SUMMARY!$C$16,"Cukup","Perlu Pembinaan"))) -> Sangat Baik | Y90: =SUMIFS(DETAIL!$J$2:$J$137,DETAIL!$B$2:$B$137,$C90) -> 9 | Z90: =SUMIFS(DETAIL!$L$2:$L$137,DETAIL!$B$2:$B$137,$C90) -> 6 | AA90: =M90+ROW()/100000 -> 28.0009 | AB90: =W90-ROW()/100000 -> 90.8991 | AC90: =IF(I90>=40,K90-ROW()/10000000,"") -> 0.94665767 | AD90: =TEXT(PEMAGANG!J11,"dd-mm-yy")&" s.d. "&TEXT(PEMAGANG!K11,"dd-mm-yy") -> 01-06-26 s.d. 30-09-26 | AE90: =PEMAGANG!N11 -> Aktif sepanjang periode | AF90: =IFERROR(INDEX(PRODUKTIVITAS!$J$10:$J$43,MATCH($C90,PRODUKTIVITAS!$B$10:$B$43,0)),0) -> 1.5320892 | AG90: =IFERROR(INDEX(PRODUKTIVITAS!$K$10:$K$43,MATCH($C90,PRODUKTIVITAS!$B$10:$B$43,0)),0) -> 1
A91: ="Pembimbing: "&D92&" ("&COUNTIF($D$79:$D$133,D92)&" pemagang)" -> Pembimbing: DIAN RIZKA SARI (2 pemagang)
A92: =ROW()-ROW($A$78)-4 -> 10 | B92: =PEMAGANG!B12 -> MG5026 | C92: =PEMAGANG!C12 -> DINDA RAHADATUL AISY | D92: =PEMAGANG!D12 -> DIAN RIZKA SARI | E92: =PEMAGANG!E12 -> KEMNAKER | F92: =PEMAGANG!F12 -> PGS TREASURY (SID) OFFICER | G92: =IF(PEMAGANG!H12="","Tidak tercatat",PEMAGANG!H12) -> 46223 | H92: =IF(PEMAGANG!I12="","Tidak tercatat",PEMAGANG!I12) -> 46386 | I92: =SUMIFS(DETAIL!$I$2:$I$137,DETAIL!$B$2:$B$137,$C92) -> 49 | J92: =SUMIFS(DETAIL!$K$2:$K$137,DETAIL!$B$2:$B$137,$C92) -> 42 | K92: =IFERROR(J92/I92,0) -> 0.85714286 | L92: =I92-J92 -> 7 | M92: =SUMIFS(DETAIL!$N$2:$N$137,DETAIL!$B$2:$B$137,$C92) -> 0 | N92: =IFERROR(1-M92/SUMIFS(DETAIL!$M$2:$M$137,DETAIL!$B$2:$B$137,$C92),0) -> 1 | O92: =IFERROR(SUMIFS(DETAIL!$O$2:$O$137,DETAIL!$B$2:$B$137,$C92)/M92,0) -> 0 | P92: =SUMIFS(DETAIL!$P$2:$P$137,DETAIL!$B$2:$B$137,$C92) -> 1 | Q92: =SUMIFS(DETAIL!$Q$2:$Q$137,DETAIL!$B$2:$B$137,$C92) -> 42 | R92: =IFERROR(Q92/SUMIFS(DETAIL!$M$2:$M$137,DETAIL!$B$2:$B$137,$C92),0) -> 1 | S92: =IFERROR(SUMIFS(DETAIL!$K$2:$K$137,DETAIL!$B$2:$B$137,$C92,DETAIL!$F$2:$F$137,MONTH(DATE(YEAR(SUMMARY!$C$6),MONTH(SUMMARY!$C$6)+0,1)))/SUMIFS(DETAIL!$I$2:$I$137,DETAIL!$B$2:$B$137,$C92,DETAIL!$F$2:$F$137,MONTH(DATE(YEAR(SUMMARY!$C$6),MONTH(SUMMARY!$C$6)+0,1))),"-") -> - | T92: =IFERROR(SUMIFS(DETAIL!$K$2:$K$137,DETAIL!$B$2:$B$137,$C92,DETAIL!$F$2:$F$137,MONTH(DATE(YEAR(SUMMARY!$C$6),MONTH(SUMMARY!$C$6)+1,1)))/SUMIFS(DETAIL!$I$2:$I$137,DETAIL!$B$2:$B$137,$C92,DETAIL!$F$2:$F$137,MONTH(DATE(YEAR(SUMMARY!$C$6),MONTH(SUMMARY!$C$6)+1,1))),"-") -> 0.875 | U92: =IFERROR(SUMIFS(DETAIL!$K$2:$K$137,DETAIL!$B$2:$B$137,$C92,DETAIL!$F$2:$F$137,MONTH(DATE(YEAR(SUMMARY!$C$6),MONTH(SUMMARY!$C$6)+2,1)))/SUMIFS(DETAIL!$I$2:$I$137,DETAIL!$B$2:$B$137,$C92,DETAIL!$F$2:$F$137,MONTH(DATE(YEAR(SUMMARY!$C$6),MONTH(SUMMARY!$C$6)+2,1))),"-") -> 0.89473684 | V92: =IFERROR(SUMIFS(DETAIL!$K$2:$K$137,DETAIL!$B$2:$B$137,$C92,DETAIL!$F$2:$F$137,MONTH(DATE(YEAR(SUMMARY!$C$6),MONTH(SUMMARY!$C$6)+3,1)))/SUMIFS(DETAIL!$I$2:$I$137,DETAIL!$B$2:$B$137,$C92,DETAIL!$F$2:$F$137,MONTH(DATE(YEAR(SUMMARY!$C$6),MONTH(SUMMARY!$C$6)+3,1))),"-") -> 0.81818182 | W92: =ROUND(100*(K92*SUMMARY!$C$11+N92*SUMMARY!$C$12+R92*SUMMARY!$C$13+AG92*SUMMARY!$C$17),1) -> 81.4 | X92: =IF(W92>=100*SUMMARY!$C$14,"Sangat Baik",IF(W92>=100*SUMMARY!$C$15,"Baik",IF(W92>=100*SUMMARY!$C$16,"Cukup","Perlu Pembinaan"))) -> Baik | Y92: =SUMIFS(DETAIL!$J$2:$J$137,DETAIL!$B$2:$B$137,$C92) -> 2 | Z92: =SUMIFS(DETAIL!$L$2:$L$137,DETAIL!$B$2:$B$137,$C92) -> 0 | AA92: =M92+ROW()/100000 -> 0.00092 | AB92: =W92-ROW()/100000 -> 81.39908 | AC92: =IF(I92>=40,K92-ROW()/10000000,"") -> 0.85713366 | AD92: =TEXT(PEMAGANG!J12,"dd-mm-yy")&" s.d. "&TEXT(PEMAGANG!K12,"dd-mm-yy") -> 20-07-26 s.d. 30-09-26 | AE92: =PEMAGANG!N12 -> Masuk 20-07-2026 | AF92: =IFERROR(INDEX(PRODUKTIVITAS!$J$10:$J$43,MATCH($C92,PRODUKTIVITAS!$B$10:$B$43,0)),0) -> 0.52417378 | AG92: =IFERROR(INDEX(PRODUKTIVITAS!$K$10:$K$43,MATCH($C92,PRODUKTIVITAS!$B$10:$B$43,0)),0) -> 0.52417378
A93: =ROW()-ROW($A$78)-4 -> 11 | B93: =PEMAGANG!B13 -> MG27 | C93: =PEMAGANG!C13 -> NIKEN AURELIA SAPUTRI | D93: =PEMAGANG!D13 -> DIAN RIZKA SARI | E93: =PEMAGANG!E13 -> MANDIRI | F93: =PEMAGANG!F13 -> PGS TREASURY (SID) OFFICER | G93: =IF(PEMAGANG!H13="","Tidak tercatat",PEMAGANG!H13) -> 45971 | H93: =IF(PEMAGANG!I13="","Tidak tercatat",PEMAGANG!I13) -> 46203 | I93: =SUMIFS(DETAIL!$I$2:$I$137,DETAIL!$B$2:$B$137,$C93) -> 16 | J93: =SUMIFS(DETAIL!$K$2:$K$137,DETAIL!$B$2:$B$137,$C93) -> 16 | K93: =IFERROR(J93/I93,0) -> 1 | L93: =I93-J93 -> 0 | M93: =SUMIFS(DETAIL!$N$2:$N$137,DETAIL!$B$2:$B$137,$C93) -> 0 | N93: =IFERROR(1-M93/SUMIFS(DETAIL!$M$2:$M$137,DETAIL!$B$2:$B$137,$C93),0) -> 1 | O93: =IFERROR(SUMIFS(DETAIL!$O$2:$O$137,DETAIL!$B$2:$B$137,$C93)/M93,0) -> 0 | P93: =SUMIFS(DETAIL!$P$2:$P$137,DETAIL!$B$2:$B$137,$C93) -> 2 | Q93: =SUMIFS(DETAIL!$Q$2:$Q$137,DETAIL!$B$2:$B$137,$C93) -> 15 | R93: =IFERROR(Q93/SUMIFS(DETAIL!$M$2:$M$137,DETAIL!$B$2:$B$137,$C93),0) -> 0.9375 | S93: =IFERROR(SUMIFS(DETAIL!$K$2:$K$137,DETAIL!$B$2:$B$137,$C93,DETAIL!$F$2:$F$137,MONTH(DATE(YEAR(SUMMARY!$C$6),MONTH(SUMMARY!$C$6)+0,1)))/SUMIFS(DETAIL!$I$2:$I$137,DETAIL!$B$2:$B$137,$C93,DETAIL!$F$2:$F$137,MONTH(DATE(YEAR(SUMMARY!$C$6),MONTH(SUMMARY!$C$6)+0,1))),"-") -> 1 | T93: =IFERROR(SUMIFS(DETAIL!$K$2:$K$137,DETAIL!$B$2:$B$137,$C93,DETAIL!$F$2:$F$137,MONTH(DATE(YEAR(SUMMARY!$C$6),MONTH(SUMMARY!$C$6)+1,1)))/SUMIFS(DETAIL!$I$2:$I$137,DETAIL!$B$2:$B$137,$C93,DETAIL!$F$2:$F$137,MONTH(DATE(YEAR(SUMMARY!$C$6),MONTH(SUMMARY!$C$6)+1,1))),"-") -> - | U93: =IFERROR(SUMIFS(DETAIL!$K$2:$K$137,DETAIL!$B$2:$B$137,$C93,DETAIL!$F$2:$F$137,MONTH(DATE(YEAR(SUMMARY!$C$6),MONTH(SUMMARY!$C$6)+2,1)))/SUMIFS(DETAIL!$I$2:$I$137,DETAIL!$B$2:$B$137,$C93,DETAIL!$F$2:$F$137,MONTH(DATE(YEAR(SUMMARY!$C$6),MONTH(SUMMARY!$C$6)+2,1))),"-") -> - | V93: =IFERROR(SUMIFS(DETAIL!$K$2:$K$137,DETAIL!$B$2:$B$137,$C93,DETAIL!$F$2:$F$137,MONTH(DATE(YEAR(SUMMARY!$C$6),MONTH(SUMMARY!$C$6)+3,1)))/SUMIFS(DETAIL!$I$2:$I$137,DETAIL!$B$2:$B$137,$C93,DETAIL!$F$2:$F$137,MONTH(DATE(YEAR(SUMMARY!$C$6),MONTH(SUMMARY!$C$6)+3,1))),"-") -> - | W93: =ROUND(100*(K93*SUMMARY!$C$11+N93*SUMMARY!$C$12+R93*SUMMARY!$C$13+AG93*SUMMARY!$C$17),1) -> 81.3 | X93: =IF(W93>=100*SUMMARY!$C$14,"Sangat Baik",IF(W93>=100*SUMMARY!$C$15,"Baik",IF(W93>=100*SUMMARY!$C$16,"Cukup","Perlu Pembinaan"))) -> Baik | Y93: =SUMIFS(DETAIL!$J$2:$J$137,DETAIL!$B$2:$B$137,$C93) -> 4 | Z93: =SUMIFS(DETAIL!$L$2:$L$137,DETAIL!$B$2:$B$137,$C93) -> 1 | AA93: =M93+ROW()/100000 -> 0.00093 | AB93: =W93-ROW()/100000 -> 81.29907 | AC93: =IF(I93>=40,K93-ROW()/10000000,"") | AD93: =TEXT(PEMAGANG!J13,"dd-mm-yy")&" s.d. "&TEXT(PEMAGANG!K13,"dd-mm-yy") -> 01-06-26 s.d. 30-06-26 | AE93: =PEMAGANG!N13 -> Selesai 30-06-2026 | AF93: =IFERROR(INDEX(PRODUKTIVITAS!$J$10:$J$43,MATCH($C93,PRODUKTIVITAS!$B$10:$B$43,0)),0) -> 0.4186691 | AG93: =IFERROR(INDEX(PRODUKTIVITAS!$K$10:$K$43,MATCH($C93,PRODUKTIVITAS!$B$10:$B$43,0)),0) -> 0.4186691
A94: ="Pembimbing: "&D95&" ("&COUNTIF($D$79:$D$133,D95)&" pemagang)" -> Pembimbing: DWI SULIASTARI (2 pemagang)
A95: =ROW()-ROW($A$78)-5 -> 12 | B95: =PEMAGANG!B14 -> MG4426 | C95: =PEMAGANG!C14 -> EKA PUTRI FEBRIANTI | D95: =PEMAGANG!D14 -> DWI SULIASTARI | E95: =PEMAGANG!E14 -> MANDIRI | F95: =PEMAGANG!F14 -> SM OF SECRETARIAT & FILLING | G95: =IF(PEMAGANG!H14="","Tidak tercatat",PEMAGANG!H14) -> 46177 | H95: =IF(PEMAGANG!I14="","Tidak tercatat",PEMAGANG!I14) -> 46387 | I95: =SUMIFS(DETAIL!$I$2:$I$137,DETAIL!$B$2:$B$137,$C95) -> 74 | J95: =SUMIFS(DETAIL!$K$2:$K$137,DETAIL!$B$2:$B$137,$C95) -> 69 | K95: =IFERROR(J95/I95,0) -> 0.93243243 | L95: =I95-J95 -> 5 | M95: =SUMIFS(DETAIL!$N$2:$N$137,DETAIL!$B$2:$B$137,$C95) -> 3 | N95: =IFERROR(1-M95/SUMIFS(DETAIL!$M$2:$M$137,DETAIL!$B$2:$B$137,$C95),0) -> 0.95652174 | O95: =IFERROR(SUMIFS(DETAIL!$O$2:$O$137,DETAIL!$B$2:$B$137,$C95)/M95,0) -> 186.33333 | P95: =SUMIFS(DETAIL!$P$2:$P$137,DETAIL!$B$2:$B$137,$C95) -> 3 | Q95: =SUMIFS(DETAIL!$Q$2:$Q$137,DETAIL!$B$2:$B$137,$C95) -> 64 | R95: =IFERROR(Q95/SUMIFS(DETAIL!$M$2:$M$137,DETAIL!$B$2:$B$137,$C95),0) -> 0.92753623 | S95: =IFERROR(SUMIFS(DETAIL!$K$2:$K$137,DETAIL!$B$2:$B$137,$C95,DETAIL!$F$2:$F$137,MONTH(DATE(YEAR(SUMMARY!$C$6),MONTH(SUMMARY!$C$6)+0,1)))/SUMIFS(DETAIL!$I$2:$I$137,DETAIL!$B$2:$B$137,$C95,DETAIL!$F$2:$F$137,MONTH(DATE(YEAR(SUMMARY!$C$6),MONTH(SUMMARY!$C$6)+0,1))),"-") -> 0.93333333 | T95: =IFERROR(SUMIFS(DETAIL!$K$2:$K$137,DETAIL!$B$2:$B$137,$C95,DETAIL!$F$2:$F$137,MONTH(DATE(YEAR(SUMMARY!$C$6),MONTH(SUMMARY!$C$6)+1,1)))/SUMIFS(DETAIL!$I$2:$I$137,DETAIL!$B$2:$B$137,$C95,DETAIL!$F$2:$F$137,MONTH(DATE(YEAR(SUMMARY!$C$6),MONTH(SUMMARY!$C$6)+1,1))),"-") -> 1 | U95: =IFERROR(SUMIFS(DETAIL!$K$2:$K$137,DETAIL!$B$2:$B$137,$C95,DETAIL!$F$2:$F$137,MONTH(DATE(YEAR(SUMMARY!$C$6),MONTH(SUMMARY!$C$6)+2,1)))/SUMIFS(DETAIL!$I$2:$I$137,DETAIL!$B$2:$B$137,$C95,DETAIL!$F$2:$F$137,MONTH(DATE(YEAR(SUMMARY!$C$6),MONTH(SUMMARY!$C$6)+2,1))),"-") -> 1 | V95: =IFERROR(SUMIFS(DETAIL!$K$2:$K$137,DETAIL!$B$2:$B$137,$C95,DETAIL!$F$2:$F$137,MONTH(DATE(YEAR(SUMMARY!$C$6),MONTH(SUMMARY!$C$6)+3,1)))/SUMIFS(DETAIL!$I$2:$I$137,DETAIL!$B$2:$B$137,$C95,DETAIL!$F$2:$F$137,MONTH(DATE(YEAR(SUMMARY!$C$6),MONTH(SUMMARY!$C$6)+3,1))),"-") -> 0.81818182 | W95: =ROUND(100*(K95*SUMMARY!$C$11+N95*SUMMARY!$C$12+R95*SUMMARY!$C$13+AG95*SUMMARY!$C$17),1) -> 77.7 | X95: =IF(W95>=100*SUMMARY!$C$14,"Sangat Baik",IF(W95>=100*SUMMARY!$C$15,"Baik",IF(W95>=100*SUMMARY!$C$16,"Cukup","Perlu Pembinaan"))) -> Cukup | Y95: =SUMIFS(DETAIL!$J$2:$J$137,DETAIL!$B$2:$B$137,$C95) -> 8 | Z95: =SUMIFS(DETAIL!$L$2:$L$137,DETAIL!$B$2:$B$137,$C95) -> 0 | AA95: =M95+ROW()/100000 -> 3.00095 | AB95: =W95-ROW()/100000 -> 77.69905 | AC95: =IF(I95>=40,K95-ROW()/10000000,"") -> 0.93242293 | AD95: =TEXT(PEMAGANG!J14,"dd-mm-yy")&" s.d. "&TEXT(PEMAGANG!K14,"dd-mm-yy") -> 04-06-26 s.d. 30-09-26 | AE95: =PEMAGANG!N14 -> Masuk 04-06-2026 | AF95: =IFERROR(INDEX(PRODUKTIVITAS!$J$10:$J$43,MATCH($C95,PRODUKTIVITAS!$B$10:$B$43,0)),0) -> 0.401338 | AG95: =IFERROR(INDEX(PRODUKTIVITAS!$K$10:$K$43,MATCH($C95,PRODUKTIVITAS!$B$10:$B$43,0)),0) -> 0.401338
A96: =ROW()-ROW($A$78)-5 -> 13 | B96: =PEMAGANG!B15 -> MG4526 | C96: =PEMAGANG!C15 -> NABILA RAIS NUR ROMADHONA | D96: =PEMAGANG!D15 -> DWI SULIASTARI | E96: =PEMAGANG!E15 -> MANDIRI | F96: =PEMAGANG!F15 -> SM OF SECRETARIAT & FILLING | G96: =IF(PEMAGANG!H15="","Tidak tercatat",PEMAGANG!H15) -> 46177 | H96: =IF(PEMAGANG!I15="","Tidak tercatat",PEMAGANG!I15) -> 46387 | I96: =SUMIFS(DETAIL!$I$2:$I$137,DETAIL!$B$2:$B$137,$C96) -> 74 | J96: =SUMIFS(DETAIL!$K$2:$K$137,DETAIL!$B$2:$B$137,$C96) -> 69 | K96: =IFERROR(J96/I96,0) -> 0.93243243 | L96: =I96-J96 -> 5 | M96: =SUMIFS(DETAIL!$N$2:$N$137,DETAIL!$B$2:$B$137,$C96) -> 4 | N96: =IFERROR(1-M96/SUMIFS(DETAIL!$M$2:$M$137,DETAIL!$B$2:$B$137,$C96),0) -> 0.94202899 | O96: =IFERROR(SUMIFS(DETAIL!$O$2:$O$137,DETAIL!$B$2:$B$137,$C96)/M96,0) -> 91.5 | P96: =SUMIFS(DETAIL!$P$2:$P$137,DETAIL!$B$2:$B$137,$C96) -> 3 | Q96: =SUMIFS(DETAIL!$Q$2:$Q$137,DETAIL!$B$2:$B$137,$C96) -> 68 | R96: =IFERROR(Q96/SUMIFS(DETAIL!$M$2:$M$137,DETAIL!$B$2:$B$137,$C96),0) -> 0.98550725 | S96: =IFERROR(SUMIFS(DETAIL!$K$2:$K$137,DETAIL!$B$2:$B$137,$C96,DETAIL!$F$2:$F$137,MONTH(DATE(YEAR(SUMMARY!$C$6),MONTH(SUMMARY!$C$6)+0,1)))/SUMIFS(DETAIL!$I$2:$I$137,DETAIL!$B$2:$B$137,$C96,DETAIL!$F$2:$F$137,MONTH(DATE(YEAR(SUMMARY!$C$6),MONTH(SUMMARY!$C$6)+0,1))),"-") -> 0.93333333 | T96: =IFERROR(SUMIFS(DETAIL!$K$2:$K$137,DETAIL!$B$2:$B$137,$C96,DETAIL!$F$2:$F$137,MONTH(DATE(YEAR(SUMMARY!$C$6),MONTH(SUMMARY!$C$6)+1,1)))/SUMIFS(DETAIL!$I$2:$I$137,DETAIL!$B$2:$B$137,$C96,DETAIL!$F$2:$F$137,MONTH(DATE(YEAR(SUMMARY!$C$6),MONTH(SUMMARY!$C$6)+1,1))),"-") -> 0.94444444 | U96: =IFERROR(SUMIFS(DETAIL!$K$2:$K$137,DETAIL!$B$2:$B$137,$C96,DETAIL!$F$2:$F$137,MONTH(DATE(YEAR(SUMMARY!$C$6),MONTH(SUMMARY!$C$6)+2,1)))/SUMIFS(DETAIL!$I$2:$I$137,DETAIL!$B$2:$B$137,$C96,DETAIL!$F$2:$F$137,MONTH(DATE(YEAR(SUMMARY!$C$6),MONTH(SUMMARY!$C$6)+2,1))),"-") -> 1 | V96: =IFERROR(SUMIFS(DETAIL!$K$2:$K$137,DETAIL!$B$2:$B$137,$C96,DETAIL!$F$2:$F$137,MONTH(DATE(YEAR(SUMMARY!$C$6),MONTH(SUMMARY!$C$6)+3,1)))/SUMIFS(DETAIL!$I$2:$I$137,DETAIL!$B$2:$B$137,$C96,DETAIL!$F$2:$F$137,MONTH(DATE(YEAR(SUMMARY!$C$6),MONTH(SUMMARY!$C$6)+3,1))),"-") -> 0.86363636 | W96: =ROUND(100*(K96*SUMMARY!$C$11+N96*SUMMARY!$C$12+R96*SUMMARY!$C$13+AG96*SUMMARY!$C$17),1) -> 83.1 | X96: =IF(W96>=100*SUMMARY!$C$14,"Sangat Baik",IF(W96>=100*SUMMARY!$C$15,"Baik",IF(W96>=100*SUMMARY!$C$16,"Cukup","Perlu Pembinaan"))) -> Baik | Y96: =SUMIFS(DETAIL!$J$2:$J$137,DETAIL!$B$2:$B$137,$C96) -> 8 | Z96: =SUMIFS(DETAIL!$L$2:$L$137,DETAIL!$B$2:$B$137,$C96) -> 0 | AA96: =M96+ROW()/100000 -> 4.00096 | AB96: =W96-ROW()/100000 -> 83.09904 | AC96: =IF(I96>=40,K96-ROW()/10000000,"") -> 0.93242283 | AD96: =TEXT(PEMAGANG!J15,"dd-mm-yy")&" s.d. "&TEXT(PEMAGANG!K15,"dd-mm-yy") -> 04-06-26 s.d. 30-09-26 | AE96: =PEMAGANG!N15 -> Masuk 04-06-2026 | AF96: =IFERROR(INDEX(PRODUKTIVITAS!$J$10:$J$43,MATCH($C96,PRODUKTIVITAS!$B$10:$B$43,0)),0) -> 0.55248519 | AG96: =IFERROR(INDEX(PRODUKTIVITAS!$K$10:$K$43,MATCH($C96,PRODUKTIVITAS!$B$10:$B$43,0)),0) -> 0.55248519
A97: ="Pembimbing: "&D98&" ("&COUNTIF($D$79:$D$133,D98)&" pemagang)" -> Pembimbing: ELFANO RANGGA PRATAMA (1 pemagang)
A98: =ROW()-ROW($A$78)-6 -> 14 | B98: =PEMAGANG!B16 -> RK/KH/25008 | C98: =PEMAGANG!C16 -> FETI FATMAWATI | D98: =PEMAGANG!D16 -> ELFANO RANGGA PRATAMA | E98: =PEMAGANG!E16 -> KEMNAKER | F98: =PEMAGANG!F16 -> MARKETING & EXPANSION MODERN RETAIL OFFICER | G98: =IF(PEMAGANG!H16="","Tidak tercatat",PEMAGANG!H16) -> 45985 | H98: =IF(PEMAGANG!I16="","Tidak tercatat",PEMAGANG!I16) -> 46356 | I98: =SUMIFS(DETAIL!$I$2:$I$137,DETAIL!$B$2:$B$137,$C98) -> 75 | J98: =SUMIFS(DETAIL!$K$2:$K$137,DETAIL!$B$2:$B$137,$C98) -> 70 | K98: =IFERROR(J98/I98,0) -> 0.93333333 | L98: =I98-J98 -> 5 | M98: =SUMIFS(DETAIL!$N$2:$N$137,DETAIL!$B$2:$B$137,$C98) -> 59 | N98: =IFERROR(1-M98/SUMIFS(DETAIL!$M$2:$M$137,DETAIL!$B$2:$B$137,$C98),0) -> 0.37234043 | O98: =IFERROR(SUMIFS(DETAIL!$O$2:$O$137,DETAIL!$B$2:$B$137,$C98)/M98,0) -> 19.271186 | P98: =SUMIFS(DETAIL!$P$2:$P$137,DETAIL!$B$2:$B$137,$C98) -> 1 | Q98: =SUMIFS(DETAIL!$Q$2:$Q$137,DETAIL!$B$2:$B$137,$C98) -> 86 | R98: =IFERROR(Q98/SUMIFS(DETAIL!$M$2:$M$137,DETAIL!$B$2:$B$137,$C98),0) -> 0.91489362 | S98: =IFERROR(SUMIFS(DETAIL!$K$2:$K$137,DETAIL!$B$2:$B$137,$C98,DETAIL!$F$2:$F$137,MONTH(DATE(YEAR(SUMMARY!$C$6),MONTH(SUMMARY!$C$6)+0,1)))/SUMIFS(DETAIL!$I$2:$I$137,DETAIL!$B$2:$B$137,$C98,DETAIL!$F$2:$F$137,MONTH(DATE(YEAR(SUMMARY!$C$6),MONTH(SUMMARY!$C$6)+0,1))),"-") -> 0.875 | T98: =IFERROR(SUMIFS(DETAIL!$K$2:$K$137,DETAIL!$B$2:$B$137,$C98,DETAIL!$F$2:$F$137,MONTH(DATE(YEAR(SUMMARY!$C$6),MONTH(SUMMARY!$C$6)+1,1)))/SUMIFS(DETAIL!$I$2:$I$137,DETAIL!$B$2:$B$137,$C98,DETAIL!$F$2:$F$137,MONTH(DATE(YEAR(SUMMARY!$C$6),MONTH(SUMMARY!$C$6)+1,1))),"-") -> 0.94444444 | U98: =IFERROR(SUMIFS(DETAIL!$K$2:$K$137,DETAIL!$B$2:$B$137,$C98,DETAIL!$F$2:$F$137,MONTH(DATE(YEAR(SUMMARY!$C$6),MONTH(SUMMARY!$C$6)+2,1)))/SUMIFS(DETAIL!$I$2:$I$137,DETAIL!$B$2:$B$137,$C98,DETAIL!$F$2:$F$137,MONTH(DATE(YEAR(SUMMARY!$C$6),MONTH(SUMMARY!$C$6)+2,1))),"-") -> 0.94736842 | V98: =IFERROR(SUMIFS(DETAIL!$K$2:$K$137,DETAIL!$B$2:$B$137,$C98,DETAIL!$F$2:$F$137,MONTH(DATE(YEAR(SUMMARY!$C$6),MONTH(SUMMARY!$C$6)+3,1)))/SUMIFS(DETAIL!$I$2:$I$137,DETAIL!$B$2:$B$137,$C98,DETAIL!$F$2:$F$137,MONTH(DATE(YEAR(SUMMARY!$C$6),MONTH(SUMMARY!$C$6)+3,1))),"-") -> 0.95454545 | W98: =ROUND(100*(K98*SUMMARY!$C$11+N98*SUMMARY!$C$12+R98*SUMMARY!$C$13+AG98*SUMMARY!$C$17),1) -> 74.5 | X98: =IF(W98>=100*SUMMARY!$C$14,"Sangat Baik",IF(W98>=100*SUMMARY!$C$15,"Baik",IF(W98>=100*SUMMARY!$C$16,"Cukup","Perlu Pembinaan"))) -> Cukup | Y98: =SUMIFS(DETAIL!$J$2:$J$137,DETAIL!$B$2:$B$137,$C98) -> 9 | Z98: =SUMIFS(DETAIL!$L$2:$L$137,DETAIL!$B$2:$B$137,$C98) -> 24 | AA98: =M98+ROW()/100000 -> 59.00098 | AB98: =W98-ROW()/100000 -> 74.49902 | AC98: =IF(I98>=40,K98-ROW()/10000000,"") -> 0.93332353 | AD98: =TEXT(PEMAGANG!J16,"dd-mm-yy")&" s.d. "&TEXT(PEMAGANG!K16,"dd-mm-yy") -> 01-06-26 s.d. 30-09-26 | AE98: =PEMAGANG!N16 -> Aktif sepanjang periode | AF98: =IFERROR(INDEX(PRODUKTIVITAS!$J$10:$J$43,MATCH($C98,PRODUKTIVITAS!$B$10:$B$43,0)),0) -> 0.69279781 | AG98: =IFERROR(INDEX(PRODUKTIVITAS!$K$10:$K$43,MATCH($C98,PRODUKTIVITAS!$B$10:$B$43,0)),0) -> 0.69279781
A99: ="Pembimbing: "&D100&" ("&COUNTIF($D$79:$D$133,D100)&" pemagang)" -> Pembimbing: ENDAH YUNIA SRI WINDARI (2 pemagang)
A100: =ROW()-ROW($A$78)-7 -> 15 | B100: =PEMAGANG!B17 -> MG/KH/4726 | C100: =PEMAGANG!C17 -> AHMAD NOVAN JUNIARDY | D100: =PEMAGANG!D17 -> ENDAH YUNIA SRI WINDARI | E100: =PEMAGANG!E17 -> KEMNAKER | F100: =PEMAGANG!F17 -> SM OF FINANCE (SID) | G100: =IF(PEMAGANG!H17="","Tidak tercatat",PEMAGANG!H17) -> 46244 | H100: =IF(PEMAGANG!I17="","Tidak tercatat",PEMAGANG!I17) -> 46427 | I100: =SUMIFS(DETAIL!$I$2:$I$137,DETAIL!$B$2:$B$137,$C100) -> 36 | J100: =SUMIFS(DETAIL!$K$2:$K$137,DETAIL!$B$2:$B$137,$C100) -> 33 | K100: =IFERROR(J100/I100,0) -> 0.91666667 | L100: =I100-J100 -> 3 | M100: =SUMIFS(DETAIL!$N$2:$N$137,DETAIL!$B$2:$B$137,$C100) -> 1 | N100: =IFERROR(1-M100/SUMIFS(DETAIL!$M$2:$M$137,DETAIL!$B$2:$B$137,$C100),0) -> 0.96969697 | O100: =IFERROR(SUMIFS(DETAIL!$O$2:$O$137,DETAIL!$B$2:$B$137,$C100)/M100,0) -> 262 | P100: =SUMIFS(DETAIL!$P$2:$P$137,DETAIL!$B$2:$B$137,$C100) -> 2 | Q100: =SUMIFS(DETAIL!$Q$2:$Q$137,DETAIL!$B$2:$B$137,$C100) -> 33 | R100: =IFERROR(Q100/SUMIFS(DETAIL!$M$2:$M$137,DETAIL!$B$2:$B$137,$C100),0) -> 1 | S100: =IFERROR(SUMIFS(DETAIL!$K$2:$K$137,DETAIL!$B$2:$B$137,$C100,DETAIL!$F$2:$F$137,MONTH(DATE(YEAR(SUMMARY!$C$6),MONTH(SUMMARY!$C$6)+0,1)))/SUMIFS(DETAIL!$I$2:$I$137,DETAIL!$B$2:$B$137,$C100,DETAIL!$F$2:$F$137,MONTH(DATE(YEAR(SUMMARY!$C$6),MONTH(SUMMARY!$C$6)+0,1))),"-") -> - | T100: =IFERROR(SUMIFS(DETAIL!$K$2:$K$137,DETAIL!$B$2:$B$137,$C100,DETAIL!$F$2:$F$137,MONTH(DATE(YEAR(SUMMARY!$C$6),MONTH(SUMMARY!$C$6)+1,1)))/SUMIFS(DETAIL!$I$2:$I$137,DETAIL!$B$2:$B$137,$C100,DETAIL!$F$2:$F$137,MONTH(DATE(YEAR(SUMMARY!$C$6),MONTH(SUMMARY!$C$6)+1,1))),"-") -> - | U100: =IFERROR(SUMIFS(DETAIL!$K$2:$K$137,DETAIL!$B$2:$B$137,$C100,DETAIL!$F$2:$F$137,MONTH(DATE(YEAR(SUMMARY!$C$6),MONTH(SUMMARY!$C$6)+2,1)))/SUMIFS(DETAIL!$I$2:$I$137,DETAIL!$B$2:$B$137,$C100,DETAIL!$F$2:$F$137,MONTH(DATE(YEAR(SUMMARY!$C$6),MONTH(SUMMARY!$C$6)+2,1))),"-") -> 1 | V100: =IFERROR(SUMIFS(DETAIL!$K$2:$K$137,DETAIL!$B$2:$B$137,$C100,DETAIL!$F$2:$F$137,MONTH(DATE(YEAR(SUMMARY!$C$6),MONTH(SUMMARY!$C$6)+3,1)))/SUMIFS(DETAIL!$I$2:$I$137,DETAIL!$B$2:$B$137,$C100,DETAIL!$F$2:$F$137,MONTH(DATE(YEAR(SUMMARY!$C$6),MONTH(SUMMARY!$C$6)+3,1))),"-") -> 0.86363636 | W100: =ROUND(100*(K100*SUMMARY!$C$11+N100*SUMMARY!$C$12+R100*SUMMARY!$C$13+AG100*SUMMARY!$C$17),1) -> 96.9 | X100: =IF(W100>=100*SUMMARY!$C$14,"Sangat Baik",IF(W100>=100*SUMMARY!$C$15,"Baik",IF(W100>=100*SUMMARY!$C$16,"Cukup","Perlu Pembinaan"))) -> Sangat Baik | Y100: =SUMIFS(DETAIL!$J$2:$J$137,DETAIL!$B$2:$B$137,$C100) -> 0 | Z100: =SUMIFS(DETAIL!$L$2:$L$137,DETAIL!$B$2:$B$137,$C100) -> 0 | AA100: =M100+ROW()/100000 -> 1.001 | AB100: =W100-ROW()/100000 -> 96.899 | AC100: =IF(I100>=40,K100-ROW()/10000000,"") | AD100: =TEXT(PEMAGANG!J17,"dd-mm-yy")&" s.d. "&TEXT(PEMAGANG!K17,"dd-mm-yy") -> 10-08-26 s.d. 30-09-26 | AE100: =PEMAGANG!N17 -> Masuk 10-08-2026 | AF100: =IFERROR(INDEX(PRODUKTIVITAS!$J$10:$J$43,MATCH($C100,PRODUKTIVITAS!$B$10:$B$43,0)),0) -> 1.4473095 | AG100: =IFERROR(INDEX(PRODUKTIVITAS!$K$10:$K$43,MATCH($C100,PRODUKTIVITAS!$B$10:$B$43,0)),0) -> 1
A101: =ROW()-ROW($A$78)-7 -> 16 | B101: =PEMAGANG!B18 -> MG/KH/4426 | C101: =PEMAGANG!C18 -> TAHYUDIN UZI SAFAAT | D101: =PEMAGANG!D18 -> ENDAH YUNIA SRI WINDARI | E101: =PEMAGANG!E18 -> KEMNAKER | F101: =PEMAGANG!F18 -> SM OF FINANCE (SID) | G101: =IF(PEMAGANG!H18="","Tidak tercatat",PEMAGANG!H18) -> 46244 | H101: =IF(PEMAGANG!I18="","Tidak tercatat",PEMAGANG!I18) -> 46427 | I101: =SUMIFS(DETAIL!$I$2:$I$137,DETAIL!$B$2:$B$137,$C101) -> 36 | J101: =SUMIFS(DETAIL!$K$2:$K$137,DETAIL!$B$2:$B$137,$C101) -> 35 | K101: =IFERROR(J101/I101,0) -> 0.97222222 | L101: =I101-J101 -> 1 | M101: =SUMIFS(DETAIL!$N$2:$N$137,DETAIL!$B$2:$B$137,$C101) -> 1 | N101: =IFERROR(1-M101/SUMIFS(DETAIL!$M$2:$M$137,DETAIL!$B$2:$B$137,$C101),0) -> 0.97142857 | O101: =IFERROR(SUMIFS(DETAIL!$O$2:$O$137,DETAIL!$B$2:$B$137,$C101)/M101,0) -> 261 | P101: =SUMIFS(DETAIL!$P$2:$P$137,DETAIL!$B$2:$B$137,$C101) -> 3 | Q101: =SUMIFS(DETAIL!$Q$2:$Q$137,DETAIL!$B$2:$B$137,$C101) -> 35 | R101: =IFERROR(Q101/SUMIFS(DETAIL!$M$2:$M$137,DETAIL!$B$2:$B$137,$C101),0) -> 1 | S101: =IFERROR(SUMIFS(DETAIL!$K$2:$K$137,DETAIL!$B$2:$B$137,$C101,DETAIL!$F$2:$F$137,MONTH(DATE(YEAR(SUMMARY!$C$6),MONTH(SUMMARY!$C$6)+0,1)))/SUMIFS(DETAIL!$I$2:$I$137,DETAIL!$B$2:$B$137,$C101,DETAIL!$F$2:$F$137,MONTH(DATE(YEAR(SUMMARY!$C$6),MONTH(SUMMARY!$C$6)+0,1))),"-") -> - | T101: =IFERROR(SUMIFS(DETAIL!$K$2:$K$137,DETAIL!$B$2:$B$137,$C101,DETAIL!$F$2:$F$137,MONTH(DATE(YEAR(SUMMARY!$C$6),MONTH(SUMMARY!$C$6)+1,1)))/SUMIFS(DETAIL!$I$2:$I$137,DETAIL!$B$2:$B$137,$C101,DETAIL!$F$2:$F$137,MONTH(DATE(YEAR(SUMMARY!$C$6),MONTH(SUMMARY!$C$6)+1,1))),"-") -> - | U101: =IFERROR(SUMIFS(DETAIL!$K$2:$K$137,DETAIL!$B$2:$B$137,$C101,DETAIL!$F$2:$F$137,MONTH(DATE(YEAR(SUMMARY!$C$6),MONTH(SUMMARY!$C$6)+2,1)))/SUMIFS(DETAIL!$I$2:$I$137,DETAIL!$B$2:$B$137,$C101,DETAIL!$F$2:$F$137,MONTH(DATE(YEAR(SUMMARY!$C$6),MONTH(SUMMARY!$C$6)+2,1))),"-") -> 1 | V101: =IFERROR(SUMIFS(DETAIL!$K$2:$K$137,DETAIL!$B$2:$B$137,$C101,DETAIL!$F$2:$F$137,MONTH(DATE(YEAR(SUMMARY!$C$6),MONTH(SUMMARY!$C$6)+3,1)))/SUMIFS(DETAIL!$I$2:$I$137,DETAIL!$B$2:$B$137,$C101,DETAIL!$F$2:$F$137,MONTH(DATE(YEAR(SUMMARY!$C$6),MONTH(SUMMARY!$C$6)+3,1))),"-") -> 0.95454545 | W101: =ROUND(100*(K101*SUMMARY!$C$11+N101*SUMMARY!$C$12+R101*SUMMARY!$C$13+AG101*SUMMARY!$C$17),1) -> 98.6 | X101: =IF(W101>=100*SUMMARY!$C$14,"Sangat Baik",IF(W101>=100*SUMMARY!$C$15,"Baik",IF(W101>=100*SUMMARY!$C$16,"Cukup","Perlu Pembinaan"))) -> Sangat Baik | Y101: =SUMIFS(DETAIL!$J$2:$J$137,DETAIL!$B$2:$B$137,$C101) -> 0 | Z101: =SUMIFS(DETAIL!$L$2:$L$137,DETAIL!$B$2:$B$137,$C101) -> 0 | AA101: =M101+ROW()/100000 -> 1.00101 | AB101: =W101-ROW()/100000 -> 98.59899 | AC101: =IF(I101>=40,K101-ROW()/10000000,"") | AD101: =TEXT(PEMAGANG!J18,"dd-mm-yy")&" s.d. "&TEXT(PEMAGANG!K18,"dd-mm-yy") -> 10-08-26 s.d. 30-09-26 | AE101: =PEMAGANG!N18 -> Masuk 10-08-2026 | AF101: =IFERROR(INDEX(PRODUKTIVITAS!$J$10:$J$43,MATCH($C101,PRODUKTIVITAS!$B$10:$B$43,0)),0) -> 1.1123329 | AG101: =IFERROR(INDEX(PRODUKTIVITAS!$K$10:$K$43,MATCH($C101,PRODUKTIVITAS!$B$10:$B$43,0)),0) -> 1
A102: ="Pembimbing: "&D103&" ("&COUNTIF($D$79:$D$133,D103)&" pemagang)" -> Pembimbing: FETI MUBAIYINI (2 pemagang)
A103: =ROW()-ROW($A$78)-8 -> 17 | B103: =PEMAGANG!B19 -> MG4726 | C103: =PEMAGANG!C19 -> NILNA FAIRUSSAKTI SALBANI AFANO | D103: =PEMAGANG!D19 -> FETI MUBAIYINI | E103: =PEMAGANG!E19 -> MANDIRI | F103: =PEMAGANG!F19 -> CENTRAL JAVA CURAH ADMINISTRATION JR. OFFICER | G103: =IF(PEMAGANG!H19="","Tidak tercatat",PEMAGANG!H19) -> 46177 | H103: =IF(PEMAGANG!I19="","Tidak tercatat",PEMAGANG!I19) -> 46418 | I103: =SUMIFS(DETAIL!$I$2:$I$137,DETAIL!$B$2:$B$137,$C103) -> 74 | J103: =SUMIFS(DETAIL!$K$2:$K$137,DETAIL!$B$2:$B$137,$C103) -> 69 | K103: =IFERROR(J103/I103,0) -> 0.93243243 | L103: =I103-J103 -> 5 | M103: =SUMIFS(DETAIL!$N$2:$N$137,DETAIL!$B$2:$B$137,$C103) -> 3 | N103: =IFERROR(1-M103/SUMIFS(DETAIL!$M$2:$M$137,DETAIL!$B$2:$B$137,$C103),0) -> 0.95652174 | O103: =IFERROR(SUMIFS(DETAIL!$O$2:$O$137,DETAIL!$B$2:$B$137,$C103)/M103,0) -> 108.66667 | P103: =SUMIFS(DETAIL!$P$2:$P$137,DETAIL!$B$2:$B$137,$C103) -> 6 | Q103: =SUMIFS(DETAIL!$Q$2:$Q$137,DETAIL!$B$2:$B$137,$C103) -> 67 | R103: =IFERROR(Q103/SUMIFS(DETAIL!$M$2:$M$137,DETAIL!$B$2:$B$137,$C103),0) -> 0.97101449 | S103: =IFERROR(SUMIFS(DETAIL!$K$2:$K$137,DETAIL!$B$2:$B$137,$C103,DETAIL!$F$2:$F$137,MONTH(DATE(YEAR(SUMMARY!$C$6),MONTH(SUMMARY!$C$6)+0,1)))/SUMIFS(DETAIL!$I$2:$I$137,DETAIL!$B$2:$B$137,$C103,DETAIL!$F$2:$F$137,MONTH(DATE(YEAR(SUMMARY!$C$6),MONTH(SUMMARY!$C$6)+0,1))),"-") -> 0.93333333 | T103: =IFERROR(SUMIFS(DETAIL!$K$2:$K$137,DETAIL!$B$2:$B$137,$C103,DETAIL!$F$2:$F$137,MONTH(DATE(YEAR(SUMMARY!$C$6),MONTH(SUMMARY!$C$6)+1,1)))/SUMIFS(DETAIL!$I$2:$I$137,DETAIL!$B$2:$B$137,$C103,DETAIL!$F$2:$F$137,MONTH(DATE(YEAR(SUMMARY!$C$6),MONTH(SUMMARY!$C$6)+1,1))),"-") -> 1 | U103: =IFERROR(SUMIFS(DETAIL!$K$2:$K$137,DETAIL!$B$2:$B$137,$C103,DETAIL!$F$2:$F$137,MONTH(DATE(YEAR(SUMMARY!$C$6),MONTH(SUMMARY!$C$6)+2,1)))/SUMIFS(DETAIL!$I$2:$I$137,DETAIL!$B$2:$B$137,$C103,DETAIL!$F$2:$F$137,MONTH(DATE(YEAR(SUMMARY!$C$6),MONTH(SUMMARY!$C$6)+2,1))),"-") -> 1 | V103: =IFERROR(SUMIFS(DETAIL!$K$2:$K$137,DETAIL!$B$2:$B$137,$C103,DETAIL!$F$2:$F$137,MONTH(DATE(YEAR(SUMMARY!$C$6),MONTH(SUMMARY!$C$6)+3,1)))/SUMIFS(DETAIL!$I$2:$I$137,DETAIL!$B$2:$B$137,$C103,DETAIL!$F$2:$F$137,MONTH(DATE(YEAR(SUMMARY!$C$6),MONTH(SUMMARY!$C$6)+3,1))),"-") -> 0.81818182 | W103: =ROUND(100*(K103*SUMMARY!$C$11+N103*SUMMARY!$C$12+R103*SUMMARY!$C$13+AG103*SUMMARY!$C$17),1) -> 93.1 | X103: =IF(W103>=100*SUMMARY!$C$14,"Sangat Baik",IF(W103>=100*SUMMARY!$C$15,"Baik",IF(W103>=100*SUMMARY!$C$16,"Cukup","Perlu Pembinaan"))) -> Sangat Baik | Y103: =SUMIFS(DETAIL!$J$2:$J$137,DETAIL!$B$2:$B$137,$C103) -> 8 | Z103: =SUMIFS(DETAIL!$L$2:$L$137,DETAIL!$B$2:$B$137,$C103) -> 0 | AA103: =M103+ROW()/100000 -> 3.00103 | AB103: =W103-ROW()/100000 -> 93.09897 | AC103: =IF(I103>=40,K103-ROW()/10000000,"") -> 0.93242213 | AD103: =TEXT(PEMAGANG!J19,"dd-mm-yy")&" s.d. "&TEXT(PEMAGANG!K19,"dd-mm-yy") -> 04-06-26 s.d. 30-09-26 | AE103: =PEMAGANG!N19 -> Masuk 04-06-2026 | AF103: =IFERROR(INDEX(PRODUKTIVITAS!$J$10:$J$43,MATCH($C103,PRODUKTIVITAS!$B$10:$B$43,0)),0) -> 0.88536794 | AG103: =IFERROR(INDEX(PRODUKTIVITAS!$K$10:$K$43,MATCH($C103,PRODUKTIVITAS!$B$10:$B$43,0)),0) -> 0.88536794
A104: =ROW()-ROW($A$78)-8 -> 18 | B104: =PEMAGANG!B20 -> MG29 | C104: =PEMAGANG!C20 -> SYACHIRA FARA NABILA | D104: =PEMAGANG!D20 -> FETI MUBAIYINI | E104: =PEMAGANG!E20 -> MANDIRI | F104: =PEMAGANG!F20 -> CENTRAL JAVA CURAH ADMINISTRATION JR. OFFICER | G104: =IF(PEMAGANG!H20="","Tidak tercatat",PEMAGANG!H20) -> 45971 | H104: =IF(PEMAGANG!I20="","Tidak tercatat",PEMAGANG!I20) -> 46203 | I104: =SUMIFS(DETAIL!$I$2:$I$137,DETAIL!$B$2:$B$137,$C104) -> 16 | J104: =SUMIFS(DETAIL!$K$2:$K$137,DETAIL!$B$2:$B$137,$C104) -> 16 | K104: =IFERROR(J104/I104,0) -> 1 | L104: =I104-J104 -> 0 | M104: =SUMIFS(DETAIL!$N$2:$N$137,DETAIL!$B$2:$B$137,$C104) -> 0 | N104: =IFERROR(1-M104/SUMIFS(DETAIL!$M$2:$M$137,DETAIL!$B$2:$B$137,$C104),0) -> 1 | O104: =IFERROR(SUMIFS(DETAIL!$O$2:$O$137,DETAIL!$B$2:$B$137,$C104)/M104,0) -> 0 | P104: =SUMIFS(DETAIL!$P$2:$P$137,DETAIL!$B$2:$B$137,$C104) -> 2 | Q104: =SUMIFS(DETAIL!$Q$2:$Q$137,DETAIL!$B$2:$B$137,$C104) -> 14 | R104: =IFERROR(Q104/SUMIFS(DETAIL!$M$2:$M$137,DETAIL!$B$2:$B$137,$C104),0) -> 0.875 | S104: =IFERROR(SUMIFS(DETAIL!$K$2:$K$137,DETAIL!$B$2:$B$137,$C104,DETAIL!$F$2:$F$137,MONTH(DATE(YEAR(SUMMARY!$C$6),MONTH(SUMMARY!$C$6)+0,1)))/SUMIFS(DETAIL!$I$2:$I$137,DETAIL!$B$2:$B$137,$C104,DETAIL!$F$2:$F$137,MONTH(DATE(YEAR(SUMMARY!$C$6),MONTH(SUMMARY!$C$6)+0,1))),"-") -> 1 | T104: =IFERROR(SUMIFS(DETAIL!$K$2:$K$137,DETAIL!$B$2:$B$137,$C104,DETAIL!$F$2:$F$137,MONTH(DATE(YEAR(SUMMARY!$C$6),MONTH(SUMMARY!$C$6)+1,1)))/SUMIFS(DETAIL!$I$2:$I$137,DETAIL!$B$2:$B$137,$C104,DETAIL!$F$2:$F$137,MONTH(DATE(YEAR(SUMMARY!$C$6),MONTH(SUMMARY!$C$6)+1,1))),"-") -> - | U104: =IFERROR(SUMIFS(DETAIL!$K$2:$K$137,DETAIL!$B$2:$B$137,$C104,DETAIL!$F$2:$F$137,MONTH(DATE(YEAR(SUMMARY!$C$6),MONTH(SUMMARY!$C$6)+2,1)))/SUMIFS(DETAIL!$I$2:$I$137,DETAIL!$B$2:$B$137,$C104,DETAIL!$F$2:$F$137,MONTH(DATE(YEAR(SUMMARY!$C$6),MONTH(SUMMARY!$C$6)+2,1))),"-") -> - | V104: =IFERROR(SUMIFS(DETAIL!$K$2:$K$137,DETAIL!$B$2:$B$137,$C104,DETAIL!$F$2:$F$137,MONTH(DATE(YEAR(SUMMARY!$C$6),MONTH(SUMMARY!$C$6)+3,1)))/SUMIFS(DETAIL!$I$2:$I$137,DETAIL!$B$2:$B$137,$C104,DETAIL!$F$2:$F$137,MONTH(DATE(YEAR(SUMMARY!$C$6),MONTH(SUMMARY!$C$6)+3,1))),"-") -> - | W104: =ROUND(100*(K104*SUMMARY!$C$11+N104*SUMMARY!$C$12+R104*SUMMARY!$C$13+AG104*SUMMARY!$C$17),1) -> 76.7 | X104: =IF(W104>=100*SUMMARY!$C$14,"Sangat Baik",IF(W104>=100*SUMMARY!$C$15,"Baik",IF(W104>=100*SUMMARY!$C$16,"Cukup","Perlu Pembinaan"))) -> Cukup | Y104: =SUMIFS(DETAIL!$J$2:$J$137,DETAIL!$B$2:$B$137,$C104) -> 4 | Z104: =SUMIFS(DETAIL!$L$2:$L$137,DETAIL!$B$2:$B$137,$C104) -> 1 | AA104: =M104+ROW()/100000 -> 0.00104 | AB104: =W104-ROW()/100000 -> 76.69896 | AC104: =IF(I104>=40,K104-ROW()/10000000,"") | AD104: =TEXT(PEMAGANG!J20,"dd-mm-yy")&" s.d. "&TEXT(PEMAGANG!K20,"dd-mm-yy") -> 01-06-26 s.d. 30-06-26 | AE104: =PEMAGANG!N20 -> Selesai 30-06-2026 | AF104: =IFERROR(INDEX(PRODUKTIVITAS!$J$10:$J$43,MATCH($C104,PRODUKTIVITAS!$B$10:$B$43,0)),0) -> 0.30667882 | AG104: =IFERROR(INDEX(PRODUKTIVITAS!$K$10:$K$43,MATCH($C104,PRODUKTIVITAS!$B$10:$B$43,0)),0) -> 0.30667882
A105: ="Pembimbing: "&D106&" ("&COUNTIF($D$79:$D$133,D106)&" pemagang)" -> Pembimbing: GANANG MUSYAFFA FAHMI (1 pemagang)
A106: =ROW()-ROW($A$78)-9 -> 19 | B106: =PEMAGANG!B21 -> MG12 | C106: =PEMAGANG!C21 -> SELVI NURUL HASANAH | D106: =PEMAGANG!D21 -> GANANG MUSYAFFA FAHMI | E106: =PEMAGANG!E21 -> Kontrak Project | F106: =PEMAGANG!F21 -> PKSDM | G106: =IF(PEMAGANG!H21="","Tidak tercatat",PEMAGANG!H21) -> 45855 | H106: =IF(PEMAGANG!I21="","Tidak tercatat",PEMAGANG!I21) -> 46418 | I106: =SUMIFS(DETAIL!$I$2:$I$137,DETAIL!$B$2:$B$137,$C106) -> 75 | J106: =SUMIFS(DETAIL!$K$2:$K$137,DETAIL!$B$2:$B$137,$C106) -> 71 | K106: =IFERROR(J106/I106,0) -> 0.94666667 | L106: =I106-J106 -> 4 | M106: =SUMIFS(DETAIL!$N$2:$N$137,DETAIL!$B$2:$B$137,$C106) -> 0 | N106: =IFERROR(1-M106/SUMIFS(DETAIL!$M$2:$M$137,DETAIL!$B$2:$B$137,$C106),0) -> 1 | O106: =IFERROR(SUMIFS(DETAIL!$O$2:$O$137,DETAIL!$B$2:$B$137,$C106)/M106,0) -> 0 | P106: =SUMIFS(DETAIL!$P$2:$P$137,DETAIL!$B$2:$B$137,$C106) -> 5 | Q106: =SUMIFS(DETAIL!$Q$2:$Q$137,DETAIL!$B$2:$B$137,$C106) -> 74 | R106: =IFERROR(Q106/SUMIFS(DETAIL!$M$2:$M$137,DETAIL!$B$2:$B$137,$C106),0) -> 0.97368421 | S106: =IFERROR(SUMIFS(DETAIL!$K$2:$K$137,DETAIL!$B$2:$B$137,$C106,DETAIL!$F$2:$F$137,MONTH(DATE(YEAR(SUMMARY!$C$6),MONTH(SUMMARY!$C$6)+0,1)))/SUMIFS(DETAIL!$I$2:$I$137,DETAIL!$B$2:$B$137,$C106,DETAIL!$F$2:$F$137,MONTH(DATE(YEAR(SUMMARY!$C$6),MONTH(SUMMARY!$C$6)+0,1))),"-") -> 0.9375 | T106: =IFERROR(SUMIFS(DETAIL!$K$2:$K$137,DETAIL!$B$2:$B$137,$C106,DETAIL!$F$2:$F$137,MONTH(DATE(YEAR(SUMMARY!$C$6),MONTH(SUMMARY!$C$6)+1,1)))/SUMIFS(DETAIL!$I$2:$I$137,DETAIL!$B$2:$B$137,$C106,DETAIL!$F$2:$F$137,MONTH(DATE(YEAR(SUMMARY!$C$6),MONTH(SUMMARY!$C$6)+1,1))),"-") -> 0.94444444 | U106: =IFERROR(SUMIFS(DETAIL!$K$2:$K$137,DETAIL!$B$2:$B$137,$C106,DETAIL!$F$2:$F$137,MONTH(DATE(YEAR(SUMMARY!$C$6),MONTH(SUMMARY!$C$6)+2,1)))/SUMIFS(DETAIL!$I$2:$I$137,DETAIL!$B$2:$B$137,$C106,DETAIL!$F$2:$F$137,MONTH(DATE(YEAR(SUMMARY!$C$6),MONTH(SUMMARY!$C$6)+2,1))),"-") -> 0.94736842 | V106: =IFERROR(SUMIFS(DETAIL!$K$2:$K$137,DETAIL!$B$2:$B$137,$C106,DETAIL!$F$2:$F$137,MONTH(DATE(YEAR(SUMMARY!$C$6),MONTH(SUMMARY!$C$6)+3,1)))/SUMIFS(DETAIL!$I$2:$I$137,DETAIL!$B$2:$B$137,$C106,DETAIL!$F$2:$F$137,MONTH(DATE(YEAR(SUMMARY!$C$6),MONTH(SUMMARY!$C$6)+3,1))),"-") -> 0.95454545 | W106: =ROUND(100*(K106*SUMMARY!$C$11+N106*SUMMARY!$C$12+R106*SUMMARY!$C$13+AG106*SUMMARY!$C$17),1) -> 97.9 | X106: =IF(W106>=100*SUMMARY!$C$14,"Sangat Baik",IF(W106>=100*SUMMARY!$C$15,"Baik",IF(W106>=100*SUMMARY!$C$16,"Cukup","Perlu Pembinaan"))) -> Sangat Baik | Y106: =SUMIFS(DETAIL!$J$2:$J$137,DETAIL!$B$2:$B$137,$C106) -> 9 | Z106: =SUMIFS(DETAIL!$L$2:$L$137,DETAIL!$B$2:$B$137,$C106) -> 5 | AA106: =M106+ROW()/100000 -> 0.00106 | AB106: =W106-ROW()/100000 -> 97.89894 | AC106: =IF(I106>=40,K106-ROW()/10000000,"") -> 0.94665607 | AD106: =TEXT(PEMAGANG!J21,"dd-mm-yy")&" s.d. "&TEXT(PEMAGANG!K21,"dd-mm-yy") -> 01-06-26 s.d. 30-09-26 | AE106: =PEMAGANG!N21 -> Aktif sepanjang periode | AF106: =IFERROR(INDEX(PRODUKTIVITAS!$J$10:$J$43,MATCH($C106,PRODUKTIVITAS!$B$10:$B$43,0)),0) -> 2.2128952 | AG106: =IFERROR(INDEX(PRODUKTIVITAS!$K$10:$K$43,MATCH($C106,PRODUKTIVITAS!$B$10:$B$43,0)),0) -> 1
A107: ="Pembimbing: "&D108&" ("&COUNTIF($D$79:$D$133,D108)&" pemagang)" -> Pembimbing: HASKIN AVIONATA (1 pemagang)
A108: =ROW()-ROW($A$78)-10 -> 20 | B108: =PEMAGANG!B22 -> MG3826 | C108: =PEMAGANG!C22 -> FARREL ALWIN RAHMADHAN | D108: =PEMAGANG!D22 -> HASKIN AVIONATA | E108: =PEMAGANG!E22 -> MANDIRI | F108: =PEMAGANG!F22 -> EQUALISATION OFFICER (SID) | G108: =IF(PEMAGANG!H22="","Tidak tercatat",PEMAGANG!H22) -> 46031 | H108: =IF(PEMAGANG!I22="","Tidak tercatat",PEMAGANG!I22) -> 46387 | I108: =SUMIFS(DETAIL!$I$2:$I$137,DETAIL!$B$2:$B$137,$C108) -> 75 | J108: =SUMIFS(DETAIL!$K$2:$K$137,DETAIL!$B$2:$B$137,$C108) -> 64 | K108: =IFERROR(J108/I108,0) -> 0.85333333 | L108: =I108-J108 -> 11 | M108: =SUMIFS(DETAIL!$N$2:$N$137,DETAIL!$B$2:$B$137,$C108) -> 17 | N108: =IFERROR(1-M108/SUMIFS(DETAIL!$M$2:$M$137,DETAIL!$B$2:$B$137,$C108),0) -> 0.73846154 | O108: =IFERROR(SUMIFS(DETAIL!$O$2:$O$137,DETAIL!$B$2:$B$137,$C108)/M108,0) -> 3.8235294 | P108: =SUMIFS(DETAIL!$P$2:$P$137,DETAIL!$B$2:$B$137,$C108) -> 3 | Q108: =SUMIFS(DETAIL!$Q$2:$Q$137,DETAIL!$B$2:$B$137,$C108) -> 63 | R108: =IFERROR(Q108/SUMIFS(DETAIL!$M$2:$M$137,DETAIL!$B$2:$B$137,$C108),0) -> 0.96923077 | S108: =IFERROR(SUMIFS(DETAIL!$K$2:$K$137,DETAIL!$B$2:$B$137,$C108,DETAIL!$F$2:$F$137,MONTH(DATE(YEAR(SUMMARY!$C$6),MONTH(SUMMARY!$C$6)+0,1)))/SUMIFS(DETAIL!$I$2:$I$137,DETAIL!$B$2:$B$137,$C108,DETAIL!$F$2:$F$137,MONTH(DATE(YEAR(SUMMARY!$C$6),MONTH(SUMMARY!$C$6)+0,1))),"-") -> 0.5625 | T108: =IFERROR(SUMIFS(DETAIL!$K$2:$K$137,DETAIL!$B$2:$B$137,$C108,DETAIL!$F$2:$F$137,MONTH(DATE(YEAR(SUMMARY!$C$6),MONTH(SUMMARY!$C$6)+1,1)))/SUMIFS(DETAIL!$I$2:$I$137,DETAIL!$B$2:$B$137,$C108,DETAIL!$F$2:$F$137,MONTH(DATE(YEAR(SUMMARY!$C$6),MONTH(SUMMARY!$C$6)+1,1))),"-") -> 0.83333333 | U108: =IFERROR(SUMIFS(DETAIL!$K$2:$K$137,DETAIL!$B$2:$B$137,$C108,DETAIL!$F$2:$F$137,MONTH(DATE(YEAR(SUMMARY!$C$6),MONTH(SUMMARY!$C$6)+2,1)))/SUMIFS(DETAIL!$I$2:$I$137,DETAIL!$B$2:$B$137,$C108,DETAIL!$F$2:$F$137,MONTH(DATE(YEAR(SUMMARY!$C$6),MONTH(SUMMARY!$C$6)+2,1))),"-") -> 0.94736842 | V108: =IFERROR(SUMIFS(DETAIL!$K$2:$K$137,DETAIL!$B$2:$B$137,$C108,DETAIL!$F$2:$F$137,MONTH(DATE(YEAR(SUMMARY!$C$6),MONTH(SUMMARY!$C$6)+3,1)))/SUMIFS(DETAIL!$I$2:$I$137,DETAIL!$B$2:$B$137,$C108,DETAIL!$F$2:$F$137,MONTH(DATE(YEAR(SUMMARY!$C$6),MONTH(SUMMARY!$C$6)+3,1))),"-") -> 1 | W108: =ROUND(100*(K108*SUMMARY!$C$11+N108*SUMMARY!$C$12+R108*SUMMARY!$C$13+AG108*SUMMARY!$C$17),1) -> 78.1 | X108: =IF(W108>=100*SUMMARY!$C$14,"Sangat Baik",IF(W108>=100*SUMMARY!$C$15,"Baik",IF(W108>=100*SUMMARY!$C$16,"Cukup","Perlu Pembinaan"))) -> Cukup | Y108: =SUMIFS(DETAIL!$J$2:$J$137,DETAIL!$B$2:$B$137,$C108) -> 9 | Z108: =SUMIFS(DETAIL!$L$2:$L$137,DETAIL!$B$2:$B$137,$C108) -> 1 | AA108: =M108+ROW()/100000 -> 17.00108 | AB108: =W108-ROW()/100000 -> 78.09892 | AC108: =IF(I108>=40,K108-ROW()/10000000,"") -> 0.85332253 | AD108: =TEXT(PEMAGANG!J22,"dd-mm-yy")&" s.d. "&TEXT(PEMAGANG!K22,"dd-mm-yy") -> 01-06-26 s.d. 30-09-26 | AE108: =PEMAGANG!N22 -> Aktif sepanjang periode | AF108: =IFERROR(INDEX(PRODUKTIVITAS!$J$10:$J$43,MATCH($C108,PRODUKTIVITAS!$B$10:$B$43,0)),0) -> 0.61100401 | AG108: =IFERROR(INDEX(PRODUKTIVITAS!$K$10:$K$43,MATCH($C108,PRODUKTIVITAS!$B$10:$B$43,0)),0) -> 0.61100401
A109: ="Pembimbing: "&D110&" ("&COUNTIF($D$79:$D$133,D110)&" pemagang)" -> Pembimbing: IMAM SUBEKTI (1 pemagang)
A110: =ROW()-ROW($A$78)-11 -> 21 | B110: =PEMAGANG!B23 -> INT/SILOG/260353 | C110: =PEMAGANG!C23 -> MASDUQI MUHAMMAD | D110: =PEMAGANG!D23 -> IMAM SUBEKTI | E110: =PEMAGANG!E23 -> - | F110: =PEMAGANG!F23 -> PGS MANAGER OF LAMONGAN BRANCH | G110: =IF(PEMAGANG!H23="","Tidak tercatat",PEMAGANG!H23) -> Tidak tercatat | H110: =IF(PEMAGANG!I23="","Tidak tercatat",PEMAGANG!I23) -> Tidak tercatat | I110: =SUMIFS(DETAIL!$I$2:$I$137,DETAIL!$B$2:$B$137,$C110) -> 20 | J110: =SUMIFS(DETAIL!$K$2:$K$137,DETAIL!$B$2:$B$137,$C110) -> 15 | K110: =IFERROR(J110/I110,0) -> 0.75 | L110: =I110-J110 -> 5 | M110: =SUMIFS(DETAIL!$N$2:$N$137,DETAIL!$B$2:$B$137,$C110) -> 8 | N110: =IFERROR(1-M110/SUMIFS(DETAIL!$M$2:$M$137,DETAIL!$B$2:$B$137,$C110),0) -> 0.46666667 | O110: =IFERROR(SUMIFS(DETAIL!$O$2:$O$137,DETAIL!$B$2:$B$137,$C110)/M110,0) -> 18.75 | P110: =SUMIFS(DETAIL!$P$2:$P$137,DETAIL!$B$2:$B$137,$C110) -> 12 | Q110: =SUMIFS(DETAIL!$Q$2:$Q$137,DETAIL!$B$2:$B$137,$C110) -> 0 | R110: =IFERROR(Q110/SUMIFS(DETAIL!$M$2:$M$137,DETAIL!$B$2:$B$137,$C110),0) -> 0 | S110: =IFERROR(SUMIFS(DETAIL!$K$2:$K$137,DETAIL!$B$2:$B$137,$C110,DETAIL!$F$2:$F$137,MONTH(DATE(YEAR(SUMMARY!$C$6),MONTH(SUMMARY!$C$6)+0,1)))/SUMIFS(DETAIL!$I$2:$I$137,DETAIL!$B$2:$B$137,$C110,DETAIL!$F$2:$F$137,MONTH(DATE(YEAR(SUMMARY!$C$6),MONTH(SUMMARY!$C$6)+0,1))),"-") -> - | T110: =IFERROR(SUMIFS(DETAIL!$K$2:$K$137,DETAIL!$B$2:$B$137,$C110,DETAIL!$F$2:$F$137,MONTH(DATE(YEAR(SUMMARY!$C$6),MONTH(SUMMARY!$C$6)+1,1)))/SUMIFS(DETAIL!$I$2:$I$137,DETAIL!$B$2:$B$137,$C110,DETAIL!$F$2:$F$137,MONTH(DATE(YEAR(SUMMARY!$C$6),MONTH(SUMMARY!$C$6)+1,1))),"-") -> - | U110: =IFERROR(SUMIFS(DETAIL!$K$2:$K$137,DETAIL!$B$2:$B$137,$C110,DETAIL!$F$2:$F$137,MONTH(DATE(YEAR(SUMMARY!$C$6),MONTH(SUMMARY!$C$6)+2,1)))/SUMIFS(DETAIL!$I$2:$I$137,DETAIL!$B$2:$B$137,$C110,DETAIL!$F$2:$F$137,MONTH(DATE(YEAR(SUMMARY!$C$6),MONTH(SUMMARY!$C$6)+2,1))),"-") -> - | V110: =IFERROR(SUMIFS(DETAIL!$K$2:$K$137,DETAIL!$B$2:$B$137,$C110,DETAIL!$F$2:$F$137,MONTH(DATE(YEAR(SUMMARY!$C$6),MONTH(SUMMARY!$C$6)+3,1)))/SUMIFS(DETAIL!$I$2:$I$137,DETAIL!$B$2:$B$137,$C110,DETAIL!$F$2:$F$137,MONTH(DATE(YEAR(SUMMARY!$C$6),MONTH(SUMMARY!$C$6)+3,1))),"-") -> 0.75 | W110: =ROUND(100*(K110*SUMMARY!$C$11+N110*SUMMARY!$C$12+R110*SUMMARY!$C$13+AG110*SUMMARY!$C$17),1) -> 31.8 | X110: =IF(W110>=100*SUMMARY!$C$14,"Sangat Baik",IF(W110>=100*SUMMARY!$C$15,"Baik",IF(W110>=100*SUMMARY!$C$16,"Cukup","Perlu Pembinaan"))) -> Perlu Pembinaan | Y110: =SUMIFS(DETAIL!$J$2:$J$137,DETAIL!$B$2:$B$137,$C110) -> 0 | Z110: =SUMIFS(DETAIL!$L$2:$L$137,DETAIL!$B$2:$B$137,$C110) -> 0 | AA110: =M110+ROW()/100000 -> 8.0011 | AB110: =W110-ROW()/100000 -> 31.7989 | AC110: =IF(I110>=40,K110-ROW()/10000000,"") | AD110: =TEXT(PEMAGANG!J23,"dd-mm-yy")&" s.d. "&TEXT(PEMAGANG!K23,"dd-mm-yy") -> 03-09-26 s.d. 30-09-26 | AE110: =PEMAGANG!N23 -> Masuk 03-09-2026 | AF110: =IFERROR(INDEX(PRODUKTIVITAS!$J$10:$J$43,MATCH($C110,PRODUKTIVITAS!$B$10:$B$43,0)),0) -> 0 | AG110: =IFERROR(INDEX(PRODUKTIVITAS!$K$10:$K$43,MATCH($C110,PRODUKTIVITAS!$B$10:$B$43,0)),0) -> 0
A111: ="Pembimbing: "&D112&" ("&COUNTIF($D$79:$D$133,D112)&" pemagang)" -> Pembimbing: IMANIAR PUTRI UTAMI (1 pemagang)
A112: =ROW()-ROW($A$78)-12 -> 22 | B112: =PEMAGANG!B24 -> MG5226 | C112: =PEMAGANG!C24 -> CITRA ANGGRAINI | D112: =PEMAGANG!D24 -> IMANIAR PUTRI UTAMI | E112: =PEMAGANG!E24 -> MANDIRI | F112: =PEMAGANG!F24 -> MANAGER OF VERIFICATION | G112: =IF(PEMAGANG!H24="","Tidak tercatat",PEMAGANG!H24) -> 46279 | H112: =IF(PEMAGANG!I24="","Tidak tercatat",PEMAGANG!I24) -> 46460 | I112: =SUMIFS(DETAIL!$I$2:$I$137,DETAIL!$B$2:$B$137,$C112) -> 13 | J112: =SUMIFS(DETAIL!$K$2:$K$137,DETAIL!$B$2:$B$137,$C112) -> 13 | K112: =IFERROR(J112/I112,0) -> 1 | L112: =I112-J112 -> 0 | M112: =SUMIFS(DETAIL!$N$2:$N$137,DETAIL!$B$2:$B$137,$C112) -> 1 | N112: =IFERROR(1-M112/SUMIFS(DETAIL!$M$2:$M$137,DETAIL!$B$2:$B$137,$C112),0) -> 0.92307692 | O112: =IFERROR(SUMIFS(DETAIL!$O$2:$O$137,DETAIL!$B$2:$B$137,$C112)/M112,0) -> 202 | P112: =SUMIFS(DETAIL!$P$2:$P$137,DETAIL!$B$2:$B$137,$C112) -> 0 | Q112: =SUMIFS(DETAIL!$Q$2:$Q$137,DETAIL!$B$2:$B$137,$C112) -> 13 | R112: =IFERROR(Q112/SUMIFS(DETAIL!$M$2:$M$137,DETAIL!$B$2:$B$137,$C112),0) -> 1 | S112: =IFERROR(SUMIFS(DETAIL!$K$2:$K$137,DETAIL!$B$2:$B$137,$C112,DETAIL!$F$2:$F$137,MONTH(DATE(YEAR(SUMMARY!$C$6),MONTH(SUMMARY!$C$6)+0,1)))/SUMIFS(DETAIL!$I$2:$I$137,DETAIL!$B$2:$B$137,$C112,DETAIL!$F$2:$F$137,MONTH(DATE(YEAR(SUMMARY!$C$6),MONTH(SUMMARY!$C$6)+0,1))),"-") -> - | T112: =IFERROR(SUMIFS(DETAIL!$K$2:$K$137,DETAIL!$B$2:$B$137,$C112,DETAIL!$F$2:$F$137,MONTH(DATE(YEAR(SUMMARY!$C$6),MONTH(SUMMARY!$C$6)+1,1)))/SUMIFS(DETAIL!$I$2:$I$137,DETAIL!$B$2:$B$137,$C112,DETAIL!$F$2:$F$137,MONTH(DATE(YEAR(SUMMARY!$C$6),MONTH(SUMMARY!$C$6)+1,1))),"-") -> - | U112: =IFERROR(SUMIFS(DETAIL!$K$2:$K$137,DETAIL!$B$2:$B$137,$C112,DETAIL!$F$2:$F$137,MONTH(DATE(YEAR(SUMMARY!$C$6),MONTH(SUMMARY!$C$6)+2,1)))/SUMIFS(DETAIL!$I$2:$I$137,DETAIL!$B$2:$B$137,$C112,DETAIL!$F$2:$F$137,MONTH(DATE(YEAR(SUMMARY!$C$6),MONTH(SUMMARY!$C$6)+2,1))),"-") -> - | V112: =IFERROR(SUMIFS(DETAIL!$K$2:$K$137,DETAIL!$B$2:$B$137,$C112,DETAIL!$F$2:$F$137,MONTH(DATE(YEAR(SUMMARY!$C$6),MONTH(SUMMARY!$C$6)+3,1)))/SUMIFS(DETAIL!$I$2:$I$137,DETAIL!$B$2:$B$137,$C112,DETAIL!$F$2:$F$137,MONTH(DATE(YEAR(SUMMARY!$C$6),MONTH(SUMMARY!$C$6)+3,1))),"-") -> 1 | W112: =ROUND(100*(K112*SUMMARY!$C$11+N112*SUMMARY!$C$12+R112*SUMMARY!$C$13+AG112*SUMMARY!$C$17),1) -> 91.8 | X112: =IF(W112>=100*SUMMARY!$C$14,"Sangat Baik",IF(W112>=100*SUMMARY!$C$15,"Baik",IF(W112>=100*SUMMARY!$C$16,"Cukup","Perlu Pembinaan"))) -> Sangat Baik | Y112: =SUMIFS(DETAIL!$J$2:$J$137,DETAIL!$B$2:$B$137,$C112) -> 0 | Z112: =SUMIFS(DETAIL!$L$2:$L$137,DETAIL!$B$2:$B$137,$C112) -> 0 | AA112: =M112+ROW()/100000 -> 1.00112 | AB112: =W112-ROW()/100000 -> 91.79888 | AC112: =IF(I112>=40,K112-ROW()/10000000,"") | AD112: =TEXT(PEMAGANG!J24,"dd-mm-yy")&" s.d. "&TEXT(PEMAGANG!K24,"dd-mm-yy") -> 14-09-26 s.d. 30-09-26 | AE112: =PEMAGANG!N24 -> Masuk 14-09-2026 | AF112: =IFERROR(INDEX(PRODUKTIVITAS!$J$10:$J$43,MATCH($C112,PRODUKTIVITAS!$B$10:$B$43,0)),0) -> 0.7791278 | AG112: =IFERROR(INDEX(PRODUKTIVITAS!$K$10:$K$43,MATCH($C112,PRODUKTIVITAS!$B$10:$B$43,0)),0) -> 0.7791278
A113: ="Pembimbing: "&D114&" ("&COUNTIF($D$79:$D$133,D114)&" pemagang)" -> Pembimbing: M. RIZAD FAHRURI (1 pemagang)
A114: =ROW()-ROW($A$78)-13 -> 23 | B114: =PEMAGANG!B25 -> MG/KH/3125 | C114: =PEMAGANG!C25 -> KHOFIFATUNNABILAH | D114: =PEMAGANG!D25 -> M. RIZAD FAHRURI | E114: =PEMAGANG!E25 -> Kontrak Project | F114: =PEMAGANG!F25 -> PGS FINANCIAL ANALYSIS OFFICER | G114: =IF(PEMAGANG!H25="","Tidak tercatat",PEMAGANG!H25) -> 45985 | H114: =IF(PEMAGANG!I25="","Tidak tercatat",PEMAGANG!I25) -> 46356 | I114: =SUMIFS(DETAIL!$I$2:$I$137,DETAIL!$B$2:$B$137,$C114) -> 75 | J114: =SUMIFS(DETAIL!$K$2:$K$137,DETAIL!$B$2:$B$137,$C114) -> 72 | K114: =IFERROR(J114/I114,0) -> 0.96 | L114: =I114-J114 -> 3 | M114: =SUMIFS(DETAIL!$N$2:$N$137,DETAIL!$B$2:$B$137,$C114) -> 0 | N114: =IFERROR(1-M114/SUMIFS(DETAIL!$M$2:$M$137,DETAIL!$B$2:$B$137,$C114),0) -> 1 | O114: =IFERROR(SUMIFS(DETAIL!$O$2:$O$137,DETAIL!$B$2:$B$137,$C114)/M114,0) -> 0 | P114: =SUMIFS(DETAIL!$P$2:$P$137,DETAIL!$B$2:$B$137,$C114) -> 3 | Q114: =SUMIFS(DETAIL!$Q$2:$Q$137,DETAIL!$B$2:$B$137,$C114) -> 77 | R114: =IFERROR(Q114/SUMIFS(DETAIL!$M$2:$M$137,DETAIL!$B$2:$B$137,$C114),0) -> 0.98717949 | S114: =IFERROR(SUMIFS(DETAIL!$K$2:$K$137,DETAIL!$B$2:$B$137,$C114,DETAIL!$F$2:$F$137,MONTH(DATE(YEAR(SUMMARY!$C$6),MONTH(SUMMARY!$C$6)+0,1)))/SUMIFS(DETAIL!$I$2:$I$137,DETAIL!$B$2:$B$137,$C114,DETAIL!$F$2:$F$137,MONTH(DATE(YEAR(SUMMARY!$C$6),MONTH(SUMMARY!$C$6)+0,1))),"-") -> 1 | T114: =IFERROR(SUMIFS(DETAIL!$K$2:$K$137,DETAIL!$B$2:$B$137,$C114,DETAIL!$F$2:$F$137,MONTH(DATE(YEAR(SUMMARY!$C$6),MONTH(SUMMARY!$C$6)+1,1)))/SUMIFS(DETAIL!$I$2:$I$137,DETAIL!$B$2:$B$137,$C114,DETAIL!$F$2:$F$137,MONTH(DATE(YEAR(SUMMARY!$C$6),MONTH(SUMMARY!$C$6)+1,1))),"-") -> 0.83333333 | U114: =IFERROR(SUMIFS(DETAIL!$K$2:$K$137,DETAIL!$B$2:$B$137,$C114,DETAIL!$F$2:$F$137,MONTH(DATE(YEAR(SUMMARY!$C$6),MONTH(SUMMARY!$C$6)+2,1)))/SUMIFS(DETAIL!$I$2:$I$137,DETAIL!$B$2:$B$137,$C114,DETAIL!$F$2:$F$137,MONTH(DATE(YEAR(SUMMARY!$C$6),MONTH(SUMMARY!$C$6)+2,1))),"-") -> 1 | V114: =IFERROR(SUMIFS(DETAIL!$K$2:$K$137,DETAIL!$B$2:$B$137,$C114,DETAIL!$F$2:$F$137,MONTH(DATE(YEAR(SUMMARY!$C$6),MONTH(SUMMARY!$C$6)+3,1)))/SUMIFS(DETAIL!$I$2:$I$137,DETAIL!$B$2:$B$137,$C114,DETAIL!$F$2:$F$137,MONTH(DATE(YEAR(SUMMARY!$C$6),MONTH(SUMMARY!$C$6)+3,1))),"-") -> 1 | W114: =ROUND(100*(K114*SUMMARY!$C$11+N114*SUMMARY!$C$12+R114*SUMMARY!$C$13+AG114*SUMMARY!$C$17),1) -> 98.5 | X114: =IF(W114>=100*SUMMARY!$C$14,"Sangat Baik",IF(W114>=100*SUMMARY!$C$15,"Baik",IF(W114>=100*SUMMARY!$C$16,"Cukup","Perlu Pembinaan"))) -> Sangat Baik | Y114: =SUMIFS(DETAIL!$J$2:$J$137,DETAIL!$B$2:$B$137,$C114) -> 9 | Z114: =SUMIFS(DETAIL!$L$2:$L$137,DETAIL!$B$2:$B$137,$C114) -> 6 | AA114: =M114+ROW()/100000 -> 0.00114 | AB114: =W114-ROW()/100000 -> 98.49886 | AC114: =IF(I114>=40,K114-ROW()/10000000,"") -> 0.9599886 | AD114: =TEXT(PEMAGANG!J25,"dd-mm-yy")&" s.d. "&TEXT(PEMAGANG!K25,"dd-mm-yy") -> 01-06-26 s.d. 30-09-26 | AE114: =PEMAGANG!N25 -> Aktif sepanjang periode | AF114: =IFERROR(INDEX(PRODUKTIVITAS!$J$10:$J$43,MATCH($C114,PRODUKTIVITAS!$B$10:$B$43,0)),0) -> 1.9549136 | AG114: =IFERROR(INDEX(PRODUKTIVITAS!$K$10:$K$43,MATCH($C114,PRODUKTIVITAS!$B$10:$B$43,0)),0) -> 1
A115: ="Pembimbing: "&D116&" ("&COUNTIF($D$79:$D$133,D116)&" pemagang)" -> Pembimbing: MOH. AGUS EFENDI (2 pemagang)
A116: =ROW()-ROW($A$78)-14 -> 24 | B116: =PEMAGANG!B26 -> MG/KH/3925 | C116: =PEMAGANG!C26 -> ANGGUN NUR TSANIA AGUSTIN | D116: =PEMAGANG!D26 -> MOH. AGUS EFENDI | E116: =PEMAGANG!E26 -> Kontrak Project | F116: =PEMAGANG!F26 -> MANAGER OF TRANSPORTATION | G116: =IF(PEMAGANG!H26="","Tidak tercatat",PEMAGANG!H26) -> 45985 | H116: =IF(PEMAGANG!I26="","Tidak tercatat",PEMAGANG!I26) -> 46356 | I116: =SUMIFS(DETAIL!$I$2:$I$137,DETAIL!$B$2:$B$137,$C116) -> 75 | J116: =SUMIFS(DETAIL!$K$2:$K$137,DETAIL!$B$2:$B$137,$C116) -> 73 | K116: =IFERROR(J116/I116,0) -> 0.97333333 | L116: =I116-J116 -> 2 | M116: =SUMIFS(DETAIL!$N$2:$N$137,DETAIL!$B$2:$B$137,$C116) -> 0 | N116: =IFERROR(1-M116/SUMIFS(DETAIL!$M$2:$M$137,DETAIL!$B$2:$B$137,$C116),0) -> 1 | O116: =IFERROR(SUMIFS(DETAIL!$O$2:$O$137,DETAIL!$B$2:$B$137,$C116)/M116,0) -> 0 | P116: =SUMIFS(DETAIL!$P$2:$P$137,DETAIL!$B$2:$B$137,$C116) -> 1 | Q116: =SUMIFS(DETAIL!$Q$2:$Q$137,DETAIL!$B$2:$B$137,$C116) -> 80 | R116: =IFERROR(Q116/SUMIFS(DETAIL!$M$2:$M$137,DETAIL!$B$2:$B$137,$C116),0) -> 0.98765432 | S116: =IFERROR(SUMIFS(DETAIL!$K$2:$K$137,DETAIL!$B$2:$B$137,$C116,DETAIL!$F$2:$F$137,MONTH(DATE(YEAR(SUMMARY!$C$6),MONTH(SUMMARY!$C$6)+0,1)))/SUMIFS(DETAIL!$I$2:$I$137,DETAIL!$B$2:$B$137,$C116,DETAIL!$F$2:$F$137,MONTH(DATE(YEAR(SUMMARY!$C$6),MONTH(SUMMARY!$C$6)+0,1))),"-") -> 1 | T116: =IFERROR(SUMIFS(DETAIL!$K$2:$K$137,DETAIL!$B$2:$B$137,$C116,DETAIL!$F$2:$F$137,MONTH(DATE(YEAR(SUMMARY!$C$6),MONTH(SUMMARY!$C$6)+1,1)))/SUMIFS(DETAIL!$I$2:$I$137,DETAIL!$B$2:$B$137,$C116,DETAIL!$F$2:$F$137,MONTH(DATE(YEAR(SUMMARY!$C$6),MONTH(SUMMARY!$C$6)+1,1))),"-") -> 0.88888889 | U116: =IFERROR(SUMIFS(DETAIL!$K$2:$K$137,DETAIL!$B$2:$B$137,$C116,DETAIL!$F$2:$F$137,MONTH(DATE(YEAR(SUMMARY!$C$6),MONTH(SUMMARY!$C$6)+2,1)))/SUMIFS(DETAIL!$I$2:$I$137,DETAIL!$B$2:$B$137,$C116,DETAIL!$F$2:$F$137,MONTH(DATE(YEAR(SUMMARY!$C$6),MONTH(SUMMARY!$C$6)+2,1))),"-") -> 1 | V116: =IFERROR(SUMIFS(DETAIL!$K$2:$K$137,DETAIL!$B$2:$B$137,$C116,DETAIL!$F$2:$F$137,MONTH(DATE(YEAR(SUMMARY!$C$6),MONTH(SUMMARY!$C$6)+3,1)))/SUMIFS(DETAIL!$I$2:$I$137,DETAIL!$B$2:$B$137,$C116,DETAIL!$F$2:$F$137,MONTH(DATE(YEAR(SUMMARY!$C$6),MONTH(SUMMARY!$C$6)+3,1))),"-") -> 1 | W116: =ROUND(100*(K116*SUMMARY!$C$11+N116*SUMMARY!$C$12+R116*SUMMARY!$C$13+AG116*SUMMARY!$C$17),1) -> 99 | X116: =IF(W116>=100*SUMMARY!$C$14,"Sangat Baik",IF(W116>=100*SUMMARY!$C$15,"Baik",IF(W116>=100*SUMMARY!$C$16,"Cukup","Perlu Pembinaan"))) -> Sangat Baik | Y116: =SUMIFS(DETAIL!$J$2:$J$137,DETAIL!$B$2:$B$137,$C116) -> 9 | Z116: =SUMIFS(DETAIL!$L$2:$L$137,DETAIL!$B$2:$B$137,$C116) -> 8 | AA116: =M116+ROW()/100000 -> 0.00116 | AB116: =W116-ROW()/100000 -> 98.99884 | AC116: =IF(I116>=40,K116-ROW()/10000000,"") -> 0.97332173 | AD116: =TEXT(PEMAGANG!J26,"dd-mm-yy")&" s.d. "&TEXT(PEMAGANG!K26,"dd-mm-yy") -> 01-06-26 s.d. 30-09-26 | AE116: =PEMAGANG!N26 -> Aktif sepanjang periode | AF116: =IFERROR(INDEX(PRODUKTIVITAS!$J$10:$J$43,MATCH($C116,PRODUKTIVITAS!$B$10:$B$43,0)),0) -> 1.3577475 | AG116: =IFERROR(INDEX(PRODUKTIVITAS!$K$10:$K$43,MATCH($C116,PRODUKTIVITAS!$B$10:$B$43,0)),0) -> 1
A117: =ROW()-ROW($A$78)-14 -> 25 | B117: =PEMAGANG!B27 -> MG4926 | C117: =PEMAGANG!C27 -> MUHAMMAD FATCHUL ALAM | D117: =PEMAGANG!D27 -> MOH. AGUS EFENDI | E117: =PEMAGANG!E27 -> MANDIRI | F117: =PEMAGANG!F27 -> MANAGER OF TRANSPORTATION | G117: =IF(PEMAGANG!H27="","Tidak tercatat",PEMAGANG!H27) -> 46204 | H117: =IF(PEMAGANG!I27="","Tidak tercatat",PEMAGANG!I27) -> 46295 | I117: =SUMIFS(DETAIL!$I$2:$I$137,DETAIL!$B$2:$B$137,$C117) -> 59 | J117: =SUMIFS(DETAIL!$K$2:$K$137,DETAIL!$B$2:$B$137,$C117) -> 55 | K117: =IFERROR(J117/I117,0) -> 0.93220339 | L117: =I117-J117 -> 4 | M117: =SUMIFS(DETAIL!$N$2:$N$137,DETAIL!$B$2:$B$137,$C117) -> 3 | N117: =IFERROR(1-M117/SUMIFS(DETAIL!$M$2:$M$137,DETAIL!$B$2:$B$137,$C117),0) -> 0.94545455 | O117: =IFERROR(SUMIFS(DETAIL!$O$2:$O$137,DETAIL!$B$2:$B$137,$C117)/M117,0) -> 14 | P117: =SUMIFS(DETAIL!$P$2:$P$137,DETAIL!$B$2:$B$137,$C117) -> 2 | Q117: =SUMIFS(DETAIL!$Q$2:$Q$137,DETAIL!$B$2:$B$137,$C117) -> 55 | R117: =IFERROR(Q117/SUMIFS(DETAIL!$M$2:$M$137,DETAIL!$B$2:$B$137,$C117),0) -> 1 | S117: =IFERROR(SUMIFS(DETAIL!$K$2:$K$137,DETAIL!$B$2:$B$137,$C117,DETAIL!$F$2:$F$137,MONTH(DATE(YEAR(SUMMARY!$C$6),MONTH(SUMMARY!$C$6)+0,1)))/SUMIFS(DETAIL!$I$2:$I$137,DETAIL!$B$2:$B$137,$C117,DETAIL!$F$2:$F$137,MONTH(DATE(YEAR(SUMMARY!$C$6),MONTH(SUMMARY!$C$6)+0,1))),"-") -> - | T117: =IFERROR(SUMIFS(DETAIL!$K$2:$K$137,DETAIL!$B$2:$B$137,$C117,DETAIL!$F$2:$F$137,MONTH(DATE(YEAR(SUMMARY!$C$6),MONTH(SUMMARY!$C$6)+1,1)))/SUMIFS(DETAIL!$I$2:$I$137,DETAIL!$B$2:$B$137,$C117,DETAIL!$F$2:$F$137,MONTH(DATE(YEAR(SUMMARY!$C$6),MONTH(SUMMARY!$C$6)+1,1))),"-") -> 1 | U117: =IFERROR(SUMIFS(DETAIL!$K$2:$K$137,DETAIL!$B$2:$B$137,$C117,DETAIL!$F$2:$F$137,MONTH(DATE(YEAR(SUMMARY!$C$6),MONTH(SUMMARY!$C$6)+2,1)))/SUMIFS(DETAIL!$I$2:$I$137,DETAIL!$B$2:$B$137,$C117,DETAIL!$F$2:$F$137,MONTH(DATE(YEAR(SUMMARY!$C$6),MONTH(SUMMARY!$C$6)+2,1))),"-") -> 0.84210526 | V117: =IFERROR(SUMIFS(DETAIL!$K$2:$K$137,DETAIL!$B$2:$B$137,$C117,DETAIL!$F$2:$F$137,MONTH(DATE(YEAR(SUMMARY!$C$6),MONTH(SUMMARY!$C$6)+3,1)))/SUMIFS(DETAIL!$I$2:$I$137,DETAIL!$B$2:$B$137,$C117,DETAIL!$F$2:$F$137,MONTH(DATE(YEAR(SUMMARY!$C$6),MONTH(SUMMARY!$C$6)+3,1))),"-") -> 0.95454545 | W117: =ROUND(100*(K117*SUMMARY!$C$11+N117*SUMMARY!$C$12+R117*SUMMARY!$C$13+AG117*SUMMARY!$C$17),1) -> 85.6 | X117: =IF(W117>=100*SUMMARY!$C$14,"Sangat Baik",IF(W117>=100*SUMMARY!$C$15,"Baik",IF(W117>=100*SUMMARY!$C$16,"Cukup","Perlu Pembinaan"))) -> Baik | Y117: =SUMIFS(DETAIL!$J$2:$J$137,DETAIL!$B$2:$B$137,$C117) -> 5 | Z117: =SUMIFS(DETAIL!$L$2:$L$137,DETAIL!$B$2:$B$137,$C117) -> 0 | AA117: =M117+ROW()/100000 -> 3.00117 | AB117: =W117-ROW()/100000 -> 85.59883 | AC117: =IF(I117>=40,K117-ROW()/10000000,"") -> 0.93219169 | AD117: =TEXT(PEMAGANG!J27,"dd-mm-yy")&" s.d. "&TEXT(PEMAGANG!K27,"dd-mm-yy") -> 01-07-26 s.d. 30-09-26 | AE117: =PEMAGANG!N27 -> Masuk 01-07-2026 | AF117: =IFERROR(INDEX(PRODUKTIVITAS!$J$10:$J$43,MATCH($C117,PRODUKTIVITAS!$B$10:$B$43,0)),0) -> 0.62363424 | AG117: =IFERROR(INDEX(PRODUKTIVITAS!$K$10:$K$43,MATCH($C117,PRODUKTIVITAS!$B$10:$B$43,0)),0) -> 0.62363424
...

Sheet PRODUKTIVITAS
A1: ANALISIS PRODUKTIVITAS PEMAGANG
B2: Bobot jumlah entri laporan | C2: =EVALUASI!$C$28 -> 0.5 | D2: Batas "Sangat Tinggi" (indeks ≥) | E2: 1.5
B3: Bobot panjang laporan | C3: =EVALUASI!$C$29 -> 0.5 | D3: Batas "Tinggi" (indeks ≥) | E3: 1
B4: Indeks untuk nilai penuh | C4: =SUMMARY!$C$18 -> 1 | D4: Batas "Sedang" (indeks ≥) | E4: 0.7
B5: Rata-rata entri / hari hadir (semua pemagang) | C5: =SUM(DETAIL!$R$2:$R$137)/SUM(DETAIL!$M$2:$M$137) -> 1.7862998
B6: Rata-rata karakter / hari hadir (semua pemagang) | C6: =SUM(DETAIL!$T$2:$T$137)/SUM(DETAIL!$M$2:$M$137) -> 97.151639
A8: A. PRODUKTIVITAS PER PEMAGANG
A9: No | B9: Nama Pemagang | C9: Pembimbing | D9: Departemen Penempatan | E9: Hari Hadir (dlm masa magang) | F9: Entri Laporan | G9: Karakter Laporan | H9: Entri / Hari | I9: Karakter / Hari | J9: Indeks Produktivitas | K9: Nilai Produktivitas | L9: Kategori | M9: Peringkat | N9: Indeks Jun | O9: Indeks Jul | P9: Indeks Agu | Q9: Indeks Sep | R9: Skor Akhir | S9: Predikat | T9: key
A10: 1 | B10: =PEMAGANG!C3 -> ARINDA PUTRI AULIA | C10: =PEMAGANG!D3 -> AHMAD JALALUDDIN BASYAR | D10: =PEMAGANG!F3 -> PGS SM OF DIGITAL BUSSINES | E10: =SUMIFS(DETAIL!$M$2:$M$137,DETAIL!$B$2:$B$137,$B10) -> 75 | F10: =SUMIFS(DETAIL!$R$2:$R$137,DETAIL!$B$2:$B$137,$B10) -> 86 | G10: =SUMIFS(DETAIL!$T$2:$T$137,DETAIL!$B$2:$B$137,$B10) -> 1799 | H10: =IFERROR(F10/E10,0) -> 1.1466667 | I10: =IFERROR(G10/E10,0) -> 23.986667 | J10: =IFERROR($C$2*H10/$C$5+$C$3*I10/$C$6,0) -> 0.44441106 | K10: =MIN(1,IFERROR(J10/$C$4,0)) -> 0.44441106 | L10: =IF(E10=0,"-",IF(F10=0,"Tidak ada laporan",IF(J10>=$E$2,"Sangat Tinggi",IF(J10>=$E$3,"Tinggi",IF(J10>=$E$4,"Sedang","Rendah"))))) -> Rendah | M10: =RANK(T10,$T$10:$T$43) -> 28 | N10: =IFERROR($C$2*(SUMIFS(DETAIL!$R$2:$R$137,DETAIL!$B$2:$B$137,$B10,DETAIL!$F$2:$F$137,MONTH(DATE(YEAR(SUMMARY!$C$6),MONTH(SUMMARY!$C$6)+0,1)))/SUMIFS(DETAIL!$M$2:$M$137,DETAIL!$B$2:$B$137,$B10,DETAIL!$F$2:$F$137,MONTH(DATE(YEAR(SUMMARY!$C$6),MONTH(SUMMARY!$C$6)+0,1))))/$C$5+$C$3*(SUMIFS(DETAIL!$T$2:$T$137,DETAIL!$B$2:$B$137,$B10,DETAIL!$F$2:$F$137,MONTH(DATE(YEAR(SUMMARY!$C$6),MONTH(SUMMARY!$C$6)+0,1)))/SUMIFS(DETAIL!$M$2:$M$137,DETAIL!$B$2:$B$137,$B10,DETAIL!$F$2:$F$137,MONTH(DATE(YEAR(SUMMARY!$C$6),MONTH(SUMMARY!$C$6)+0,1))))/$C$6,"-") -> 0.34243104 | O10: =IFERROR($C$2*(SUMIFS(DETAIL!$R$2:$R$137,DETAIL!$B$2:$B$137,$B10,DETAIL!$F$2:$F$137,MONTH(DATE(YEAR(SUMMARY!$C$6),MONTH(SUMMARY!$C$6)+1,1)))/SUMIFS(DETAIL!$M$2:$M$137,DETAIL!$B$2:$B$137,$B10,DETAIL!$F$2:$F$137,MONTH(DATE(YEAR(SUMMARY!$C$6),MONTH(SUMMARY!$C$6)+1,1))))/$C$5+$C$3*(SUMIFS(DETAIL!$T$2:$T$137,DETAIL!$B$2:$B$137,$B10,DETAIL!$F$2:$F$137,MONTH(DATE(YEAR(SUMMARY!$C$6),MONTH(SUMMARY!$C$6)+1,1)))/SUMIFS(DETAIL!$M$2:$M$137,DETAIL!$B$2:$B$137,$B10,DETAIL!$F$2:$F$137,MONTH(DATE(YEAR(SUMMARY!$C$6),MONTH(SUMMARY!$C$6)+1,1))))/$C$6,"-") -> 0.37808672 | P10: =IFERROR($C$2*(SUMIFS(DETAIL!$R$2:$R$137,DETAIL!$B$2:$B$137,$B10,DETAIL!$F$2:$F$137,MONTH(DATE(YEAR(SUMMARY!$C$6),MONTH(SUMMARY!$C$6)+2,1)))/SUMIFS(DETAIL!$M$2:$M$137,DETAIL!$B$2:$B$137,$B10,DETAIL!$F$2:$F$137,MONTH(DATE(YEAR(SUMMARY!$C$6),MONTH(SUMMARY!$C$6)+2,1))))/$C$5+$C$3*(SUMIFS(DETAIL!$T$2:$T$137,DETAIL!$B$2:$B$137,$B10,DETAIL!$F$2:$F$137,MONTH(DATE(YEAR(SUMMARY!$C$6),MONTH(SUMMARY!$C$6)+2,1)))/SUMIFS(DETAIL!$M$2:$M$137,DETAIL!$B$2:$B$137,$B10,DETAIL!$F$2:$F$137,MONTH(DATE(YEAR(SUMMARY!$C$6),MONTH(SUMMARY!$C$6)+2,1))))/$C$6,"-") -> 0.31057809 | Q10: =IFERROR($C$2*(SUMIFS(DETAIL!$R$2:$R$137,DETAIL!$B$2:$B$137,$B10,DETAIL!$F$2:$F$137,MONTH(DATE(YEAR(SUMMARY!$C$6),MONTH(SUMMARY!$C$6)+3,1)))/SUMIFS(DETAIL!$M$2:$M$137,DETAIL!$B$2:$B$137,$B10,DETAIL!$F$2:$F$137,MONTH(DATE(YEAR(SUMMARY!$C$6),MONTH(SUMMARY!$C$6)+3,1))))/$C$5+$C$3*(SUMIFS(DETAIL!$T$2:$T$137,DETAIL!$B$2:$B$137,$B10,DETAIL!$F$2:$F$137,MONTH(DATE(YEAR(SUMMARY!$C$6),MONTH(SUMMARY!$C$6)+3,1)))/SUMIFS(DETAIL!$M$2:$M$137,DETAIL!$B$2:$B$137,$B10,DETAIL!$F$2:$F$137,MONTH(DATE(YEAR(SUMMARY!$C$6),MONTH(SUMMARY!$C$6)+3,1))))/$C$6,"-") -> 0.68680602 | R10: =IFERROR(INDEX(EVALUASI!$W$79:$W$132,MATCH($B10,EVALUASI!$C$79:$C$132,0)),"-") -> 75.5 | S10: =IFERROR(INDEX(EVALUASI!$X$79:$X$132,MATCH($B10,EVALUASI!$C$79:$C$132,0)),"-") -> Cukup | T10: =J10-ROW()/1000000 -> 0.44440106
A11: 2 | B11: =PEMAGANG!C4 -> BERLIAN AURELYA RAHMA | C11: =PEMAGANG!D4 -> AHMAD JALALUDDIN BASYAR | D11: =PEMAGANG!F4 -> PGS SM OF DIGITAL BUSSINES | E11: =SUMIFS(DETAIL!$M$2:$M$137,DETAIL!$B$2:$B$137,$B11) -> 36 | F11: =SUMIFS(DETAIL!$R$2:$R$137,DETAIL!$B$2:$B$137,$B11) -> 54 | G11: =SUMIFS(DETAIL!$T$2:$T$137,DETAIL!$B$2:$B$137,$B11) -> 3241 | H11: =IFERROR(F11/E11,0) -> 1.5 | I11: =IFERROR(G11/E11,0) -> 90.027778 | J11: =IFERROR($C$2*H11/$C$5+$C$3*I11/$C$6,0) -> 0.88319872 | K11: =MIN(1,IFERROR(J11/$C$4,0)) -> 0.88319872 | L11: =IF(E11=0,"-",IF(F11=0,"Tidak ada laporan",IF(J11>=$E$2,"Sangat Tinggi",IF(J11>=$E$3,"Tinggi",IF(J11>=$E$4,"Sedang","Rendah"))))) -> Sedang | M11: =RANK(T11,$T$10:$T$43) -> 16 | N11: =IFERROR($C$2*(SUMIFS(DETAIL!$R$2:$R$137,DETAIL!$B$2:$B$137,$B11,DETAIL!$F$2:$F$137,MONTH(DATE(YEAR(SUMMARY!$C$6),MONTH(SUMMARY!$C$6)+0,1)))/SUMIFS(DETAIL!$M$2:$M$137,DETAIL!$B$2:$B$137,$B11,DETAIL!$F$2:$F$137,MONTH(DATE(YEAR(SUMMARY!$C$6),MONTH(SUMMARY!$C$6)+0,1))))/$C$5+$C$3*(SUMIFS(DETAIL!$T$2:$T$137,DETAIL!$B$2:$B$137,$B11,DETAIL!$F$2:$F$137,MONTH(DATE(YEAR(SUMMARY!$C$6),MONTH(SUMMARY!$C$6)+0,1)))/SUMIFS(DETAIL!$M$2:$M$137,DETAIL!$B$2:$B$137,$B11,DETAIL!$F$2:$F$137,MONTH(DATE(YEAR(SUMMARY!$C$6),MONTH(SUMMARY!$C$6)+0,1))))/$C$6,"-") -> - | O11: =IFERROR($C$2*(SUMIFS(DETAIL!$R$2:$R$137,DETAIL!$B$2:$B$137,$B11,DETAIL!$F$2:$F$137,MONTH(DATE(YEAR(SUMMARY!$C$6),MONTH(SUMMARY!$C$6)+1,1)))/SUMIFS(DETAIL!$M$2:$M$137,DETAIL!$B$2:$B$137,$B11,DETAIL!$F$2:$F$137,MONTH(DATE(YEAR(SUMMARY!$C$6),MONTH(SUMMARY!$C$6)+1,1))))/$C$5+$C$3*(SUMIFS(DETAIL!$T$2:$T$137,DETAIL!$B$2:$B$137,$B11,DETAIL!$F$2:$F$137,MONTH(DATE(YEAR(SUMMARY!$C$6),MONTH(SUMMARY!$C$6)+1,1)))/SUMIFS(DETAIL!$M$2:$M$137,DETAIL!$B$2:$B$137,$B11,DETAIL!$F$2:$F$137,MONTH(DATE(YEAR(SUMMARY!$C$6),MONTH(SUMMARY!$C$6)+1,1))))/$C$6,"-") -> - | P11: =IFERROR($C$2*(SUMIFS(DETAIL!$R$2:$R$137,DETAIL!$B$2:$B$137,$B11,DETAIL!$F$2:$F$137,MONTH(DATE(YEAR(SUMMARY!$C$6),MONTH(SUMMARY!$C$6)+2,1)))/SUMIFS(DETAIL!$M$2:$M$137,DETAIL!$B$2:$B$137,$B11,DETAIL!$F$2:$F$137,MONTH(DATE(YEAR(SUMMARY!$C$6),MONTH(SUMMARY!$C$6)+2,1))))/$C$5+$C$3*(SUMIFS(DETAIL!$T$2:$T$137,DETAIL!$B$2:$B$137,$B11,DETAIL!$F$2:$F$137,MONTH(DATE(YEAR(SUMMARY!$C$6),MONTH(SUMMARY!$C$6)+2,1)))/SUMIFS(DETAIL!$M$2:$M$137,DETAIL!$B$2:$B$137,$B11,DETAIL!$F$2:$F$137,MONTH(DATE(YEAR(SUMMARY!$C$6),MONTH(SUMMARY!$C$6)+2,1))))/$C$6,"-") -> 0.79771007 | Q11: =IFERROR($C$2*(SUMIFS(DETAIL!$R$2:$R$137,DETAIL!$B$2:$B$137,$B11,DETAIL!$F$2:$F$137,MONTH(DATE(YEAR(SUMMARY!$C$6),MONTH(SUMMARY!$C$6)+3,1)))/SUMIFS(DETAIL!$M$2:$M$137,DETAIL!$B$2:$B$137,$B11,DETAIL!$F$2:$F$137,MONTH(DATE(YEAR(SUMMARY!$C$6),MONTH(SUMMARY!$C$6)+3,1))))/$C$5+$C$3*(SUMIFS(DETAIL!$T$2:$T$137,DETAIL!$B$2:$B$137,$B11,DETAIL!$F$2:$F$137,MONTH(DATE(YEAR(SUMMARY!$C$6),MONTH(SUMMARY!$C$6)+3,1)))/SUMIFS(DETAIL!$M$2:$M$137,DETAIL!$B$2:$B$137,$B11,DETAIL!$F$2:$F$137,MONTH(DATE(YEAR(SUMMARY!$C$6),MONTH(SUMMARY!$C$6)+3,1))))/$C$6,"-") -> 0.93760059 | R11: =IFERROR(INDEX(EVALUASI!$W$79:$W$132,MATCH($B11,EVALUASI!$C$79:$C$132,0)),"-") -> 89.8 | S11: =IFERROR(INDEX(EVALUASI!$X$79:$X$132,MATCH($B11,EVALUASI!$C$79:$C$132,0)),"-") -> Baik | T11: =J11-ROW()/1000000 -> 0.88318772
A12: 3 | B12: =PEMAGANG!C5 -> CLARA OKTAVIA FIRDAUS | C12: =PEMAGANG!D5 -> AHMAD JALALUDDIN BASYAR | D12: =PEMAGANG!F5 -> PGS SM OF DIGITAL BUSSINES | E12: =SUMIFS(DETAIL!$M$2:$M$137,DETAIL!$B$2:$B$137,$B12) -> 33 | F12: =SUMIFS(DETAIL!$R$2:$R$137,DETAIL!$B$2:$B$137,$B12) -> 49 | G12: =SUMIFS(DETAIL!$T$2:$T$137,DETAIL!$B$2:$B$137,$B12) -> 1869 | H12: =IFERROR(F12/E12,0) -> 1.4848485 | I12: =IFERROR(G12/E12,0) -> 56.636364 | J12: =IFERROR($C$2*H12/$C$5+$C$3*I12/$C$6,0) -> 0.70710565 | K12: =MIN(1,IFERROR(J12/$C$4,0)) -> 0.70710565 | L12: =IF(E12=0,"-",IF(F12=0,"Tidak ada laporan",IF(J12>=$E$2,"Sangat Tinggi",IF(J12>=$E$3,"Tinggi",IF(J12>=$E$4,"Sedang","Rendah"))))) -> Sedang | M12: =RANK(T12,$T$10:$T$43) -> 19 | N12: =IFERROR($C$2*(SUMIFS(DETAIL!$R$2:$R$137,DETAIL!$B$2:$B$137,$B12,DETAIL!$F$2:$F$137,MONTH(DATE(YEAR(SUMMARY!$C$6),MONTH(SUMMARY!$C$6)+0,1)))/SUMIFS(DETAIL!$M$2:$M$137,DETAIL!$B$2:$B$137,$B12,DETAIL!$F$2:$F$137,MONTH(DATE(YEAR(SUMMARY!$C$6),MONTH(SUMMARY!$C$6)+0,1))))/$C$5+$C$3*(SUMIFS(DETAIL!$T$2:$T$137,DETAIL!$B$2:$B$137,$B12,DETAIL!$F$2:$F$137,MONTH(DATE(YEAR(SUMMARY!$C$6),MONTH(SUMMARY!$C$6)+0,1)))/SUMIFS(DETAIL!$M$2:$M$137,DETAIL!$B$2:$B$137,$B12,DETAIL!$F$2:$F$137,MONTH(DATE(YEAR(SUMMARY!$C$6),MONTH(SUMMARY!$C$6)+0,1))))/$C$6,"-") -> - | O12: =IFERROR($C$2*(SUMIFS(DETAIL!$R$2:$R$137,DETAIL!$B$2:$B$137,$B12,DETAIL!$F$2:$F$137,MONTH(DATE(YEAR(SUMMARY!$C$6),MONTH(SUMMARY!$C$6)+1,1)))/SUMIFS(DETAIL!$M$2:$M$137,DETAIL!$B$2:$B$137,$B12,DETAIL!$F$2:$F$137,MONTH(DATE(YEAR(SUMMARY!$C$6),MONTH(SUMMARY!$C$6)+1,1))))/$C$5+$C$3*(SUMIFS(DETAIL!$T$2:$T$137,DETAIL!$B$2:$B$137,$B12,DETAIL!$F$2:$F$137,MONTH(DATE(YEAR(SUMMARY!$C$6),MONTH(SUMMARY!$C$6)+1,1)))/SUMIFS(DETAIL!$M$2:$M$137,DETAIL!$B$2:$B$137,$B12,DETAIL!$F$2:$F$137,MONTH(DATE(YEAR(SUMMARY!$C$6),MONTH(SUMMARY!$C$6)+1,1))))/$C$6,"-") -> - | P12: =IFERROR($C$2*(SUMIFS(DETAIL!$R$2:$R$137,DETAIL!$B$2:$B$137,$B12,DETAIL!$F$2:$F$137,MONTH(DATE(YEAR(SUMMARY!$C$6),MONTH(SUMMARY!$C$6)+2,1)))/SUMIFS(DETAIL!$M$2:$M$137,DETAIL!$B$2:$B$137,$B12,DETAIL!$F$2:$F$137,MONTH(DATE(YEAR(SUMMARY!$C$6),MONTH(SUMMARY!$C$6)+2,1))))/$C$5+$C$3*(SUMIFS(DETAIL!$T$2:$T$137,DETAIL!$B$2:$B$137,$B12,DETAIL!$F$2:$F$137,MONTH(DATE(YEAR(SUMMARY!$C$6),MONTH(SUMMARY!$C$6)+2,1)))/SUMIFS(DETAIL!$M$2:$M$137,DETAIL!$B$2:$B$137,$B12,DETAIL!$F$2:$F$137,MONTH(DATE(YEAR(SUMMARY!$C$6),MONTH(SUMMARY!$C$6)+2,1))))/$C$6,"-") -> 0.57911303 | Q12: =IFERROR($C$2*(SUMIFS(DETAIL!$R$2:$R$137,DETAIL!$B$2:$B$137,$B12,DETAIL!$F$2:$F$137,MONTH(DATE(YEAR(SUMMARY!$C$6),MONTH(SUMMARY!$C$6)+3,1)))/SUMIFS(DETAIL!$M$2:$M$137,DETAIL!$B$2:$B$137,$B12,DETAIL!$F$2:$F$137,MONTH(DATE(YEAR(SUMMARY!$C$6),MONTH(SUMMARY!$C$6)+3,1))))/$C$5+$C$3*(SUMIFS(DETAIL!$T$2:$T$137,DETAIL!$B$2:$B$137,$B12,DETAIL!$F$2:$F$137,MONTH(DATE(YEAR(SUMMARY!$C$6),MONTH(SUMMARY!$C$6)+3,1)))/SUMIFS(DETAIL!$M$2:$M$137,DETAIL!$B$2:$B$137,$B12,DETAIL!$F$2:$F$137,MONTH(DATE(YEAR(SUMMARY!$C$6),MONTH(SUMMARY!$C$6)+3,1))))/$C$6,"-") -> 0.79030085 | R12: =IFERROR(INDEX(EVALUASI!$W$79:$W$132,MATCH($B12,EVALUASI!$C$79:$C$132,0)),"-") -> 82.7 | S12: =IFERROR(INDEX(EVALUASI!$X$79:$X$132,MATCH($B12,EVALUASI!$C$79:$C$132,0)),"-") -> Baik | T12: =J12-ROW()/1000000 -> 0.70709365
A13: 4 | B13: =PEMAGANG!C6 -> NELLA DIFA SALSABILAH | C13: =PEMAGANG!D6 -> AHMAD JALALUDDIN BASYAR | D13: =PEMAGANG!F6 -> PGS SM OF DIGITAL BUSSINES | E13: =SUMIFS(DETAIL!$M$2:$M$137,DETAIL!$B$2:$B$137,$B13) -> 84 | F13: =SUMIFS(DETAIL!$R$2:$R$137,DETAIL!$B$2:$B$137,$B13) -> 168 | G13: =SUMIFS(DETAIL!$T$2:$T$137,DETAIL!$B$2:$B$137,$B13) -> 1426 | H13: =IFERROR(F13/E13,0) -> 2 | I13: =IFERROR(G13/E13,0) -> 16.97619 | J13: =IFERROR($C$2*H13/$C$5+$C$3*I13/$C$6,0) -> 0.64718601 | K13: =MIN(1,IFERROR(J13/$C$4,0)) -> 0.64718601 | L13: =IF(E13=0,"-",IF(F13=0,"Tidak ada laporan",IF(J13>=$E$2,"Sangat Tinggi",IF(J13>=$E$3,"Tinggi",IF(J13>=$E$4,"Sedang","Rendah"))))) -> Rendah | M13: =RANK(T13,$T$10:$T$43) -> 21 | N13: =IFERROR($C$2*(SUMIFS(DETAIL!$R$2:$R$137,DETAIL!$B$2:$B$137,$B13,DETAIL!$F$2:$F$137,MONTH(DATE(YEAR(SUMMARY!$C$6),MONTH(SUMMARY!$C$6)+0,1)))/SUMIFS(DETAIL!$M$2:$M$137,DETAIL!$B$2:$B$137,$B13,DETAIL!$F$2:$F$137,MONTH(DATE(YEAR(SUMMARY!$C$6),MONTH(SUMMARY!$C$6)+0,1))))/$C$5+$C$3*(SUMIFS(DETAIL!$T$2:$T$137,DETAIL!$B$2:$B$137,$B13,DETAIL!$F$2:$F$137,MONTH(DATE(YEAR(SUMMARY!$C$6),MONTH(SUMMARY!$C$6)+0,1)))/SUMIFS(DETAIL!$M$2:$M$137,DETAIL!$B$2:$B$137,$B13,DETAIL!$F$2:$F$137,MONTH(DATE(YEAR(SUMMARY!$C$6),MONTH(SUMMARY!$C$6)+0,1))))/$C$6,"-") -> 0.62250529 | O13: =IFERROR($C$2*(SUMIFS(DETAIL!$R$2:$R$137,DETAIL!$B$2:$B$137,$B13,DETAIL!$F$2:$F$137,MONTH(DATE(YEAR(SUMMARY!$C$6),MONTH(SUMMARY!$C$6)+1,1)))/SUMIFS(DETAIL!$M$2:$M$137,DETAIL!$B$2:$B$137,$B13,DETAIL!$F$2:$F$137,MONTH(DATE(YEAR(SUMMARY!$C$6),MONTH(SUMMARY!$C$6)+1,1))))/$C$5+$C$3*(SUMIFS(DETAIL!$T$2:$T$137,DETAIL!$B$2:$B$137,$B13,DETAIL!$F$2:$F$137,MONTH(DATE(YEAR(SUMMARY!$C$6),MONTH(SUMMARY!$C$6)+1,1)))/SUMIFS(DETAIL!$M$2:$M$137,DETAIL!$B$2:$B$137,$B13,DETAIL!$F$2:$F$137,MONTH(DATE(YEAR(SUMMARY!$C$6),MONTH(SUMMARY!$C$6)+1,1))))/$C$6,"-") -> 0.68051237 | P13: =IFERROR($C$2*(SUMIFS(DETAIL!$R$2:$R$137,DETAIL!$B$2:$B$137,$B13,DETAIL!$F$2:$F$137,MONTH(DATE(YEAR(SUMMARY!$C$6),MONTH(SUMMARY!$C$6)+2,1)))/SUMIFS(DETAIL!$M$2:$M$137,DETAIL!$B$2:$B$137,$B13,DETAIL!$F$2:$F$137,MONTH(DATE(YEAR(SUMMARY!$C$6),MONTH(SUMMARY!$C$6)+2,1))))/$C$5+$C$3*(SUMIFS(DETAIL!$T$2:$T$137,DETAIL!$B$2:$B$137,$B13,DETAIL!$F$2:$F$137,MONTH(DATE(YEAR(SUMMARY!$C$6),MONTH(SUMMARY!$C$6)+2,1)))/SUMIFS(DETAIL!$M$2:$M$137,DETAIL!$B$2:$B$137,$B13,DETAIL!$F$2:$F$137,MONTH(DATE(YEAR(SUMMARY!$C$6),MONTH(SUMMARY!$C$6)+2,1))))/$C$6,"-") -> 0.64459981 | Q13: =IFERROR($C$2*(SUMIFS(DETAIL!$R$2:$R$137,DETAIL!$B$2:$B$137,$B13,DETAIL!$F$2:$F$137,MONTH(DATE(YEAR(SUMMARY!$C$6),MONTH(SUMMARY!$C$6)+3,1)))/SUMIFS(DETAIL!$M$2:$M$137,DETAIL!$B$2:$B$137,$B13,DETAIL!$F$2:$F$137,MONTH(DATE(YEAR(SUMMARY!$C$6),MONTH(SUMMARY!$C$6)+3,1))))/$C$5+$C$3*(SUMIFS(DETAIL!$T$2:$T$137,DETAIL!$B$2:$B$137,$B13,DETAIL!$F$2:$F$137,MONTH(DATE(YEAR(SUMMARY!$C$6),MONTH(SUMMARY!$C$6)+3,1)))/SUMIFS(DETAIL!$M$2:$M$137,DETAIL!$B$2:$B$137,$B13,DETAIL!$F$2:$F$137,MONTH(DATE(YEAR(SUMMARY!$C$6),MONTH(SUMMARY!$C$6)+3,1))))/$C$6,"-") -> 0.63701536 | R13: =IFERROR(INDEX(EVALUASI!$W$79:$W$132,MATCH($B13,EVALUASI!$C$79:$C$132,0)),"-") -> 88.2 | S13: =IFERROR(INDEX(EVALUASI!$X$79:$X$132,MATCH($B13,EVALUASI!$C$79:$C$132,0)),"-") -> Baik | T13: =J13-ROW()/1000000 -> 0.64717301
A14: 5 | B14: =PEMAGANG!C7 -> SYAKIRAH TSALTSA FITRIAH | C14: =PEMAGANG!D7 -> AHMAD JALALUDDIN BASYAR | D14: =PEMAGANG!F7 -> PGS SM OF DIGITAL BUSSINES | E14: =SUMIFS(DETAIL!$M$2:$M$137,DETAIL!$B$2:$B$137,$B14) -> 36 | F14: =SUMIFS(DETAIL!$R$2:$R$137,DETAIL!$B$2:$B$137,$B14) -> 80 | G14: =SUMIFS(DETAIL!$T$2:$T$137,DETAIL!$B$2:$B$137,$B14) -> 10052 | H14: =IFERROR(F14/E14,0) -> 2.2222222 | I14: =IFERROR(G14/E14,0) -> 279.22222 | J14: =IFERROR($C$2*H14/$C$5+$C$3*I14/$C$6,0) -> 2.0590616 | K14: =MIN(1,IFERROR(J14/$C$4,0)) -> 1 | L14: =IF(E14=0,"-",IF(F14=0,"Tidak ada laporan",IF(J14>=$E$2,"Sangat Tinggi",IF(J14>=$E$3,"Tinggi",IF(J14>=$E$4,"Sedang","Rendah"))))) -> Sangat Tinggi | M14: =RANK(T14,$T$10:$T$43) -> 2 | N14: =IFERROR($C$2*(SUMIFS(DETAIL!$R$2:$R$137,DETAIL!$B$2:$B$137,$B14,DETAIL!$F$2:$F$137,MONTH(DATE(YEAR(SUMMARY!$C$6),MONTH(SUMMARY!$C$6)+0,1)))/SUMIFS(DETAIL!$M$2:$M$137,DETAIL!$B$2:$B$137,$B14,DETAIL!$F$2:$F$137,MONTH(DATE(YEAR(SUMMARY!$C$6),MONTH(SUMMARY!$C$6)+0,1))))/$C$5+$C$3*(SUMIFS(DETAIL!$T$2:$T$137,DETAIL!$B$2:$B$137,$B14,DETAIL!$F$2:$F$137,MONTH(DATE(YEAR(SUMMARY!$C$6),MONTH(SUMMARY!$C$6)+0,1)))/SUMIFS(DETAIL!$M$2:$M$137,DETAIL!$B$2:$B$137,$B14,DETAIL!$F$2:$F$137,MONTH(DATE(YEAR(SUMMARY!$C$6),MONTH(SUMMARY!$C$6)+0,1))))/$C$6,"-") -> - | O14: =IFERROR($C$2*(SUMIFS(DETAIL!$R$2:$R$137,DETAIL!$B$2:$B$137,$B14,DETAIL!$F$2:$F$137,MONTH(DATE(YEAR(SUMMARY!$C$6),MONTH(SUMMARY!$C$6)+1,1)))/SUMIFS(DETAIL!$M$2:$M$137,DETAIL!$B$2:$B$137,$B14,DETAIL!$F$2:$F$137,MONTH(DATE(YEAR(SUMMARY!$C$6),MONTH(SUMMARY!$C$6)+1,1))))/$C$5+$C$3*(SUMIFS(DETAIL!$T$2:$T$137,DETAIL!$B$2:$B$137,$B14,DETAIL!$F$2:$F$137,MONTH(DATE(YEAR(SUMMARY!$C$6),MONTH(SUMMARY!$C$6)+1,1)))/SUMIFS(DETAIL!$M$2:$M$137,DETAIL!$B$2:$B$137,$B14,DETAIL!$F$2:$F$137,MONTH(DATE(YEAR(SUMMARY!$C$6),MONTH(SUMMARY!$C$6)+1,1))))/$C$6,"-") -> - | P14: =IFERROR($C$2*(SUMIFS(DETAIL!$R$2:$R$137,DETAIL!$B$2:$B$137,$B14,DETAIL!$F$2:$F$137,MONTH(DATE(YEAR(SUMMARY!$C$6),MONTH(SUMMARY!$C$6)+2,1)))/SUMIFS(DETAIL!$M$2:$M$137,DETAIL!$B$2:$B$137,$B14,DETAIL!$F$2:$F$137,MONTH(DATE(YEAR(SUMMARY!$C$6),MONTH(SUMMARY!$C$6)+2,1))))/$C$5+$C$3*(SUMIFS(DETAIL!$T$2:$T$137,DETAIL!$B$2:$B$137,$B14,DETAIL!$F$2:$F$137,MONTH(DATE(YEAR(SUMMARY!$C$6),MONTH(SUMMARY!$C$6)+2,1)))/SUMIFS(DETAIL!$M$2:$M$137,DETAIL!$B$2:$B$137,$B14,DETAIL!$F$2:$F$137,MONTH(DATE(YEAR(SUMMARY!$C$6),MONTH(SUMMARY!$C$6)+2,1))))/$C$6,"-") -> 1.9624055 | Q14: =IFERROR($C$2*(SUMIFS(DETAIL!$R$2:$R$137,DETAIL!$B$2:$B$137,$B14,DETAIL!$F$2:$F$137,MONTH(DATE(YEAR(SUMMARY!$C$6),MONTH(SUMMARY!$C$6)+3,1)))/SUMIFS(DETAIL!$M$2:$M$137,DETAIL!$B$2:$B$137,$B14,DETAIL!$F$2:$F$137,MONTH(DATE(YEAR(SUMMARY!$C$6),MONTH(SUMMARY!$C$6)+3,1))))/$C$5+$C$3*(SUMIFS(DETAIL!$T$2:$T$137,DETAIL!$B$2:$B$137,$B14,DETAIL!$F$2:$F$137,MONTH(DATE(YEAR(SUMMARY!$C$6),MONTH(SUMMARY!$C$6)+3,1)))/SUMIFS(DETAIL!$M$2:$M$137,DETAIL!$B$2:$B$137,$B14,DETAIL!$F$2:$F$137,MONTH(DATE(YEAR(SUMMARY!$C$6),MONTH(SUMMARY!$C$6)+3,1))))/$C$6,"-") -> 2.12057 | R14: =IFERROR(INDEX(EVALUASI!$W$79:$W$132,MATCH($B14,EVALUASI!$C$79:$C$132,0)),"-") -> 97.8 | S14: =IFERROR(INDEX(EVALUASI!$X$79:$X$132,MATCH($B14,EVALUASI!$C$79:$C$132,0)),"-") -> Sangat Baik | T14: =J14-ROW()/1000000 -> 2.0590476
A15: 6 | B15: =PEMAGANG!C8 -> TIARA MARTHA ASNADHINATA | C15: =PEMAGANG!D8 -> AHMAD JALALUDDIN BASYAR | D15: =PEMAGANG!F8 -> PGS SM OF DIGITAL BUSSINES | E15: =SUMIFS(DETAIL!$M$2:$M$137,DETAIL!$B$2:$B$137,$B15) -> 78 | F15: =SUMIFS(DETAIL!$R$2:$R$137,DETAIL!$B$2:$B$137,$B15) -> 192 | G15: =SUMIFS(DETAIL!$T$2:$T$137,DETAIL!$B$2:$B$137,$B15) -> 11227 | H15: =IFERROR(F15/E15,0) -> 2.4615385 | I15: =IFERROR(G15/E15,0) -> 143.9359 | J15: =IFERROR($C$2*H15/$C$5+$C$3*I15/$C$6,0) -> 1.4297844 | K15: =MIN(1,IFERROR(J15/$C$4,0)) -> 1 | L15: =IF(E15=0,"-",IF(F15=0,"Tidak ada laporan",IF(J15>=$E$2,"Sangat Tinggi",IF(J15>=$E$3,"Tinggi",IF(J15>=$E$4,"Sedang","Rendah"))))) -> Tinggi | M15: =RANK(T15,$T$10:$T$43) -> 7 | N15: =IFERROR($C$2*(SUMIFS(DETAIL!$R$2:$R$137,DETAIL!$B$2:$B$137,$B15,DETAIL!$F$2:$F$137,MONTH(DATE(YEAR(SUMMARY!$C$6),MONTH(SUMMARY!$C$6)+0,1)))/SUMIFS(DETAIL!$M$2:$M$137,DETAIL!$B$2:$B$137,$B15,DETAIL!$F$2:$F$137,MONTH(DATE(YEAR(SUMMARY!$C$6),MONTH(SUMMARY!$C$6)+0,1))))/$C$5+$C$3*(SUMIFS(DETAIL!$T$2:$T$137,DETAIL!$B$2:$B$137,$B15,DETAIL!$F$2:$F$137,MONTH(DATE(YEAR(SUMMARY!$C$6),MONTH(SUMMARY!$C$6)+0,1)))/SUMIFS(DETAIL!$M$2:$M$137,DETAIL!$B$2:$B$137,$B15,DETAIL!$F$2:$F$137,MONTH(DATE(YEAR(SUMMARY!$C$6),MONTH(SUMMARY!$C$6)+0,1))))/$C$6,"-") -> 1.2367346 | O15: =IFERROR($C$2*(SUMIFS(DETAIL!$R$2:$R$137,DETAIL!$B$2:$B$137,$B15,DETAIL!$F$2:$F$137,MONTH(DATE(YEAR(SUMMARY!$C$6),MONTH(SUMMARY!$C$6)+1,1)))/SUMIFS(DETAIL!$M$2:$M$137,DETAIL!$B$2:$B$137,$B15,DETAIL!$F$2:$F$137,MONTH(DATE(YEAR(SUMMARY!$C$6),MONTH(SUMMARY!$C$6)+1,1))))/$C$5+$C$3*(SUMIFS(DETAIL!$T$2:$T$137,DETAIL!$B$2:$B$137,$B15,DETAIL!$F$2:$F$137,MONTH(DATE(YEAR(SUMMARY!$C$6),MONTH(SUMMARY!$C$6)+1,1)))/SUMIFS(DETAIL!$M$2:$M$137,DETAIL!$B$2:$B$137,$B15,DETAIL!$F$2:$F$137,MONTH(DATE(YEAR(SUMMARY!$C$6),MONTH(SUMMARY!$C$6)+1,1))))/$C$6,"-") -> 1.8204367 | P15: =IFERROR($C$2*(SUMIFS(DETAIL!$R$2:$R$137,DETAIL!$B$2:$B$137,$B15,DETAIL!$F$2:$F$137,MONTH(DATE(YEAR(SUMMARY!$C$6),MONTH(SUMMARY!$C$6)+2,1)))/SUMIFS(DETAIL!$M$2:$M$137,DETAIL!$B$2:$B$137,$B15,DETAIL!$F$2:$F$137,MONTH(DATE(YEAR(SUMMARY!$C$6),MONTH(SUMMARY!$C$6)+2,1))))/$C$5+$C$3*(SUMIFS(DETAIL!$T$2:$T$137,DETAIL!$B$2:$B$137,$B15,DETAIL!$F$2:$F$137,MONTH(DATE(YEAR(SUMMARY!$C$6),MONTH(SUMMARY!$C$6)+2,1)))/SUMIFS(DETAIL!$M$2:$M$137,DETAIL!$B$2:$B$137,$B15,DETAIL!$F$2:$F$137,MONTH(DATE(YEAR(SUMMARY!$C$6),MONTH(SUMMARY!$C$6)+2,1))))/$C$6,"-") -> 1.5305949 | Q15: =IFERROR($C$2*(SUMIFS(DETAIL!$R$2:$R$137,DETAIL!$B$2:$B$137,$B15,DETAIL!$F$2:$F$137,MONTH(DATE(YEAR(SUMMARY!$C$6),MONTH(SUMMARY!$C$6)+3,1)))/SUMIFS(DETAIL!$M$2:$M$137,DETAIL!$B$2:$B$137,$B15,DETAIL!$F$2:$F$137,MONTH(DATE(YEAR(SUMMARY!$C$6),MONTH(SUMMARY!$C$6)+3,1))))/$C$5+$C$3*(SUMIFS(DETAIL!$T$2:$T$137,DETAIL!$B$2:$B$137,$B15,DETAIL!$F$2:$F$137,MONTH(DATE(YEAR(SUMMARY!$C$6),MONTH(SUMMARY!$C$6)+3,1)))/SUMIFS(DETAIL!$M$2:$M$137,DETAIL!$B$2:$B$137,$B15,DETAIL!$F$2:$F$137,MONTH(DATE(YEAR(SUMMARY!$C$6),MONTH(SUMMARY!$C$6)+3,1))))/$C$6,"-") -> 1.2031784 | R15: =IFERROR(INDEX(EVALUASI!$W$79:$W$132,MATCH($B15,EVALUASI!$C$79:$C$132,0)),"-") -> 96.2 | S15: =IFERROR(INDEX(EVALUASI!$X$79:$X$132,MATCH($B15,EVALUASI!$C$79:$C$132,0)),"-") -> Sangat Baik | T15: =J15-ROW()/1000000 -> 1.4297694
A16: 7 | B16: =PEMAGANG!C9 -> WIDIYA DESY MAWAR SARI | C16: =PEMAGANG!D9 -> AHMAD JALALUDDIN BASYAR | D16: =PEMAGANG!F9 -> PGS SM OF DIGITAL BUSSINES | E16: =SUMIFS(DETAIL!$M$2:$M$137,DETAIL!$B$2:$B$137,$B16) -> 74 | F16: =SUMIFS(DETAIL!$R$2:$R$137,DETAIL!$B$2:$B$137,$B16) -> 62 | G16: =SUMIFS(DETAIL!$T$2:$T$137,DETAIL!$B$2:$B$137,$B16) -> 650 | H16: =IFERROR(F16/E16,0) -> 0.83783784 | I16: =IFERROR(G16/E16,0) -> 8.7837838 | J16: =IFERROR($C$2*H16/$C$5+$C$3*I16/$C$6,0) -> 0.27972427 | K16: =MIN(1,IFERROR(J16/$C$4,0)) -> 0.27972427 | L16: =IF(E16=0,"-",IF(F16=0,"Tidak ada laporan",IF(J16>=$E$2,"Sangat Tinggi",IF(J16>=$E$3,"Tinggi",IF(J16>=$E$4,"Sedang","Rendah"))))) -> Rendah | M16: =RANK(T16,$T$10:$T$43) -> 33 | N16: =IFERROR($C$2*(SUMIFS(DETAIL!$R$2:$R$137,DETAIL!$B$2:$B$137,$B16,DETAIL!$F$2:$F$137,MONTH(DATE(YEAR(SUMMARY!$C$6),MONTH(SUMMARY!$C$6)+0,1)))/SUMIFS(DETAIL!$M$2:$M$137,DETAIL!$B$2:$B$137,$B16,DETAIL!$F$2:$F$137,MONTH(DATE(YEAR(SUMMARY!$C$6),MONTH(SUMMARY!$C$6)+0,1))))/$C$5+$C$3*(SUMIFS(DETAIL!$T$2:$T$137,DETAIL!$B$2:$B$137,$B16,DETAIL!$F$2:$F$137,MONTH(DATE(YEAR(SUMMARY!$C$6),MONTH(SUMMARY!$C$6)+0,1)))/SUMIFS(DETAIL!$M$2:$M$137,DETAIL!$B$2:$B$137,$B16,DETAIL!$F$2:$F$137,MONTH(DATE(YEAR(SUMMARY!$C$6),MONTH(SUMMARY!$C$6)+0,1))))/$C$6,"-") -> 0.23586129 | O16: =IFERROR($C$2*(SUMIFS(DETAIL!$R$2:$R$137,DETAIL!$B$2:$B$137,$B16,DETAIL!$F$2:$F$137,MONTH(DATE(YEAR(SUMMARY!$C$6),MONTH(SUMMARY!$C$6)+1,1)))/SUMIFS(DETAIL!$M$2:$M$137,DETAIL!$B$2:$B$137,$B16,DETAIL!$F$2:$F$137,MONTH(DATE(YEAR(SUMMARY!$C$6),MONTH(SUMMARY!$C$6)+1,1))))/$C$5+$C$3*(SUMIFS(DETAIL!$T$2:$T$137,DETAIL!$B$2:$B$137,$B16,DETAIL!$F$2:$F$137,MONTH(DATE(YEAR(SUMMARY!$C$6),MONTH(SUMMARY!$C$6)+1,1)))/SUMIFS(DETAIL!$M$2:$M$137,DETAIL!$B$2:$B$137,$B16,DETAIL!$F$2:$F$137,MONTH(DATE(YEAR(SUMMARY!$C$6),MONTH(SUMMARY!$C$6)+1,1))))/$C$6,"-") -> 0.26621603 | P16: =IFERROR($C$2*(SUMIFS(DETAIL!$R$2:$R$137,DETAIL!$B$2:$B$137,$B16,DETAIL!$F$2:$F$137,MONTH(DATE(YEAR(SUMMARY!$C$6),MONTH(SUMMARY!$C$6)+2,1)))/SUMIFS(DETAIL!$M$2:$M$137,DETAIL!$B$2:$B$137,$B16,DETAIL!$F$2:$F$137,MONTH(DATE(YEAR(SUMMARY!$C$6),MONTH(SUMMARY!$C$6)+2,1))))/$C$5+$C$3*(SUMIFS(DETAIL!$T$2:$T$137,DETAIL!$B$2:$B$137,$B16,DETAIL!$F$2:$F$137,MONTH(DATE(YEAR(SUMMARY!$C$6),MONTH(SUMMARY!$C$6)+2,1)))/SUMIFS(DETAIL!$M$2:$M$137,DETAIL!$B$2:$B$137,$B16,DETAIL!$F$2:$F$137,MONTH(DATE(YEAR(SUMMARY!$C$6),MONTH(SUMMARY!$C$6)+2,1))))/$C$6,"-") -> 0.27715581 | Q16: =IFERROR($C$2*(SUMIFS(DETAIL!$R$2:$R$137,DETAIL!$B$2:$B$137,$B16,DETAIL!$F$2:$F$137,MONTH(DATE(YEAR(SUMMARY!$C$6),MONTH(SUMMARY!$C$6)+3,1)))/SUMIFS(DETAIL!$M$2:$M$137,DETAIL!$B$2:$B$137,$B16,DETAIL!$F$2:$F$137,MONTH(DATE(YEAR(SUMMARY!$C$6),MONTH(SUMMARY!$C$6)+3,1))))/$C$5+$C$3*(SUMIFS(DETAIL!$T$2:$T$137,DETAIL!$B$2:$B$137,$B16,DETAIL!$F$2:$F$137,MONTH(DATE(YEAR(SUMMARY!$C$6),MONTH(SUMMARY!$C$6)+3,1)))/SUMIFS(DETAIL!$M$2:$M$137,DETAIL!$B$2:$B$137,$B16,DETAIL!$F$2:$F$137,MONTH(DATE(YEAR(SUMMARY!$C$6),MONTH(SUMMARY!$C$6)+3,1))))/$C$6,"-") -> 0.33008751 | R16: =IFERROR(INDEX(EVALUASI!$W$79:$W$132,MATCH($B16,EVALUASI!$C$79:$C$132,0)),"-") -> 65.4 | S16: =IFERROR(INDEX(EVALUASI!$X$79:$X$132,MATCH($B16,EVALUASI!$C$79:$C$132,0)),"-") -> Perlu Pembinaan | T16: =J16-ROW()/1000000 -> 0.27970827
A17: 8 | B17: =PEMAGANG!C10 -> NURIKA AMELIA ROSYIDAH | C17: =PEMAGANG!D10 -> AKHMAT ABIDIN | D17: =PEMAGANG!F10 -> PJ GM OF MARKETING (SID) | E17: =SUMIFS(DETAIL!$M$2:$M$137,DETAIL!$B$2:$B$137,$B17) -> 54 | F17: =SUMIFS(DETAIL!$R$2:$R$137,DETAIL!$B$2:$B$137,$B17) -> 91 | G17: =SUMIFS(DETAIL!$T$2:$T$137,DETAIL!$B$2:$B$137,$B17) -> 6650 | H17: =IFERROR(F17/E17,0) -> 1.6851852 | I17: =IFERROR(G17/E17,0) -> 123.14815 | J17: =IFERROR($C$2*H17/$C$5+$C$3*I17/$C$6,0) -> 1.1054907 | K17: =MIN(1,IFERROR(J17/$C$4,0)) -> 1 | L17: =IF(E17=0,"-",IF(F17=0,"Tidak ada laporan",IF(J17>=$E$2,"Sangat Tinggi",IF(J17>=$E$3,"Tinggi",IF(J17>=$E$4,"Sedang","Rendah"))))) -> Tinggi | M17: =RANK(T17,$T$10:$T$43) -> 11 | N17: =IFERROR($C$2*(SUMIFS(DETAIL!$R$2:$R$137,DETAIL!$B$2:$B$137,$B17,DETAIL!$F$2:$F$137,MONTH(DATE(YEAR(SUMMARY!$C$6),MONTH(SUMMARY!$C$6)+0,1)))/SUMIFS(DETAIL!$M$2:$M$137,DETAIL!$B$2:$B$137,$B17,DETAIL!$F$2:$F$137,MONTH(DATE(YEAR(SUMMARY!$C$6),MONTH(SUMMARY!$C$6)+0,1))))/$C$5+$C$3*(SUMIFS(DETAIL!$T$2:$T$137,DETAIL!$B$2:$B$137,$B17,DETAIL!$F$2:$F$137,MONTH(DATE(YEAR(SUMMARY!$C$6),MONTH(SUMMARY!$C$6)+0,1)))/SUMIFS(DETAIL!$M$2:$M$137,DETAIL!$B$2:$B$137,$B17,DETAIL!$F$2:$F$137,MONTH(DATE(YEAR(SUMMARY!$C$6),MONTH(SUMMARY!$C$6)+0,1))))/$C$6,"-") -> 0.87067699 | O17: =IFERROR($C$2*(SUMIFS(DETAIL!$R$2:$R$137,DETAIL!$B$2:$B$137,$B17,DETAIL!$F$2:$F$137,MONTH(DATE(YEAR(SUMMARY!$C$6),MONTH(SUMMARY!$C$6)+1,1)))/SUMIFS(DETAIL!$M$2:$M$137,DETAIL!$B$2:$B$137,$B17,DETAIL!$F$2:$F$137,MONTH(DATE(YEAR(SUMMARY!$C$6),MONTH(SUMMARY!$C$6)+1,1))))/$C$5+$C$3*(SUMIFS(DETAIL!$T$2:$T$137,DETAIL!$B$2:$B$137,$B17,DETAIL!$F$2:$F$137,MONTH(DATE(YEAR(SUMMARY!$C$6),MONTH(SUMMARY!$C$6)+1,1)))/SUMIFS(DETAIL!$M$2:$M$137,DETAIL!$B$2:$B$137,$B17,DETAIL!$F$2:$F$137,MONTH(DATE(YEAR(SUMMARY!$C$6),MONTH(SUMMARY!$C$6)+1,1))))/$C$6,"-") -> 1.3976698 | P17: =IFERROR($C$2*(SUMIFS(DETAIL!$R$2:$R$137,DETAIL!$B$2:$B$137,$B17,DETAIL!$F$2:$F$137,MONTH(DATE(YEAR(SUMMARY!$C$6),MONTH(SUMMARY!$C$6)+2,1)))/SUMIFS(DETAIL!$M$2:$M$137,DETAIL!$B$2:$B$137,$B17,DETAIL!$F$2:$F$137,MONTH(DATE(YEAR(SUMMARY!$C$6),MONTH(SUMMARY!$C$6)+2,1))))/$C$5+$C$3*(SUMIFS(DETAIL!$T$2:$T$137,DETAIL!$B$2:$B$137,$B17,DETAIL!$F$2:$F$137,MONTH(DATE(YEAR(SUMMARY!$C$6),MONTH(SUMMARY!$C$6)+2,1)))/SUMIFS(DETAIL!$M$2:$M$137,DETAIL!$B$2:$B$137,$B17,DETAIL!$F$2:$F$137,MONTH(DATE(YEAR(SUMMARY!$C$6),MONTH(SUMMARY!$C$6)+2,1))))/$C$6,"-") -> 0.93855802 | Q17: =IFERROR($C$2*(SUMIFS(DETAIL!$R$2:$R$137,DETAIL!$B$2:$B$137,$B17,DETAIL!$F$2:$F$137,MONTH(DATE(YEAR(SUMMARY!$C$6),MONTH(SUMMARY!$C$6)+3,1)))/SUMIFS(DETAIL!$M$2:$M$137,DETAIL!$B$2:$B$137,$B17,DETAIL!$F$2:$F$137,MONTH(DATE(YEAR(SUMMARY!$C$6),MONTH(SUMMARY!$C$6)+3,1))))/$C$5+$C$3*(SUMIFS(DETAIL!$T$2:$T$137,DETAIL!$B$2:$B$137,$B17,DETAIL!$F$2:$F$137,MONTH(DATE(YEAR(SUMMARY!$C$6),MONTH(SUMMARY!$C$6)+3,1)))/SUMIFS(DETAIL!$M$2:$M$137,DETAIL!$B$2:$B$137,$B17,DETAIL!$F$2:$F$137,MONTH(DATE(YEAR(SUMMARY!$C$6),MONTH(SUMMARY!$C$6)+3,1))))/$C$6,"-") -> - | R17: =IFERROR(INDEX(EVALUASI!$W$79:$W$132,MATCH($B17,EVALUASI!$C$79:$C$132,0)),"-") -> 95.5 | S17: =IFERROR(INDEX(EVALUASI!$X$79:$X$132,MATCH($B17,EVALUASI!$C$79:$C$132,0)),"-") -> Sangat Baik | T17: =J17-ROW()/1000000 -> 1.1054737
A18: 9 | B18: =PEMAGANG!C11 -> JANU PRASTYO | C18: =PEMAGANG!D11 -> ARIFANO KUSUMA BAYU | D18: =PEMAGANG!F11 -> PGS SM OF DIGITAL BUSSINES | E18: =SUMIFS(DETAIL!$M$2:$M$137,DETAIL!$B$2:$B$137,$B18) -> 77 | F18: =SUMIFS(DETAIL!$R$2:$R$137,DETAIL!$B$2:$B$137,$B18) -> 207 | G18: =SUMIFS(DETAIL!$T$2:$T$137,DETAIL!$B$2:$B$137,$B18) -> 11664 | H18: =IFERROR(F18/E18,0) -> 2.6883117 | I18: =IFERROR(G18/E18,0) -> 151.48052 | J18: =IFERROR($C$2*H18/$C$5+$C$3*I18/$C$6,0) -> 1.5320892 | K18: =MIN(1,IFERROR(J18/$C$4,0)) -> 1 | L18: =IF(E18=0,"-",IF(F18=0,"Tidak ada laporan",IF(J18>=$E$2,"Sangat Tinggi",IF(J18>=$E$3,"Tinggi",IF(J18>=$E$4,"Sedang","Rendah"))))) -> Sangat Tinggi | M18: =RANK(T18,$T$10:$T$43) -> 5 | N18: =IFERROR($C$2*(SUMIFS(DETAIL!$R$2:$R$137,DETAIL!$B$2:$B$137,$B18,DETAIL!$F$2:$F$137,MONTH(DATE(YEAR(SUMMARY!$C$6),MONTH(SUMMARY!$C$6)+0,1)))/SUMIFS(DETAIL!$M$2:$M$137,DETAIL!$B$2:$B$137,$B18,DETAIL!$F$2:$F$137,MONTH(DATE(YEAR(SUMMARY!$C$6),MONTH(SUMMARY!$C$6)+0,1))))/$C$5+$C$3*(SUMIFS(DETAIL!$T$2:$T$137,DETAIL!$B$2:$B$137,$B18,DETAIL!$F$2:$F$137,MONTH(DATE(YEAR(SUMMARY!$C$6),MONTH(SUMMARY!$C$6)+0,1)))/SUMIFS(DETAIL!$M$2:$M$137,DETAIL!$B$2:$B$137,$B18,DETAIL!$F$2:$F$137,MONTH(DATE(YEAR(SUMMARY!$C$6),MONTH(SUMMARY!$C$6)+0,1))))/$C$6,"-") -> 0.90029685 | O18: =IFERROR($C$2*(SUMIFS(DETAIL!$R$2:$R$137,DETAIL!$B$2:$B$137,$B18,DETAIL!$F$2:$F$137,MONTH(DATE(YEAR(SUMMARY!$C$6),MONTH(SUMMARY!$C$6)+1,1)))/SUMIFS(DETAIL!$M$2:$M$137,DETAIL!$B$2:$B$137,$B18,DETAIL!$F$2:$F$137,MONTH(DATE(YEAR(SUMMARY!$C$6),MONTH(SUMMARY!$C$6)+1,1))))/$C$5+$C$3*(SUMIFS(DETAIL!$T$2:$T$137,DETAIL!$B$2:$B$137,$B18,DETAIL!$F$2:$F$137,MONTH(DATE(YEAR(SUMMARY!$C$6),MONTH(SUMMARY!$C$6)+1,1)))/SUMIFS(DETAIL!$M$2:$M$137,DETAIL!$B$2:$B$137,$B18,DETAIL!$F$2:$F$137,MONTH(DATE(YEAR(SUMMARY!$C$6),MONTH(SUMMARY!$C$6)+1,1))))/$C$6,"-") -> 1.5975468 | P18: =IFERROR($C$2*(SUMIFS(DETAIL!$R$2:$R$137,DETAIL!$B$2:$B$137,$B18,DETAIL!$F$2:$F$137,MONTH(DATE(YEAR(SUMMARY!$C$6),MONTH(SUMMARY!$C$6)+2,1)))/SUMIFS(DETAIL!$M$2:$M$137,DETAIL!$B$2:$B$137,$B18,DETAIL!$F$2:$F$137,MONTH(DATE(YEAR(SUMMARY!$C$6),MONTH(SUMMARY!$C$6)+2,1))))/$C$5+$C$3*(SUMIFS(DETAIL!$T$2:$T$137,DETAIL!$B$2:$B$137,$B18,DETAIL!$F$2:$F$137,MONTH(DATE(YEAR(SUMMARY!$C$6),MONTH(SUMMARY!$C$6)+2,1)))/SUMIFS(DETAIL!$M$2:$M$137,DETAIL!$B$2:$B$137,$B18,DETAIL!$F$2:$F$137,MONTH(DATE(YEAR(SUMMARY!$C$6),MONTH(SUMMARY!$C$6)+2,1))))/$C$6,"-") -> 2.0897843 | Q18: =IFERROR($C$2*(SUMIFS(DETAIL!$R$2:$R$137,DETAIL!$B$2:$B$137,$B18,DETAIL!$F$2:$F$137,MONTH(DATE(YEAR(SUMMARY!$C$6),MONTH(SUMMARY!$C$6)+3,1)))/SUMIFS(DETAIL!$M$2:$M$137,DETAIL!$B$2:$B$137,$B18,DETAIL!$F$2:$F$137,MONTH(DATE(YEAR(SUMMARY!$C$6),MONTH(SUMMARY!$C$6)+3,1))))/$C$5+$C$3*(SUMIFS(DETAIL!$T$2:$T$137,DETAIL!$B$2:$B$137,$B18,DETAIL!$F$2:$F$137,MONTH(DATE(YEAR(SUMMARY!$C$6),MONTH(SUMMARY!$C$6)+3,1)))/SUMIFS(DETAIL!$M$2:$M$137,DETAIL!$B$2:$B$137,$B18,DETAIL!$F$2:$F$137,MONTH(DATE(YEAR(SUMMARY!$C$6),MONTH(SUMMARY!$C$6)+3,1))))/$C$6,"-") -> 1.5996655 | R18: =IFERROR(INDEX(EVALUASI!$W$79:$W$132,MATCH($B18,EVALUASI!$C$79:$C$132,0)),"-") -> 90.9 | S18: =IFERROR(INDEX(EVALUASI!$X$79:$X$132,MATCH($B18,EVALUASI!$C$79:$C$132,0)),"-") -> Sangat Baik | T18: =J18-ROW()/1000000 -> 1.5320712
A19: 10 | B19: =PEMAGANG!C12 -> DINDA RAHADATUL AISY | C19: =PEMAGANG!D12 -> DIAN RIZKA SARI | D19: =PEMAGANG!F12 -> PGS TREASURY (SID) OFFICER | E19: =SUMIFS(DETAIL!$M$2:$M$137,DETAIL!$B$2:$B$137,$B19) -> 42 | F19: =SUMIFS(DETAIL!$R$2:$R$137,DETAIL!$B$2:$B$137,$B19) -> 43 | G19: =SUMIFS(DETAIL!$T$2:$T$137,DETAIL!$B$2:$B$137,$B19) -> 1939 | H19: =IFERROR(F19/E19,0) -> 1.0238095 | I19: =IFERROR(G19/E19,0) -> 46.166667 | J19: =IFERROR($C$2*H19/$C$5+$C$3*I19/$C$6,0) -> 0.52417378 | K19: =MIN(1,IFERROR(J19/$C$4,0)) -> 0.52417378 | L19: =IF(E19=0,"-",IF(F19=0,"Tidak ada laporan",IF(J19>=$E$2,"Sangat Tinggi",IF(J19>=$E$3,"Tinggi",IF(J19>=$E$4,"Sedang","Rendah"))))) -> Rendah | M19: =RANK(T19,$T$10:$T$43) -> 26 | N19: =IFERROR($C$2*(SUMIFS(DETAIL!$R$2:$R$137,DETAIL!$B$2:$B$137,$B19,DETAIL!$F$2:$F$137,MONTH(DATE(YEAR(SUMMARY!$C$6),MONTH(SUMMARY!$C$6)+0,1)))/SUMIFS(DETAIL!$M$2:$M$137,DETAIL!$B$2:$B$137,$B19,DETAIL!$F$2:$F$137,MONTH(DATE(YEAR(SUMMARY!$C$6),MONTH(SUMMARY!$C$6)+0,1))))/$C$5+$C$3*(SUMIFS(DETAIL!$T$2:$T$137,DETAIL!$B$2:$B$137,$B19,DETAIL!$F$2:$F$137,MONTH(DATE(YEAR(SUMMARY!$C$6),MONTH(SUMMARY!$C$6)+0,1)))/SUMIFS(DETAIL!$M$2:$M$137,DETAIL!$B$2:$B$137,$B19,DETAIL!$F$2:$F$137,MONTH(DATE(YEAR(SUMMARY!$C$6),MONTH(SUMMARY!$C$6)+0,1))))/$C$6,"-") -> - | O19: =IFERROR($C$2*(SUMIFS(DETAIL!$R$2:$R$137,DETAIL!$B$2:$B$137,$B19,DETAIL!$F$2:$F$137,MONTH(DATE(YEAR(SUMMARY!$C$6),MONTH(SUMMARY!$C$6)+1,1)))/SUMIFS(DETAIL!$M$2:$M$137,DETAIL!$B$2:$B$137,$B19,DETAIL!$F$2:$F$137,MONTH(DATE(YEAR(SUMMARY!$C$6),MONTH(SUMMARY!$C$6)+1,1))))/$C$5+$C$3*(SUMIFS(DETAIL!$T$2:$T$137,DETAIL!$B$2:$B$137,$B19,DETAIL!$F$2:$F$137,MONTH(DATE(YEAR(SUMMARY!$C$6),MONTH(SUMMARY!$C$6)+1,1)))/SUMIFS(DETAIL!$M$2:$M$137,DETAIL!$B$2:$B$137,$B19,DETAIL!$F$2:$F$137,MONTH(DATE(YEAR(SUMMARY!$C$6),MONTH(SUMMARY!$C$6)+1,1))))/$C$6,"-") -> 0.50884862 | P19: =IFERROR($C$2*(SUMIFS(DETAIL!$R$2:$R$137,DETAIL!$B$2:$B$137,$B19,DETAIL!$F$2:$F$137,MONTH(DATE(YEAR(SUMMARY!$C$6),MONTH(SUMMARY!$C$6)+2,1)))/SUMIFS(DETAIL!$M$2:$M$137,DETAIL!$B$2:$B$137,$B19,DETAIL!$F$2:$F$137,MONTH(DATE(YEAR(SUMMARY!$C$6),MONTH(SUMMARY!$C$6)+2,1))))/$C$5+$C$3*(SUMIFS(DETAIL!$T$2:$T$137,DETAIL!$B$2:$B$137,$B19,DETAIL!$F$2:$F$137,MONTH(DATE(YEAR(SUMMARY!$C$6),MONTH(SUMMARY!$C$6)+2,1)))/SUMIFS(DETAIL!$M$2:$M$137,DETAIL!$B$2:$B$137,$B19,DETAIL!$F$2:$F$137,MONTH(DATE(YEAR(SUMMARY!$C$6),MONTH(SUMMARY!$C$6)+2,1))))/$C$6,"-") -> 0.53602694 | Q19: =IFERROR($C$2*(SUMIFS(DETAIL!$R$2:$R$137,DETAIL!$B$2:$B$137,$B19,DETAIL!$F$2:$F$137,MONTH(DATE(YEAR(SUMMARY!$C$6),MONTH(SUMMARY!$C$6)+3,1)))/SUMIFS(DETAIL!$M$2:$M$137,DETAIL!$B$2:$B$137,$B19,DETAIL!$F$2:$F$137,MONTH(DATE(YEAR(SUMMARY!$C$6),MONTH(SUMMARY!$C$6)+3,1))))/$C$5+$C$3*(SUMIFS(DETAIL!$T$2:$T$137,DETAIL!$B$2:$B$137,$B19,DETAIL!$F$2:$F$137,MONTH(DATE(YEAR(SUMMARY!$C$6),MONTH(SUMMARY!$C$6)+3,1)))/SUMIFS(DETAIL!$M$2:$M$137,DETAIL!$B$2:$B$137,$B19,DETAIL!$F$2:$F$137,MONTH(DATE(YEAR(SUMMARY!$C$6),MONTH(SUMMARY!$C$6)+3,1))))/$C$6,"-") -> 0.5189389 | R19: =IFERROR(INDEX(EVALUASI!$W$79:$W$132,MATCH($B19,EVALUASI!$C$79:$C$132,0)),"-") -> 81.4 | S19: =IFERROR(INDEX(EVALUASI!$X$79:$X$132,MATCH($B19,EVALUASI!$C$79:$C$132,0)),"-") -> Baik | T19: =J19-ROW()/1000000 -> 0.52415478
A20: 11 | B20: =PEMAGANG!C13 -> NIKEN AURELIA SAPUTRI | C20: =PEMAGANG!D13 -> DIAN RIZKA SARI | D20: =PEMAGANG!F13 -> PGS TREASURY (SID) OFFICER | E20: =SUMIFS(DETAIL!$M$2:$M$137,DETAIL!$B$2:$B$137,$B20) -> 16 | F20: =SUMIFS(DETAIL!$R$2:$R$137,DETAIL!$B$2:$B$137,$B20) -> 17 | G20: =SUMIFS(DETAIL!$T$2:$T$137,DETAIL!$B$2:$B$137,$B20) -> 377 | H20: =IFERROR(F20/E20,0) -> 1.0625 | I20: =IFERROR(G20/E20,0) -> 23.5625 | J20: =IFERROR($C$2*H20/$C$5+$C$3*I20/$C$6,0) -> 0.4186691 | K20: =MIN(1,IFERROR(J20/$C$4,0)) -> 0.4186691 | L20: =IF(E20=0,"-",IF(F20=0,"Tidak ada laporan",IF(J20>=$E$2,"Sangat Tinggi",IF(J20>=$E$3,"Tinggi",IF(J20>=$E$4,"Sedang","Rendah"))))) -> Rendah | M20: =RANK(T20,$T$10:$T$43) -> 29 | N20: =IFERROR($C$2*(SUMIFS(DETAIL!$R$2:$R$137,DETAIL!$B$2:$B$137,$B20,DETAIL!$F$2:$F$137,MONTH(DATE(YEAR(SUMMARY!$C$6),MONTH(SUMMARY!$C$6)+0,1)))/SUMIFS(DETAIL!$M$2:$M$137,DETAIL!$B$2:$B$137,$B20,DETAIL!$F$2:$F$137,MONTH(DATE(YEAR(SUMMARY!$C$6),MONTH(SUMMARY!$C$6)+0,1))))/$C$5+$C$3*(SUMIFS(DETAIL!$T$2:$T$137,DETAIL!$B$2:$B$137,$B20,DETAIL!$F$2:$F$137,MONTH(DATE(YEAR(SUMMARY!$C$6),MONTH(SUMMARY!$C$6)+0,1)))/SUMIFS(DETAIL!$M$2:$M$137,DETAIL!$B$2:$B$137,$B20,DETAIL!$F$2:$F$137,MONTH(DATE(YEAR(SUMMARY!$C$6),MONTH(SUMMARY!$C$6)+0,1))))/$C$6,"-") -> 0.4186691 | O20: =IFERROR($C$2*(SUMIFS(DETAIL!$R$2:$R$137,DETAIL!$B$2:$B$137,$B20,DETAIL!$F$2:$F$137,MONTH(DATE(YEAR(SUMMARY!$C$6),MONTH(SUMMARY!$C$6)+1,1)))/SUMIFS(DETAIL!$M$2:$M$137,DETAIL!$B$2:$B$137,$B20,DETAIL!$F$2:$F$137,MONTH(DATE(YEAR(SUMMARY!$C$6),MONTH(SUMMARY!$C$6)+1,1))))/$C$5+$C$3*(SUMIFS(DETAIL!$T$2:$T$137,DETAIL!$B$2:$B$137,$B20,DETAIL!$F$2:$F$137,MONTH(DATE(YEAR(SUMMARY!$C$6),MONTH(SUMMARY!$C$6)+1,1)))/SUMIFS(DETAIL!$M$2:$M$137,DETAIL!$B$2:$B$137,$B20,DETAIL!$F$2:$F$137,MONTH(DATE(YEAR(SUMMARY!$C$6),MONTH(SUMMARY!$C$6)+1,1))))/$C$6,"-") -> - | P20: =IFERROR($C$2*(SUMIFS(DETAIL!$R$2:$R$137,DETAIL!$B$2:$B$137,$B20,DETAIL!$F$2:$F$137,MONTH(DATE(YEAR(SUMMARY!$C$6),MONTH(SUMMARY!$C$6)+2,1)))/SUMIFS(DETAIL!$M$2:$M$137,DETAIL!$B$2:$B$137,$B20,DETAIL!$F$2:$F$137,MONTH(DATE(YEAR(SUMMARY!$C$6),MONTH(SUMMARY!$C$6)+2,1))))/$C$5+$C$3*(SUMIFS(DETAIL!$T$2:$T$137,DETAIL!$B$2:$B$137,$B20,DETAIL!$F$2:$F$137,MONTH(DATE(YEAR(SUMMARY!$C$6),MONTH(SUMMARY!$C$6)+2,1)))/SUMIFS(DETAIL!$M$2:$M$137,DETAIL!$B$2:$B$137,$B20,DETAIL!$F$2:$F$137,MONTH(DATE(YEAR(SUMMARY!$C$6),MONTH(SUMMARY!$C$6)+2,1))))/$C$6,"-") -> - | Q20: =IFERROR($C$2*(SUMIFS(DETAIL!$R$2:$R$137,DETAIL!$B$2:$B$137,$B20,DETAIL!$F$2:$F$137,MONTH(DATE(YEAR(SUMMARY!$C$6),MONTH(SUMMARY!$C$6)+3,1)))/SUMIFS(DETAIL!$M$2:$M$137,DETAIL!$B$2:$B$137,$B20,DETAIL!$F$2:$F$137,MONTH(DATE(YEAR(SUMMARY!$C$6),MONTH(SUMMARY!$C$6)+3,1))))/$C$5+$C$3*(SUMIFS(DETAIL!$T$2:$T$137,DETAIL!$B$2:$B$137,$B20,DETAIL!$F$2:$F$137,MONTH(DATE(YEAR(SUMMARY!$C$6),MONTH(SUMMARY!$C$6)+3,1)))/SUMIFS(DETAIL!$M$2:$M$137,DETAIL!$B$2:$B$137,$B20,DETAIL!$F$2:$F$137,MONTH(DATE(YEAR(SUMMARY!$C$6),MONTH(SUMMARY!$C$6)+3,1))))/$C$6,"-") -> - | R20: =IFERROR(INDEX(EVALUASI!$W$79:$W$132,MATCH($B20,EVALUASI!$C$79:$C$132,0)),"-") -> 81.3 | S20: =IFERROR(INDEX(EVALUASI!$X$79:$X$132,MATCH($B20,EVALUASI!$C$79:$C$132,0)),"-") -> Baik | T20: =J20-ROW()/1000000 -> 0.4186491
